Workbook

Sheet Budget
C1: iCACCESS 2026: Budget
C2: No of accepted Papers | D2: 97
C3: No of Registration | D3: =D2*0.9 -> 87.3
C4: No of Guests (Internal + External) | D4: 30
C5: No of Organizers (Faculty and Officer) | D5: 40
C6: No of Session Chairs | D6: =2*D3/6 -> 29.1
C7: No of Volenteers | D7: 20
C8: Media | D8: 10
C9: Dollar rate (USD to BDT) | D9: 124
C11: Expenditure | H11: Revenue
B12: Responsible | C12: Item | D12: Price per Unit | E12: No of Units | F12: Cost | H12: Item | I12: Amount
B13: Nafees Mansoor, Rokon | C13: IEEE Registration | D13: =1450*D9 -> 179800 | E13: 1 | F13: =D13*E13 -> 179800 | H13: Savings | I13: 0
B14: Nafees Mansoor, Rokon | C14: Per Paper Registration | D14: =22*D9 -> 2728 | E14: =D3 -> 87.3 | F14: =D14*E14 -> 238154.4 | H14: Regsitration (Local) | I14: =8000*D3*0.95 -> 663480
B15: Dean, SSE | C15: Bag | D15: 780 | E15: 225 | F15: =D15*E15 -> 175500 | H15: Regsitration (International) | I15: =180*D9*D3*0.05 -> 97426.8
B16: Dean, SSE | C16: Pendrive | D16: 400 | E16: 100 | F16: =D16*E16 -> 40000 | H16: Sponsor (US-DK) | I16: 50000
B17: Dean, SSE | C17: Pen and Pad | D17: 60 | E17: 150 | F17: =D17*E17 -> 9000 | H17: ULAB | I17: 100000
B18: Nazmul, Zafor, Trina | C18: Dinner | D18: 550 | E18: =0.8*(D3+D4+D5+D6+D7+20) -> 181.12 | F18: =D18*E18 -> 99616 | H18: Others (Banks) | I18: 0
B19: Dean, SSE | C19: Crest | D19: 450 | E19: =D6+0.5*D5 -> 49.1 | F19: =D19*E19 -> 22095
B20: Dean, SSE | C20: Special Crest | D20: 1400 | E20: 10 | F20: =D20*E20 -> 14000
B21: Dean, SSE | C21: ID | D21: 90 | E21: 130 | F21: =D21*E21 -> 11700
B22: Nazmul, Zafor, Trina | C22: Snacks | F22: 20000
B23: Nazmul, Zafor, Trina | C23: Lunch | D23: 200 | E23: =D3+D4+D5+D6+D7+20 -> 226.4 | F23: =D23*E23 -> 45280
B24: Dean, SSE | C24: Branding | F24: 20000
B25: Dean, SSE | C25: Printing (Banner) | F25: 30000
C26: Cultural | F26: 5000
B27: Dean, SSE, Nazmul | C27: Others (Coupons) | F27: 5000
F28: =SUM(F13:F27) -> 915145.4 | I28: =SUM(I13:I27) -> 910906.8
B29: Dean, SSE | C29: Opening ceremony
B30: Shihavuddin, Nafees Mansoor | C30: Session design and execution | H30: Surplus | I30: =I28-F28 -> -4238.6
B31: Dean, SSE | C31: General Invitation
B32: Dean, SSE | C32: Chief guest selection and invitation
B33: Dean, SSE | C33: Closing ceremony

Sheet Sessions
A1: Track | B1: Session ID | C1: Session Title | D1: Session Room
A2: Track 1: Computing and Intelligent Systems | B2: T1P1 | C2: Machine Learning Foundations and Intelligent Systems | D2: PD101
A3: Track 1: Computing and Intelligent Systems | B3: T1P2 | C3: Natural Language, Computer Vision, and Multimodal AI | D3: PD102
A4: Track 2: Wireless and Optical Communication | B4: T1P3 | C4: Wireless Networks and Optical Communication Systems | D4: PD103
A5: Track 1 & Track 5: Computing and Intelligent Systems | B5: T2P1 | C5: Cloud, Big Data, and Distributed Computing | D5: PD104
A7: Track 1: Computing and Intelligent Systems | B7: T2P2 | C7: Applied AI and Intelligent Computing Applications | D7: PD101
A9: Track 5: Digital Learning and Educational Technologies | B9: T2P3 | C9: AI-Enabled Digital Learning and Educational Technologies | D9: PD102
A10: Track 4: Smart and Cyber-Physical Systems | B10: T2P4 | C10: IoT, Embedded, and Cyber-Physical Systems | D10: PD103
A12: Track 1: Computing and Intelligent Systems | B12: T4P1 | C12: Machine Learning Applications and Data-Driven Systems | D12: https://bdren.zoom.us/j/8428351030?pwd=7kfJZ1PoRiAzd0aKSn3l28Yuta2D1P.1&omn=92475321723
A13: Track 2: Wireless and Optical Communication + Track 1: Computing and Intelligent Systems | B13: T4P2 | C13: Intelligent Communication Networks and Computing | D13: https://bdren.zoom.us/j/3426823862?pwd=qdTx7T0wafu1iseMaIbFJzZkwB20Gq.1&omn=9670458221
A14: Track 3: Electronics, Devices, and Nanotechnology + Track 1: Computing and Intelligent Systems | B14: T4P3 | C14: Electronics and Hardware for Intelligent Computing | D14: https://bdren.zoom.us/j/5012406330?pwd=czJaVXJnaHdJZlhpM21RWWF1a2hNQT09&omn=91831440282
A15: Track 1: Computing and Intelligent Systems | B15: T4P4 | C15: Cybersecurity, Blockchain, and Trustworthy Computing | D15: https://bdren.zoom.us/j/4074534482?pwd=krdtcqcqU2E4TPlssbKu9CBmk1aJre.1&omn=98496255250
... A17: Track 1: Computing and Intelligent Systems | B17: T4P6 | C17: Emerging Topics in Computing and Intelligent Systems | D17: https://meet.google.com/warndfcavc

Sheet Schedule
A1: iCACCESS 2026 (2-3 October)
A2: Schedule
A4: Day 1
A5: Time | B5: Event | C5: Venue
A6: 8:00-9:00 | B6: Registration
A7: 9:30-10:30 | B7: Opening Ceremony
A8: 10:40-11:40 | B8: Keynote Session 1
A9: 11:40-12:40 | B9: IEEE workshop - Responsible AI for Academic Research
A10: 11:40-12:40 | B10: Technical Session 1 (T1P1, T1P2, T1P3) | D10: 4x3=12
A11: 12:40-14:30 | B11: Prayer and Lunch Break
A12: 14:30-16:30 | B12: Technical Session 2 (T2P1, T2P2, T2P3, T2P4) | D12: 8x5=40
A13: 16:30-17:30 | B13: Keynote Session 2
A14: 18:30-20:30 | B14: Cultural Ceremony and Dinner
A16: Day 2
A17: Time | B17: Event | C17: Venue
A18: 11:00-13:00 | B18: Technical Session 4 (T4P1, T4P2, T4P3, T4P4, T4P5, T4P6) | C18: Online | D18: 8x6=48
A19: 14:30-15:30 | B19: Keynote Session 3 | C19: Online
A20: 18:00-19:00 | B20: Closing and Award Ceremony | C20: Online
D21: 140

Sheet Senior Faculty
A1: Name | B1: Designation | C1: Email | D1: Mobile | E1: Session 1 | F1: Assigned | G1: Session 2 | H1: Assigned | J1: Helper: Name | K1: Helper: Session Code | L1: Helper: Email | M1: Helper: Mobile | N1: Helper: Order
A2: Prof. Dr. Muhammad Golam Kibria | B2: Professor & Dean, SSE | C2: golam.kibria@ulab.edu.bd | D2: 01771122144 | E2: Keynote 2 | F2: =IF(TRIM(E2)="","No","Yes") -> Yes | H2: =IF(TRIM(G2)="","No","Yes") -> No | J2: =IF($A2="","",$A2) -> Prof. Dr. Muhammad Golam Kibria | K2: =$E2 -> Keynote 2 | L2: =IF($A2="","",$C2) -> golam.kibria@ulab.edu.bd | M2: =IF($A2="","",$D2) -> 01771122144 | N2: =IF($K2="","",COUNTIFS($K$2:$K2,$K2)) -> 1
A3: Prof. Dr. Nafees Mansoor | B3: Professor, CSE | C3: nafees.mansoor@ulab.edu.bd | D3: 01879242323 | E3: IEEE Workshop | F3: =IF(TRIM(E3)="","No","Yes") -> Yes | H3: =IF(TRIM(G3)="","No","Yes") -> No | J3: =IF($A3="","",$A3) -> Prof. Dr. Nafees Mansoor | K3: =$E3 -> IEEE Workshop | L3: =IF($A3="","",$C3) -> nafees.mansoor@ulab.edu.bd | M3: =IF($A3="","",$D3) -> 01879242323 | N3: =IF($K3="","",COUNTIFS($K$2:$K3,$K3)) -> 1
A4: Anwarul Haque Joarder | B4: Professor, CSE | C4: anwar.joarder@ulab.edu.bd | D4: 01977000805 | F4: =IF(TRIM(E4)="","No","Yes") -> No | H4: =IF(TRIM(G4)="","No","Yes") -> No | J4: =IF($A4="","",$A4) -> Anwarul Haque Joarder | K4: =$E4 | L4: =IF($A4="","",$C4) -> anwar.joarder@ulab.edu.bd | M4: =IF($A4="","",$D4) -> 01977000805 | N4: =IF($K4="","",COUNTIFS($K$2:$K4,$K4))
A5: Dr. T. M Abul Kalam Azad | B5: Associate Professor, CSE | C5: abul.kalam@ulab.edu.bd | D5: 01789379752 | E5: Keynote 1 | F5: =IF(TRIM(E5)="","No","Yes") -> Yes | H5: =IF(TRIM(G5)="","No","Yes") -> No | J5: =IF($A5="","",$A5) -> Dr. T. M Abul Kalam Azad | K5: =$E5 -> Keynote 1 | L5: =IF($A5="","",$C5) -> abul.kalam@ulab.edu.bd | M5: =IF($A5="","",$D5) -> 01789379752 | N5: =IF($K5="","",COUNTIFS($K$2:$K5,$K5)) -> 1
A6: Dr. Rezwan Al Islam Khan | B6: Associate Professor, CSE | C6: rezwan.islam@ulab.edu.bd | D6: 01712530199 | E6: T2P1 | F6: =IF(TRIM(E6)="","No","Yes") -> Yes | H6: =IF(TRIM(G6)="","No","Yes") -> No | J6: =IF($A6="","",$A6) -> Dr. Rezwan Al Islam Khan | K6: =$E6 -> T2P1 | L6: =IF($A6="","",$C6) -> rezwan.islam@ulab.edu.bd | M6: =IF($A6="","",$D6) -> 01712530199 | N6: =IF($K6="","",COUNTIFS($K$2:$K6,$K6)) -> 1
A7: Dr. Ayesha Akter Lata | B7: Assistant Professor, CSE | C7: ayesha.akter@ulab.edu.bd | D7: 01856412501 | E7: T1P1 | F7: =IF(TRIM(E7)="","No","Yes") -> Yes | G7: T4P3 | H7: =IF(TRIM(G7)="","No","Yes") -> Yes | J7: =IF($A7="","",$A7) -> Dr. Ayesha Akter Lata | K7: =$E7 -> T1P1 | L7: =IF($A7="","",$C7) -> ayesha.akter@ulab.edu.bd | M7: =IF($A7="","",$D7) -> 01856412501 | N7: =IF($K7="","",COUNTIFS($K$2:$K7,$K7)) -> 1
A8: Dr. Al Amin Sheikh | B8: Assistant Professor, CSE | C8: taskia.khatun@ulab.edu.bd | D8: 01701564663 | E8: T1P2 | F8: =IF(TRIM(E8)="","No","Yes") -> Yes | G8: T3P3 | H8: =IF(TRIM(G8)="","No","Yes") -> Yes | J8: =IF($A8="","",$A8) -> Dr. Al Amin Sheikh | K8: =$E8 -> T1P2 | L8: =IF($A8="","",$C8) -> taskia.khatun@ulab.edu.bd | M8: =IF($A8="","",$D8) -> 01701564663 | N8: =IF($K8="","",COUNTIFS($K$2:$K8,$K8)) -> 1
A9: Dr. Mst. Taskia Khatun | B9: Assistant Professor, CSE | C9: alamin.sheikh@ulab.edu.bd | D9: 01764912222 | E9: T2P2 | F9: =IF(TRIM(E9)="","No","Yes") -> Yes | H9: =IF(TRIM(G9)="","No","Yes") -> No | J9: =IF($A9="","",$A9) -> Dr. Mst. Taskia Khatun | K9: =$E9 -> T2P2 | L9: =IF($A9="","",$C9) -> alamin.sheikh@ulab.edu.bd | M9: =IF($A9="","",$D9) -> 01764912222 | N9: =IF($K9="","",COUNTIFS($K$2:$K9,$K9)) -> 1
A10: Dr. Nafiz Jaidye | B10: Assistant Professor, CSE | C10: nafiz.jaidye@ulab.edu.bd | D10: 01889121516 | E10: T2P3 | F10: =IF(TRIM(E10)="","No","Yes") -> Yes | G10: T3P5 | H10: =IF(TRIM(G10)="","No","Yes") -> Yes | J10: =IF($A10="","",$A10) -> Dr. Nafiz Jaidye | K10: =$E10 -> T2P3 | L10: =IF($A10="","",$C10) -> nafiz.jaidye@ulab.edu.bd | M10: =IF($A10="","",$D10) -> 01889121516 | N10: =IF($K10="","",COUNTIFS($K$2:$K10,$K10)) -> 1
A11: Raihan Kibria | B11: Senior Lecturer, CSE | C11: raihan.kibria@ulab.edu.bd | D11: 01819417956 | E11: T2P4 | F11: =IF(TRIM(E11)="","No","Yes") -> Yes | G11: T4P4 | H11: =IF(TRIM(G11)="","No","Yes") -> Yes | J11: =IF($A11="","",$A11) -> Raihan Kibria | K11: =$E11 -> T2P4 | L11: =IF($A11="","",$C11) -> raihan.kibria@ulab.edu.bd | M11: =IF($A11="","",$D11) -> 01819417956 | N11: =IF($K11="","",COUNTIFS($K$2:$K11,$K11)) -> 1
A12: Rubaiya Hafiz | B12: Senior Lecturer, CSE | C12: rubaiya.hafiz@ulab.edu.bd | D12: 01914194973 | E12: T3P1 | F12: =IF(TRIM(E12)="","No","Yes") -> Yes | H12: =IF(TRIM(G12)="","No","Yes") -> No | J12: =IF($A12="","",$A12) -> Rubaiya Hafiz | K12: =$E12 -> T3P1 | L12: =IF($A12="","",$C12) -> rubaiya.hafiz@ulab.edu.bd | M12: =IF($A12="","",$D12) -> 01914194973 | N12: =IF($K12="","",COUNTIFS($K$2:$K12,$K12)) -> 1
A13: Jannatul Ferdous Ruma | B13: Senior Lecturer, Course Coordinator, CSE | C13: jannatul.ferdous1@ulab.edu.bd | D13: 01710954167 | E13: T4P6 | F13: =IF(TRIM(E13)="","No","Yes") -> Yes | G13: T4P1 | H13: =IF(TRIM(G13)="","No","Yes") -> Yes | J13: =IF($A13="","",$A13) -> Jannatul Ferdous Ruma | K13: =$E13 -> T4P6 | L13: =IF($A13="","",$C13) -> jannatul.ferdous1@ulab.edu.bd | M13: =IF($A13="","",$D13) -> 01710954167 | N13: =IF($K13="","",COUNTIFS($K$2:$K13,$K13)) -> 1
A14: Dr. A.S.M. Shihavuddin | B14: Professor & HoD, EEE | C14: shihav.uddin@ulab.edu.bd | D14: 01847246426 | F14: =IF(TRIM(E14)="","No","Yes") -> No | H14: =IF(TRIM(G14)="","No","Yes") -> No | J14: =IF($A14="","",$A14) -> Dr. A.S.M. Shihavuddin | K14: =$E14 | L14: =IF($A14="","",$C14) -> shihav.uddin@ulab.edu.bd | M14: =IF($A14="","",$D14) -> 01847246426 | N14: =IF($K14="","",COUNTIFS($K$2:$K14,$K14))
A15: Ifat Al Baqee, PhD | B15: Associate Professor, EEE | C15: ifat.albaqee@ulab.edu.bd | D15: 01715135140 | E15: T4P2 | F15: =IF(TRIM(E15)="","No","Yes") -> Yes | H15: =IF(TRIM(G15)="","No","Yes") -> No | J15: =IF($A15="","",$A15) -> Ifat Al Baqee, PhD | K15: =$E15 -> T4P2 | L15: =IF($A15="","",$C15) -> ifat.albaqee@ulab.edu.bd | M15: =IF($A15="","",$D15) -> 01715135140 | N15: =IF($K15="","",COUNTIFS($K$2:$K15,$K15)) -> 1
A16: Md. Ashraful Haque, PhD | B16: Associate Professor, EEE | C16: ashraful.haque1@ulab.edu.bd | D16: 01745323543 | E16: T1P3 | F16: =IF(TRIM(E16)="","No","Yes") -> Yes | H16: =IF(TRIM(G16)="","No","Yes") -> No | J16: =IF($A16="","",$A16) -> Md. Ashraful Haque, PhD | K16: =$E16 -> T1P3 | L16: =IF($A16="","",$C16) -> ashraful.haque1@ulab.edu.bd | M16: =IF($A16="","",$D16) -> 01745323543 | N16: =IF($K16="","",COUNTIFS($K$2:$K16,$K16)) -> 1
A17: Mainul Haque | B17: Senior Lecturer, EEE | C17: mainul.haque@ulab.edu.bd | D17: 01717172837 | F17: =IF(TRIM(E17)="","No","Yes") -> No | G17: T4P5 | H17: =IF(TRIM(G17)="","No","Yes") -> Yes | J17: =IF($A17="","",$A17) -> Mainul Haque | K17: =$E17 | L17: =IF($A17="","",$C17) -> mainul.haque@ulab.edu.bd | M17: =IF($A17="","",$D17) -> 01717172837 | N17: =IF($K17="","",COUNTIFS($K$2:$K17,$K17))
F18: =IF(TRIM(E18)="","No","Yes") -> No | H18: =IF(TRIM(G18)="","No","Yes") -> No | J18: =IF($A18="","",$A18) | K18: =$E18 | L18: =IF($A18="","",$C18) | M18: =IF($A18="","",$D18) | N18: =IF($K18="","",COUNTIFS($K$2:$K18,$K18))
F19: =IF(TRIM(E19)="","No","Yes") -> No | H19: =IF(TRIM(G19)="","No","Yes") -> No | J19: =IF($A19="","",$A19) | K19: =$E19 | L19: =IF($A19="","",$C19) | M19: =IF($A19="","",$D19) | N19: =IF($K19="","",COUNTIFS($K$2:$K19,$K19))
F20: =IF(TRIM(E20)="","No","Yes") -> No | H20: =IF(TRIM(G20)="","No","Yes") -> No | J20: =IF($A20="","",$A20) | K20: =$E20 | L20: =IF($A20="","",$C20) | M20: =IF($A20="","",$D20) | N20: =IF($K20="","",COUNTIFS($K$2:$K20,$K20))
F21: =IF(TRIM(E21)="","No","Yes") -> No | H21: =IF(TRIM(G21)="","No","Yes") -> No | J21: =IF($A21="","",$A21) | K21: =$E21 | L21: =IF($A21="","",$C21) | M21: =IF($A21="","",$D21) | N21: =IF($K21="","",COUNTIFS($K$2:$K21,$K21))
F22: =IF(TRIM(E22)="","No","Yes") -> No | H22: =IF(TRIM(G22)="","No","Yes") -> No | J22: =IF($A22="","",$A22) | K22: =$E22 | L22: =IF($A22="","",$C22) | M22: =IF($A22="","",$D22) | N22: =IF($K22="","",COUNTIFS($K$2:$K22,$K22))
F23: =IF(TRIM(E23)="","No","Yes") -> No | H23: =IF(TRIM(G23)="","No","Yes") -> No | J23: =IF($A23="","",$A23) | K23: =$E23 | L23: =IF($A23="","",$C23) | M23: =IF($A23="","",$D23) | N23: =IF($K23="","",COUNTIFS($K$2:$K23,$K23))
F24: =IF(TRIM(E24)="","No","Yes") -> No | H24: =IF(TRIM(G24)="","No","Yes") -> No | J24: =IF($A24="","",$A24) | K24: =$E24 | L24: =IF($A24="","",$C24) | M24: =IF($A24="","",$D24) | N24: =IF($K24="","",COUNTIFS($K$2:$K24,$K24))
F25: =IF(TRIM(E25)="","No","Yes") -> No | H25: =IF(TRIM(G25)="","No","Yes") -> No | J25: =IF($A25="","",$A25) | K25: =$E25 | L25: =IF($A25="","",$C25) | M25: =IF($A25="","",$D25) | N25: =IF($K25="","",COUNTIFS($K$2:$K25,$K25))
F26: =IF(TRIM(E26)="","No","Yes") -> No | H26: =IF(TRIM(G26)="","No","Yes") -> No | J26: =IF($A26="","",$A26) | K26: =$E26 | L26: =IF($A26="","",$C26) | M26: =IF($A26="","",$D26) | N26: =IF($K26="","",COUNTIFS($K$2:$K26,$K26))
F27: =IF(TRIM(E27)="","No","Yes") -> No | H27: =IF(TRIM(G27)="","No","Yes") -> No | J27: =IF($A27="","",$A27) | K27: =$E27 | L27: =IF($A27="","",$C27) | M27: =IF($A27="","",$D27) | N27: =IF($K27="","",COUNTIFS($K$2:$K27,$K27))
F28: =IF(TRIM(E28)="","No","Yes") -> No | H28: =IF(TRIM(G28)="","No","Yes") -> No | J28: =IF($A28="","",$A28) | K28: =$E28 | L28: =IF($A28="","",$C28) | M28: =IF($A28="","",$D28) | N28: =IF($K28="","",COUNTIFS($K$2:$K28,$K28))
F29: =IF(TRIM(E29)="","No","Yes") -> No | H29: =IF(TRIM(G29)="","No","Yes") -> No | J29: =IF($A29="","",$A29) | K29: =$E29 | L29: =IF($A29="","",$C29) | M29: =IF($A29="","",$D29) | N29: =IF($K29="","",COUNTIFS($K$2:$K29,$K29))
... F201: =IF(TRIM(E201)="","No","Yes") -> No | H201: =IF(TRIM(G201)="","No","Yes") -> No | J201: =IF($A201="","",$A201) | K201: =$E201 | L201: =IF($A201="","",$C201) | M201: =IF($A201="","",$D201) | N201: =IF($K201="","",COUNTIFS($K$2:$K201,$K201))
J202: =IF($A2="","",$A2) -> Prof. Dr. Muhammad Golam Kibria | K202: =$G2 | L202: =IF($A2="","",$C2) -> golam.kibria@ulab.edu.bd | M202: =IF($A2="","",$D2) -> 01771122144 | N202: =IF($K202="","",COUNTIFS($K$2:$K202,$K202))
J203: =IF($A3="","",$A3) -> Prof. Dr. Nafees Mansoor | K203: =$G3 | L203: =IF($A3="","",$C3) -> nafees.mansoor@ulab.edu.bd | M203: =IF($A3="","",$D3) -> 01879242323 | N203: =IF($K203="","",COUNTIFS($K$2:$K203,$K203))
J204: =IF($A4="","",$A4) -> Anwarul Haque Joarder | K204: =$G4 | L204: =IF($A4="","",$C4) -> anwar.joarder@ulab.edu.bd | M204: =IF($A4="","",$D4) -> 01977000805 | N204: =IF($K204="","",COUNTIFS($K$2:$K204,$K204))
J205: =IF($A5="","",$A5) -> Dr. T. M Abul Kalam Azad | K205: =$G5 | L205: =IF($A5="","",$C5) -> abul.kalam@ulab.edu.bd | M205: =IF($A5="","",$D5) -> 01789379752 | N205: =IF($K205="","",COUNTIFS($K$2:$K205,$K205))
J206: =IF($A6="","",$A6) -> Dr. Rezwan Al Islam Khan | K206: =$G6 | L206: =IF($A6="","",$C6) -> rezwan.islam@ulab.edu.bd | M206: =IF($A6="","",$D6) -> 01712530199 | N206: =IF($K206="","",COUNTIFS($K$2:$K206,$K206))
J207: =IF($A7="","",$A7) -> Dr. Ayesha Akter Lata | K207: =$G7 -> T4P3 | L207: =IF($A7="","",$C7) -> ayesha.akter@ulab.edu.bd | M207: =IF($A7="","",$D7) -> 01856412501 | N207: =IF($K207="","",COUNTIFS($K$2:$K207,$K207)) -> 1
J208: =IF($A8="","",$A8) -> Dr. Al Amin Sheikh | K208: =$G8 -> T3P3 | L208: =IF($A8="","",$C8) -> taskia.khatun@ulab.edu.bd | M208: =IF($A8="","",$D8) -> 01701564663 | N208: =IF($K208="","",COUNTIFS($K$2:$K208,$K208)) -> 1
J209: =IF($A9="","",$A9) -> Dr. Mst. Taskia Khatun | K209: =$G9 | L209: =IF($A9="","",$C9) -> alamin.sheikh@ulab.edu.bd | M209: =IF($A9="","",$D9) -> 01764912222 | N209: =IF($K209="","",COUNTIFS($K$2:$K209,$K209))
J210: =IF($A10="","",$A10) -> Dr. Nafiz Jaidye | K210: =$G10 -> T3P5 | L210: =IF($A10="","",$C10) -> nafiz.jaidye@ulab.edu.bd | M210: =IF($A10="","",$D10) -> 01889121516 | N210: =IF($K210="","",COUNTIFS($K$2:$K210,$K210)) -> 1
J211: =IF($A11="","",$A11) -> Raihan Kibria | K211: =$G11 -> T4P4 | L211: =IF($A11="","",$C11) -> raihan.kibria@ulab.edu.bd | M211: =IF($A11="","",$D11) -> 01819417956 | N211: =IF($K211="","",COUNTIFS($K$2:$K211,$K211)) -> 1
J212: =IF($A12="","",$A12) -> Rubaiya Hafiz | K212: =$G12 | L212: =IF($A12="","",$C12) -> rubaiya.hafiz@ulab.edu.bd | M212: =IF($A12="","",$D12) -> 01914194973 | N212: =IF($K212="","",COUNTIFS($K$2:$K212,$K212))
J213: =IF($A13="","",$A13) -> Jannatul Ferdous Ruma | K213: =$G13 -> T4P1 | L213: =IF($A13="","",$C13) -> jannatul.ferdous1@ulab.edu.bd | M213: =IF($A13="","",$D13) -> 01710954167 | N213: =IF($K213="","",COUNTIFS($K$2:$K213,$K213)) -> 1
... J401: =IF($A201="","",$A201) | K401: =$G201 | L401: =IF($A201="","",$C201) | M401: =IF($A201="","",$D201) | N401: =IF($K401="","",COUNTIFS($K$2:$K401,$K401))

Sheet Junior Faculty
A1: Name | B1: Designation | C1: Email | D1: Mobile | E1: Session 1 | F1: Assigned | G1: Session 2 | H1: Assigned | J1: Helper: Name | K1: Helper: Session Code | L1: Helper: Email | M1: Helper: Mobile | N1: Helper: Order
A2: Suravi Akhter | B2: Lecturer, CSE | C2: suravi.akhter@ulab.edu.bd | D2: 01308395394 | E2: T1P1 | F2: =IF(TRIM(E2)="","No","Yes") -> Yes | H2: =IF(TRIM(G2)="","No","Yes") -> No | J2: =IF($A2="","",$A2) -> Suravi Akhter | K2: =$E2 -> T1P1 | L2: =IF($A2="","",$C2) -> suravi.akhter@ulab.edu.bd | M2: =IF($A2="","",$D2) -> 01308395394 | N2: =IF($K2="","",COUNTIFS($K$2:$K2,$K2)) -> 1
A3: Nazmul Abdal | B3: Lecturer, CSE | C3: nazmul.abdal@ulab.edu.bd | D3: 01752813855 | E3: T1P2 | F3: =IF(TRIM(E3)="","No","Yes") -> Yes | G3: T3P3 | H3: =IF(TRIM(G3)="","No","Yes") -> Yes | J3: =IF($A3="","",$A3) -> Nazmul Abdal | K3: =$E3 -> T1P2 | L3: =IF($A3="","",$C3) -> nazmul.abdal@ulab.edu.bd | M3: =IF($A3="","",$D3) -> 01752813855 | N3: =IF($K3="","",COUNTIFS($K$2:$K3,$K3)) -> 1
A4: Fatema Khan | B4: Lecturer, CSE | C4: fatema.khan@ulab.edu.bd | D4: 01781527079 | E4: T1P3 | F4: =IF(TRIM(E4)="","No","Yes") -> Yes | G4: T3P1 | H4: =IF(TRIM(G4)="","No","Yes") -> Yes | J4: =IF($A4="","",$A4) -> Fatema Khan | K4: =$E4 -> T1P3 | L4: =IF($A4="","",$C4) -> fatema.khan@ulab.edu.bd | M4: =IF($A4="","",$D4) -> 01781527079 | N4: =IF($K4="","",COUNTIFS($K$2:$K4,$K4)) -> 1
A5: Md Kaviul Hossain | B5: Lecturer, CSE | C5: kaviul.hossain@ulab.edu.bd | D5: 01775520904 | E5: T2P1 | F5: =IF(TRIM(E5)="","No","Yes") -> Yes | H5: =IF(TRIM(G5)="","No","Yes") -> No | J5: =IF($A5="","",$A5) -> Md Kaviul Hossain | K5: =$E5 -> T2P1 | L5: =IF($A5="","",$C5) -> kaviul.hossain@ulab.edu.bd | M5: =IF($A5="","",$D5) -> 01775520904 | N5: =IF($K5="","",COUNTIFS($K$2:$K5,$K5)) -> 1
A6: Nasir Uddin Ahmed | B6: Lecturer, CSE | C6: nasir.uddin1@ulab.edu.bd | D6: 01818009809 | E6: T2P2 | F6: =IF(TRIM(E6)="","No","Yes") -> Yes | G6: T2P4 | H6: =IF(TRIM(G6)="","No","Yes") -> Yes | J6: =IF($A6="","",$A6) -> Nasir Uddin Ahmed | K6: =$E6 -> T2P2 | L6: =IF($A6="","",$C6) -> nasir.uddin1@ulab.edu.bd | M6: =IF($A6="","",$D6) -> 01818009809 | N6: =IF($K6="","",COUNTIFS($K$2:$K6,$K6)) -> 1
A7: Wahida Ferdose Urmi | B7: Lecturer, CSE | C7: wahida.ferdose@ulab.edu.bd | D7: 01756629803 | E7: T2P3 | F7: =IF(TRIM(E7)="","No","Yes") -> Yes | G7: T2P3 | H7: =IF(TRIM(G7)="","No","Yes") -> Yes | J7: =IF($A7="","",$A7) -> Wahida Ferdose Urmi | K7: =$E7 -> T2P3 | L7: =IF($A7="","",$C7) -> wahida.ferdose@ulab.edu.bd | M7: =IF($A7="","",$D7) -> 01756629803 | N7: =IF($K7="","",COUNTIFS($K$2:$K7,$K7)) -> 1
A8: Shah Jafor Sadeek Quaderi | B8: Lecturer, CSE | C8: jafor.sadeek@ulab.edu.bd | D8: 01725828062 | E8: T2P4 | F8: =IF(TRIM(E8)="","No","Yes") -> Yes | G8: T2P2 | H8: =IF(TRIM(G8)="","No","Yes") -> Yes | J8: =IF($A8="","",$A8) -> Shah Jafor Sadeek Quaderi | K8: =$E8 -> T2P4 | L8: =IF($A8="","",$C8) -> jafor.sadeek@ulab.edu.bd | M8: =IF($A8="","",$D8) -> 01725828062 | N8: =IF($K8="","",COUNTIFS($K$2:$K8,$K8)) -> 1
A9: Dewan Ahmed Muhtasim | B9: Lecturer, CSE | C9: ahmed.muhtasim@ulab.edu.bd | D9: 01602654504 | F9: =IF(TRIM(E9)="","No","Yes") -> No | G9: T2P1 | H9: =IF(TRIM(G9)="","No","Yes") -> Yes | J9: =IF($A9="","",$A9) -> Dewan Ahmed Muhtasim | K9: =$E9 | L9: =IF($A9="","",$C9) -> ahmed.muhtasim@ulab.edu.bd | M9: =IF($A9="","",$D9) -> 01602654504 | N9: =IF($K9="","",COUNTIFS($K$2:$K9,$K9))
A10: Atanu Shuvam Roy | B10: Lecturer, CSE | C10: atanu.shuvam@ulab.edu.bd | D10: 01937545261 | E10: T3P1 | F10: =IF(TRIM(E10)="","No","Yes") -> Yes | G10: T1P3 | H10: =IF(TRIM(G10)="","No","Yes") -> Yes | J10: =IF($A10="","",$A10) -> Atanu Shuvam Roy | K10: =$E10 -> T3P1 | L10: =IF($A10="","",$C10) -> atanu.shuvam@ulab.edu.bd | M10: =IF($A10="","",$D10) -> 01937545261 | N10: =IF($K10="","",COUNTIFS($K$2:$K10,$K10)) -> 1
A11: Foysal Ahmed | B11: Lecturer, CSE | C11: foysal.ahmed@ulab.edu.bd | D11: 01632917360 | F11: =IF(TRIM(E11)="","No","Yes") -> No | G11: T1P2 | H11: =IF(TRIM(G11)="","No","Yes") -> Yes | J11: =IF($A11="","",$A11) -> Foysal Ahmed | K11: =$E11 | L11: =IF($A11="","",$C11) -> foysal.ahmed@ulab.edu.bd | M11: =IF($A11="","",$D11) -> 01632917360 | N11: =IF($K11="","",COUNTIFS($K$2:$K11,$K11))
A12: Abir Bin Yousuf | B12: Lecturer, CSE | C12: abir.yousuf@ulab.edu.bd | D12: 01628312807 | E12: T3P3 | F12: =IF(TRIM(E12)="","No","Yes") -> Yes | G12: T1P1 | H12: =IF(TRIM(G12)="","No","Yes") -> Yes | J12: =IF($A12="","",$A12) -> Abir Bin Yousuf | K12: =$E12 -> T3P3 | L12: =IF($A12="","",$C12) -> abir.yousuf@ulab.edu.bd | M12: =IF($A12="","",$D12) -> 01628312807 | N12: =IF($K12="","",COUNTIFS($K$2:$K12,$K12)) -> 1
A13: A O M Shamsuddoha | B13: Lecturer, EEE | C13: shamsud.doha@ulab.edu.bd | D13: 01982279906 | F13: =IF(TRIM(E13)="","No","Yes") -> No | G13: T4P6 | H13: =IF(TRIM(G13)="","No","Yes") -> Yes | J13: =IF($A13="","",$A13) -> A O M Shamsuddoha | K13: =$E13 | L13: =IF($A13="","",$C13) -> shamsud.doha@ulab.edu.bd | M13: =IF($A13="","",$D13) -> 01982279906 | N13: =IF($K13="","",COUNTIFS($K$2:$K13,$K13))
A14: Abdullah Md. Zobayer | B14: Lecturer, EEE | C14: abdullah.zobayer@ulab.edu.bd | D14: 01921999286 | E14: T3P5 | F14: =IF(TRIM(E14)="","No","Yes") -> Yes | G14: T4P5 | H14: =IF(TRIM(G14)="","No","Yes") -> Yes | J14: =IF($A14="","",$A14) -> Abdullah Md. Zobayer | K14: =$E14 -> T3P5 | L14: =IF($A14="","",$C14) -> abdullah.zobayer@ulab.edu.bd | M14: =IF($A14="","",$D14) -> 01921999286 | N14: =IF($K14="","",COUNTIFS($K$2:$K14,$K14)) -> 1
A15: Md. Monzurul Haque | B15: Lecturer, EEE | C15: monzurul.haque@ulab.edu.bd | D15: 01621853028 | E15: T4P1 | F15: =IF(TRIM(E15)="","No","Yes") -> Yes | G15: T4P4 | H15: =IF(TRIM(G15)="","No","Yes") -> Yes | J15: =IF($A15="","",$A15) -> Md. Monzurul Haque | K15: =$E15 -> T4P1 | L15: =IF($A15="","",$C15) -> monzurul.haque@ulab.edu.bd | M15: =IF($A15="","",$D15) -> 01621853028 | N15: =IF($K15="","",COUNTIFS($K$2:$K15,$K15)) -> 1
A16: Imran Hossain | B16: Lecturer, EEE | C16: imran.hossain3@ulab.edu.bd | D16: 01621853028 | E16: T4P2 | F16: =IF(TRIM(E16)="","No","Yes") -> Yes | G16: T4P3 | H16: =IF(TRIM(G16)="","No","Yes") -> Yes | J16: =IF($A16="","",$A16) -> Imran Hossain | K16: =$E16 -> T4P2 | L16: =IF($A16="","",$C16) -> imran.hossain3@ulab.edu.bd | M16: =IF($A16="","",$D16) -> 01621853028 | N16: =IF($K16="","",COUNTIFS($K$2:$K16,$K16)) -> 1
F17: =IF(TRIM(E17)="","No","Yes") -> No | H17: =IF(TRIM(G17)="","No","Yes") -> No | J17: =IF($A17="","",$A17) | K17: =$E17 | L17: =IF($A17="","",$C17) | M17: =IF($A17="","",$D17) | N17: =IF($K17="","",COUNTIFS($K$2:$K17,$K17))
F18: =IF(TRIM(E18)="","No","Yes") -> No | H18: =IF(TRIM(G18)="","No","Yes") -> No | J18: =IF($A18="","",$A18) | K18: =$E18 | L18: =IF($A18="","",$C18) | M18: =IF($A18="","",$D18) | N18: =IF($K18="","",COUNTIFS($K$2:$K18,$K18))
F19: =IF(TRIM(E19)="","No","Yes") -> No | H19: =IF(TRIM(G19)="","No","Yes") -> No | J19: =IF($A19="","",$A19) | K19: =$E19 | L19: =IF($A19="","",$C19) | M19: =IF($A19="","",$D19) | N19: =IF($K19="","",COUNTIFS($K$2:$K19,$K19))
F20: =IF(TRIM(E20)="","No","Yes") -> No | H20: =IF(TRIM(G20)="","No","Yes") -> No | J20: =IF($A20="","",$A20) | K20: =$E20 | L20: =IF($A20="","",$C20) | M20: =IF($A20="","",$D20) | N20: =IF($K20="","",COUNTIFS($K$2:$K20,$K20))
F21: =IF(TRIM(E21)="","No","Yes") -> No | H21: =IF(TRIM(G21)="","No","Yes") -> No | J21: =IF($A21="","",$A21) | K21: =$E21 | L21: =IF($A21="","",$C21) | M21: =IF($A21="","",$D21) | N21: =IF($K21="","",COUNTIFS($K$2:$K21,$K21))
F22: =IF(TRIM(E22)="","No","Yes") -> No | H22: =IF(TRIM(G22)="","No","Yes") -> No | J22: =IF($A22="","",$A22) | K22: =$E22 | L22: =IF($A22="","",$C22) | M22: =IF($A22="","",$D22) | N22: =IF($K22="","",COUNTIFS($K$2:$K22,$K22))
F23: =IF(TRIM(E23)="","No","Yes") -> No | H23: =IF(TRIM(G23)="","No","Yes") -> No | J23: =IF($A23="","",$A23) | K23: =$E23 | L23: =IF($A23="","",$C23) | M23: =IF($A23="","",$D23) | N23: =IF($K23="","",COUNTIFS($K$2:$K23,$K23))
F24: =IF(TRIM(E24)="","No","Yes") -> No | H24: =IF(TRIM(G24)="","No","Yes") -> No | J24: =IF($A24="","",$A24) | K24: =$E24 | L24: =IF($A24="","",$C24) | M24: =IF($A24="","",$D24) | N24: =IF($K24="","",COUNTIFS($K$2:$K24,$K24))
F25: =IF(TRIM(E25)="","No","Yes") -> No | H25: =IF(TRIM(G25)="","No","Yes") -> No | J25: =IF($A25="","",$A25) | K25: =$E25 | L25: =IF($A25="","",$C25) | M25: =IF($A25="","",$D25) | N25: =IF($K25="","",COUNTIFS($K$2:$K25,$K25))
F26: =IF(TRIM(E26)="","No","Yes") -> No | H26: =IF(TRIM(G26)="","No","Yes") -> No | J26: =IF($A26="","",$A26) | K26: =$E26 | L26: =IF($A26="","",$C26) | M26: =IF($A26="","",$D26) | N26: =IF($K26="","",COUNTIFS($K$2:$K26,$K26))
F27: =IF(TRIM(E27)="","No","Yes") -> No | H27: =IF(TRIM(G27)="","No","Yes") -> No | J27: =IF($A27="","",$A27) | K27: =$E27 | L27: =IF($A27="","",$C27) | M27: =IF($A27="","",$D27) | N27: =IF($K27="","",COUNTIFS($K$2:$K27,$K27))
F28: =IF(TRIM(E28)="","No","Yes") -> No | H28: =IF(TRIM(G28)="","No","Yes") -> No | J28: =IF($A28="","",$A28) | K28: =$E28 | L28: =IF($A28="","",$C28) | M28: =IF($A28="","",$D28) | N28: =IF($K28="","",COUNTIFS($K$2:$K28,$K28))
... F201: =IF(TRIM(E201)="","No","Yes") -> No | H201: =IF(TRIM(G201)="","No","Yes") -> No | J201: =IF($A201="","",$A201) | K201: =$E201 | L201: =IF($A201="","",$C201) | M201: =IF($A201="","",$D201) | N201: =IF($K201="","",COUNTIFS($K$2:$K201,$K201))
J202: =IF($A2="","",$A2) -> Suravi Akhter | K202: =$G2 | L202: =IF($A2="","",$C2) -> suravi.akhter@ulab.edu.bd | M202: =IF($A2="","",$D2) -> 01308395394 | N202: =IF($K202="","",COUNTIFS($K$2:$K202,$K202))
J203: =IF($A3="","",$A3) -> Nazmul Abdal | K203: =$G3 -> T3P3 | L203: =IF($A3="","",$C3) -> nazmul.abdal@ulab.edu.bd | M203: =IF($A3="","",$D3) -> 01752813855 | N203: =IF($K203="","",COUNTIFS($K$2:$K203,$K203)) -> 2
J204: =IF($A4="","",$A4) -> Fatema Khan | K204: =$G4 -> T3P1 | L204: =IF($A4="","",$C4) -> fatema.khan@ulab.edu.bd | M204: =IF($A4="","",$D4) -> 01781527079 | N204: =IF($K204="","",COUNTIFS($K$2:$K204,$K204)) -> 2
J205: =IF($A5="","",$A5) -> Md Kaviul Hossain | K205: =$G5 | L205: =IF($A5="","",$C5) -> kaviul.hossain@ulab.edu.bd | M205: =IF($A5="","",$D5) -> 01775520904 | N205: =IF($K205="","",COUNTIFS($K$2:$K205,$K205))
J206: =IF($A6="","",$A6) -> Nasir Uddin Ahmed | K206: =$G6 -> T2P4 | L206: =IF($A6="","",$C6) -> nasir.uddin1@ulab.edu.bd | M206: =IF($A6="","",$D6) -> 01818009809 | N206: =IF($K206="","",COUNTIFS($K$2:$K206,$K206)) -> 2
J207: =IF($A7="","",$A7) -> Wahida Ferdose Urmi | K207: =$G7 -> T2P3 | L207: =IF($A7="","",$C7) -> wahida.ferdose@ulab.edu.bd | M207: =IF($A7="","",$D7) -> 01756629803 | N207: =IF($K207="","",COUNTIFS($K$2:$K207,$K207)) -> 2
J208: =IF($A8="","",$A8) -> Shah Jafor Sadeek Quaderi | K208: =$G8 -> T2P2 | L208: =IF($A8="","",$C8) -> jafor.sadeek@ulab.edu.bd | M208: =IF($A8="","",$D8) -> 01725828062 | N208: =IF($K208="","",COUNTIFS($K$2:$K208,$K208)) -> 2
J209: =IF($A9="","",$A9) -> Dewan Ahmed Muhtasim | K209: =$G9 -> T2P1 | L209: =IF($A9="","",$C9) -> ahmed.muhtasim@ulab.edu.bd | M209: =IF($A9="","",$D9) -> 01602654504 | N209: =IF($K209="","",COUNTIFS($K$2:$K209,$K209)) -> 2
J210: =IF($A10="","",$A10) -> Atanu Shuvam Roy | K210: =$G10 -> T1P3 | L210: =IF($A10="","",$C10) -> atanu.shuvam@ulab.edu.bd | M210: =IF($A10="","",$D10) -> 01937545261 | N210: =IF($K210="","",COUNTIFS($K$2:$K210,$K210)) -> 2
J211: =IF($A11="","",$A11) -> Foysal Ahmed | K211: =$G11 -> T1P2 | L211: =IF($A11="","",$C11) -> foysal.ahmed@ulab.edu.bd | M211: =IF($A11="","",$D11) -> 01632917360 | N211: =IF($K211="","",COUNTIFS($K$2:$K211,$K211)) -> 2
J212: =IF($A12="","",$A12) -> Abir Bin Yousuf | K212: =$G12 -> T1P1 | L212: =IF($A12="","",$C12) -> abir.yousuf@ulab.edu.bd | M212: =IF($A12="","",$D12) -> 01628312807 | N212: =IF($K212="","",COUNTIFS($K$2:$K212,$K212)) -> 2
J213: =IF($A13="","",$A13) -> A O M Shamsuddoha | K213: =$G13 -> T4P6 | L213: =IF($A13="","",$C13) -> shamsud.doha@ulab.edu.bd | M213: =IF($A13="","",$D13) -> 01982279906 | N213: =IF($K213="","",COUNTIFS($K$2:$K213,$K213)) -> 1
... J401: =IF($A201="","",$A201) | K401: =$G201 | L401: =IF($A201="","",$C201) | M401: =IF($A201="","",$D201) | N401: =IF($K401="","",COUNTIFS($K$2:$K401,$K401))

Sheet Chairs
A1: Name | B1: Designation | C1: Email | D1: Mobile | E1: Session 1 | F1: Assigned | G1: Session 2 | H1: Assigned | J1: Helper: Name | K1: Helper: Session Code | L1: Helper: Email | M1: Helper: Mobile | N1: Helper: Order
A2: Dr. Md.Ruhul Amin | B2: Southeast University | C2: dr.mdruhulamin@seu.edu.bd | D2: 01710949921 | E2: T1P1 | F2: =IF(TRIM(E2)="","No","Yes") -> Yes | H2: =IF(TRIM(G2)="","No","Yes") -> No | J2: =IF($A2="","",$A2) -> Dr. Md.Ruhul Amin | K2: =$E2 -> T1P1 | L2: =IF($A2="","",$C2) -> dr.mdruhulamin@seu.edu.bd | M2: =IF($A2="","",$D2) -> 01710949921 | N2: =IF($K2="","",COUNTIFS($K$2:$K2,$K2)) -> 1
A3: Dr. Mohammed Ashikur Rahman | B3: Southeast Universuty | C3: ashikur.rahman@seu.edu.bd | D3: 01735524483 | E3: T2P1 | F3: =IF(TRIM(E3)="","No","Yes") -> Yes | H3: =IF(TRIM(G3)="","No","Yes") -> No | J3: =IF($A3="","",$A3) -> Dr. Mohammed Ashikur Rahman | K3: =$E3 -> T2P1 | L3: =IF($A3="","",$C3) -> ashikur.rahman@seu.edu.bd | M3: =IF($A3="","",$D3) -> 01735524483 | N3: =IF($K3="","",COUNTIFS($K$2:$K3,$K3)) -> 1
A4: Prof. Dr. Ishtiak Al Mamoon | B4: IUBAT | C4: Ishtiak.cse@iubat.edu | D4: 01713229860 | E4: T4P1 | F4: =IF(TRIM(E4)="","No","Yes") -> Yes | H4: =IF(TRIM(G4)="","No","Yes") -> No | J4: =IF($A4="","",$A4) -> Prof. Dr. Ishtiak Al Mamoon | K4: =$E4 -> T4P1 | L4: =IF($A4="","",$C4) -> Ishtiak.cse@iubat.edu | M4: =IF($A4="","",$D4) -> 01713229860 | N4: =IF($K4="","",COUNTIFS($K$2:$K4,$K4)) -> 1
A5: Prof. Dr. Ahmed Al Mansur | B5: Bangladesh University of Business and Technology (BUBT) | C5: mansur.eee@bubt.edu.bd | D5: 01715020314 | E5: T4P2 | F5: =IF(TRIM(E5)="","No","Yes") -> Yes | H5: =IF(TRIM(G5)="","No","Yes") -> No | J5: =IF($A5="","",$A5) -> Prof. Dr. Ahmed Al Mansur | K5: =$E5 -> T4P2 | L5: =IF($A5="","",$C5) -> mansur.eee@bubt.edu.bd | M5: =IF($A5="","",$D5) -> 01715020314 | N5: =IF($K5="","",COUNTIFS($K$2:$K5,$K5)) -> 1
A6: Prof. Dr. Kamruddin Nur | B6: American International University-Bangladesh | C6: kamruddin.nur@gmail.com | D6: 01777354323 | E6: T1P2 | F6: =IF(TRIM(E6)="","No","Yes") -> Yes | H6: =IF(TRIM(G6)="","No","Yes") -> No | J6: =IF($A6="","",$A6) -> Prof. Dr. Kamruddin Nur | K6: =$E6 -> T1P2 | L6: =IF($A6="","",$C6) -> kamruddin.nur@gmail.com | M6: =IF($A6="","",$D6) -> 01777354323 | N6: =IF($K6="","",COUNTIFS($K$2:$K6,$K6)) -> 1
A7: Dr. Nahid Akhter Jahan | B7: Brac University | C7: nahid.jahan@bracu.ac.bd | D7: 01828141026 | E7: T1P3 | F7: =IF(TRIM(E7)="","No","Yes") -> Yes | H7: =IF(TRIM(G7)="","No","Yes") -> No | J7: =IF($A7="","",$A7) -> Dr. Nahid Akhter Jahan | K7: =$E7 -> T1P3 | L7: =IF($A7="","",$C7) -> nahid.jahan@bracu.ac.bd | M7: =IF($A7="","",$D7) -> 01828141026 | N7: =IF($K7="","",COUNTIFS($K$2:$K7,$K7)) -> 1
A8: Dr. Mirza Rasheduzzaman | B8: BRAC University | C8: mirza.rasheduzzaman@gmail.com | D8: 01787736780 | E8: T2P4 | F8: =IF(TRIM(E8)="","No","Yes") -> Yes | H8: =IF(TRIM(G8)="","No","Yes") -> No | J8: =IF($A8="","",$A8) -> Dr. Mirza Rasheduzzaman | K8: =$E8 -> T2P4 | L8: =IF($A8="","",$C8) -> mirza.rasheduzzaman@gmail.com | M8: =IF($A8="","",$D8) -> 01787736780 | N8: =IF($K8="","",COUNTIFS($K$2:$K8,$K8)) -> 1
A9: Dr. Mohammad Rifat Ahmmad Rashid | B9: East West University | C9: rifat.rashid@ewubd.edu | D9: 01314447616 | E9: T3P3 | F9: =IF(TRIM(E9)="","No","Yes") -> Yes | H9: =IF(TRIM(G9)="","No","Yes") -> No | J9: =IF($A9="","",$A9) -> Dr. Mohammad Rifat Ahmmad Rashid | K9: =$E9 -> T3P3 | L9: =IF($A9="","",$C9) -> rifat.rashid@ewubd.edu | M9: =IF($A9="","",$D9) -> 01314447616 | N9: =IF($K9="","",COUNTIFS($K$2:$K9,$K9)) -> 1
A10: Prof. Dr. Engr. Muhibul Haque Bhuyan | B10: American International University-Bangladesh | C10: muhibulhb@aiub.edu | D10: 01815657346 | E10: T4P4 | F10: =IF(TRIM(E10)="","No","Yes") -> Yes | H10: =IF(TRIM(G10)="","No","Yes") -> No | J10: =IF($A10="","",$A10) -> Prof. Dr. Engr. Muhibul Haque Bhuyan | K10: =$E10 -> T4P4 | L10: =IF($A10="","",$C10) -> muhibulhb@aiub.edu | M10: =IF($A10="","",$D10) -> 01815657346 | N10: =IF($K10="","",COUNTIFS($K$2:$K10,$K10)) -> 1
A11: Dr. Khairul Alam | B11: Dept. of Electrical & Electronic Engineering East West University | C11: kalam@ewubd.edu | D11: 01713458911 | E11: T4P3 | F11: =IF(TRIM(E11)="","No","Yes") -> Yes | H11: =IF(TRIM(G11)="","No","Yes") -> No | J11: =IF($A11="","",$A11) -> Dr. Khairul Alam | K11: =$E11 -> T4P3 | L11: =IF($A11="","",$C11) -> kalam@ewubd.edu | M11: =IF($A11="","",$D11) -> 01713458911 | N11: =IF($K11="","",COUNTIFS($K$2:$K11,$K11)) -> 1
A12: Dr. Sifat Momen | B12: North South University | C12: sifat.momen@northsouth.edu | D12: 01754119999 | E12: T3P5 | F12: =IF(TRIM(E12)="","No","Yes") -> Yes | H12: =IF(TRIM(G12)="","No","Yes") -> No | J12: =IF($A12="","",$A12) -> Dr. Sifat Momen | K12: =$E12 -> T3P5 | L12: =IF($A12="","",$C12) -> sifat.momen@northsouth.edu | M12: =IF($A12="","",$D12) -> 01754119999 | N12: =IF($K12="","",COUNTIFS($K$2:$K12,$K12)) -> 1
A13: Dr. Mohammad Nurul Huda | B13: United International University | C13: mnh@cse.uiu.ac.bd | D13: 01673476433 | E13: T2P2 | F13: =IF(TRIM(E13)="","No","Yes") -> Yes | H13: =IF(TRIM(G13)="","No","Yes") -> No | J13: =IF($A13="","",$A13) -> Dr. Mohammad Nurul Huda | K13: =$E13 -> T2P2 | L13: =IF($A13="","",$C13) -> mnh@cse.uiu.ac.bd | M13: =IF($A13="","",$D13) -> 01673476433 | N13: =IF($K13="","",COUNTIFS($K$2:$K13,$K13)) -> 1
... A20: Dr. Anwarul Haque Joarder | B20: Professor, CSE | C20: anwar.joarder@ulab.edu.bd | D20: 01977000805 | E20: IEEE Workshop | F20: =IF(TRIM(E20)="","No","Yes") -> Yes | H20: =IF(TRIM(G20)="","No","Yes") -> No | J20: =IF($A20="","",$A20) -> Dr. Anwarul Haque Joarder | K20: =$E20 -> IEEE Workshop | L20: =IF($A20="","",$C20) -> anwar.joarder@ulab.edu.bd | M20: =IF($A20="","",$D20) -> 01977000805 | N20: =IF($K20="","",COUNTIFS($K$2:$K20,$K20)) -> 1
A21: Dr. A. B. M. Sayeed Ud Doulah | B21: Associate Professor, EEE | C21: sayeed.doulah@seu.edu.bd | F21: =IF(TRIM(E21)="","No","Yes") -> No | H21: =IF(TRIM(G21)="","No","Yes") -> No | J21: =IF($A21="","",$A21) -> Dr. A. B. M. Sayeed Ud Doulah | K21: =$E21 | L21: =IF($A21="","",$C21) -> sayeed.doulah@seu.edu.bd | M21: =IF($A21="","",$D21) | N21: =IF($K21="","",COUNTIFS($K$2:$K21,$K21))
F22: =IF(TRIM(E22)="","No","Yes") -> No | H22: =IF(TRIM(G22)="","No","Yes") -> No | J22: =IF($A22="","",$A22) | K22: =$E22 | L22: =IF($A22="","",$C22) | M22: =IF($A22="","",$D22) | N22: =IF($K22="","",COUNTIFS($K$2:$K22,$K22))
F23: =IF(TRIM(E23)="","No","Yes") -> No | H23: =IF(TRIM(G23)="","No","Yes") -> No | J23: =IF($A23="","",$A23) | K23: =$E23 | L23: =IF($A23="","",$C23) | M23: =IF($A23="","",$D23) | N23: =IF($K23="","",COUNTIFS($K$2:$K23,$K23))
F24: =IF(TRIM(E24)="","No","Yes") -> No | H24: =IF(TRIM(G24)="","No","Yes") -> No | J24: =IF($A24="","",$A24) | K24: =$E24 | L24: =IF($A24="","",$C24) | M24: =IF($A24="","",$D24) | N24: =IF($K24="","",COUNTIFS($K$2:$K24,$K24))
F25: =IF(TRIM(E25)="","No","Yes") -> No | H25: =IF(TRIM(G25)="","No","Yes") -> No | J25: =IF($A25="","",$A25) | K25: =$E25 | L25: =IF($A25="","",$C25) | M25: =IF($A25="","",$D25) | N25: =IF($K25="","",COUNTIFS($K$2:$K25,$K25))
F26: =IF(TRIM(E26)="","No","Yes") -> No | H26: =IF(TRIM(G26)="","No","Yes") -> No | J26: =IF($A26="","",$A26) | K26: =$E26 | L26: =IF($A26="","",$C26) | M26: =IF($A26="","",$D26) | N26: =IF($K26="","",COUNTIFS($K$2:$K26,$K26))
F27: =IF(TRIM(E27)="","No","Yes") -> No | H27: =IF(TRIM(G27)="","No","Yes") -> No | J27: =IF($A27="","",$A27) | K27: =$E27 | L27: =IF($A27="","",$C27) | M27: =IF($A27="","",$D27) | N27: =IF($K27="","",COUNTIFS($K$2:$K27,$K27))
F28: =IF(TRIM(E28)="","No","Yes") -> No | H28: =IF(TRIM(G28)="","No","Yes") -> No | J28: =IF($A28="","",$A28) | K28: =$E28 | L28: =IF($A28="","",$C28) | M28: =IF($A28="","",$D28) | N28: =IF($K28="","",COUNTIFS($K$2:$K28,$K28))
F29: =IF(TRIM(E29)="","No","Yes") -> No | H29: =IF(TRIM(G29)="","No","Yes") -> No | J29: =IF($A29="","",$A29) | K29: =$E29 | L29: =IF($A29="","",$C29) | M29: =IF($A29="","",$D29) | N29: =IF($K29="","",COUNTIFS($K$2:$K29,$K29))
F30: =IF(TRIM(E30)="","No","Yes") -> No | H30: =IF(TRIM(G30)="","No","Yes") -> No | J30: =IF($A30="","",$A30) | K30: =$E30 | L30: =IF($A30="","",$C30) | M30: =IF($A30="","",$D30) | N30: =IF($K30="","",COUNTIFS($K$2:$K30,$K30))
F31: =IF(TRIM(E31)="","No","Yes") -> No | H31: =IF(TRIM(G31)="","No","Yes") -> No | J31: =IF($A31="","",$A31) | K31: =$E31 | L31: =IF($A31="","",$C31) | M31: =IF($A31="","",$D31) | N31: =IF($K31="","",COUNTIFS($K$2:$K31,$K31))
F32: =IF(TRIM(E32)="","No","Yes") -> No | H32: =IF(TRIM(G32)="","No","Yes") -> No | J32: =IF($A32="","",$A32) | K32: =$E32 | L32: =IF($A32="","",$C32) | M32: =IF($A32="","",$D32) | N32: =IF($K32="","",COUNTIFS($K$2:$K32,$K32))
F33: =IF(TRIM(E33)="","No","Yes") -> No | H33: =IF(TRIM(G33)="","No","Yes") -> No | J33: =IF($A33="","",$A33) | K33: =$E33 | L33: =IF($A33="","",$C33) | M33: =IF($A33="","",$D33) | N33: =IF($K33="","",COUNTIFS($K$2:$K33,$K33))
... F159: =IF(TRIM(E159)="","No","Yes") -> No | H159: =IF(TRIM(G159)="","No","Yes") -> No | J159: =IF($A159="","",$A159) | K159: =$E159 | L159: =IF($A159="","",$C159) | M159: =IF($A159="","",$D159) | N159: =IF($K159="","",COUNTIFS($K$2:$K159,$K159))
J160: =IF(#REF!="","",#REF!) -> #REF! | K160: =#REF! -> #REF! | L160: =IF(#REF!="","",#REF!) -> #REF! | M160: =IF(#REF!="","",#REF!) -> #REF! | N160: =IF($K160="","",COUNTIFS($K$2:$K160,$K160)) -> #REF!
J161: =IF(#REF!="","",#REF!) -> #REF! | K161: =#REF! -> #REF! | L161: =IF(#REF!="","",#REF!) -> #REF! | M161: =IF(#REF!="","",#REF!) -> #REF! | N161: =IF($K161="","",COUNTIFS($K$2:$K161,$K161)) -> #REF!
J162: =IF($A2="","",$A2) -> Dr. Md.Ruhul Amin | K162: =$G2 | L162: =IF($A2="","",$C2) -> dr.mdruhulamin@seu.edu.bd | M162: =IF($A2="","",$D2) -> 01710949921 | N162: =IF($K162="","",COUNTIFS($K$2:$K162,$K162))
J163: =IF($A3="","",$A3) -> Dr. Mohammed Ashikur Rahman | K163: =$G3 | L163: =IF($A3="","",$C3) -> ashikur.rahman@seu.edu.bd | M163: =IF($A3="","",$D3) -> 01735524483 | N163: =IF($K163="","",COUNTIFS($K$2:$K163,$K163))
J164: =IF(#REF!="","",#REF!) -> #REF! | K164: =#REF! -> #REF! | L164: =IF(#REF!="","",#REF!) -> #REF! | M164: =IF(#REF!="","",#REF!) -> #REF! | N164: =IF($K164="","",COUNTIFS($K$2:$K164,$K164)) -> #REF!
J165: =IF(#REF!="","",#REF!) -> #REF! | K165: =#REF! -> #REF! | L165: =IF(#REF!="","",#REF!) -> #REF! | M165: =IF(#REF!="","",#REF!) -> #REF! | N165: =IF($K165="","",COUNTIFS($K$2:$K165,$K165)) -> #REF!
J166: =IF($A4="","",$A4) -> Prof. Dr. Ishtiak Al Mamoon | K166: =$G4 | L166: =IF($A4="","",$C4) -> Ishtiak.cse@iubat.edu | M166: =IF($A4="","",$D4) -> 01713229860 | N166: =IF($K166="","",COUNTIFS($K$2:$K166,$K166))
J167: =IF(#REF!="","",#REF!) -> #REF! | K167: =#REF! -> #REF! | L167: =IF(#REF!="","",#REF!) -> #REF! | M167: =IF(#REF!="","",#REF!) -> #REF! | N167: =IF($K167="","",COUNTIFS($K$2:$K167,$K167)) -> #REF!
J168: =IF($A5="","",$A5) -> Prof. Dr. Ahmed Al Mansur | K168: =$G5 | L168: =IF($A5="","",$C5) -> mansur.eee@bubt.edu.bd | M168: =IF($A5="","",$D5) -> 01715020314 | N168: =IF($K168="","",COUNTIFS($K$2:$K168,$K168))
J169: =IF(#REF!="","",#REF!) -> #REF! | K169: =#REF! -> #REF! | L169: =IF(#REF!="","",#REF!) -> #REF! | M169: =IF(#REF!="","",#REF!) -> #REF! | N169: =IF($K169="","",COUNTIFS($K$2:$K169,$K169)) -> #REF!
J170: =IF($A6="","",$A6) -> Prof. Dr. Kamruddin Nur | K170: =$G6 | L170: =IF($A6="","",$C6) -> kamruddin.nur@gmail.com | M170: =IF($A6="","",$D6) -> 01777354323 | N170: =IF($K170="","",COUNTIFS($K$2:$K170,$K170))
J171: =IF(#REF!="","",#REF!) -> #REF! | K171: =#REF! -> #REF! | L171: =IF(#REF!="","",#REF!) -> #REF! | M171: =IF(#REF!="","",#REF!) -> #REF! | N171: =IF($K171="","",COUNTIFS($K$2:$K171,$K171)) -> #REF!
J172: =IF(#REF!="","",#REF!) -> #REF! | K172: =#REF! -> #REF! | L172: =IF(#REF!="","",#REF!) -> #REF! | M172: =IF(#REF!="","",#REF!) -> #REF! | N172: =IF($K172="","",COUNTIFS($K$2:$K172,$K172)) -> #REF!
J173: =IF($A7="","",$A7) -> Dr. Nahid Akhter Jahan | K173: =$G7 | L173: =IF($A7="","",$C7) -> nahid.jahan@bracu.ac.bd | M173: =IF($A7="","",$D7) -> 01828141026 | N173: =IF($K173="","",COUNTIFS($K$2:$K173,$K173))
J174: =IF(#REF!="","",#REF!) -> #REF! | K174: =#REF! -> #REF! | L174: =IF(#REF!="","",#REF!) -> #REF! | M174: =IF(#REF!="","",#REF!) -> #REF! | N174: =IF($K174="","",COUNTIFS($K$2:$K174,$K174)) -> #REF!
J175: =IF(#REF!="","",#REF!) -> #REF! | K175: =#REF! -> #REF! | L175: =IF(#REF!="","",#REF!) -> #REF! | M175: =IF(#REF!="","",#REF!) -> #REF! | N175: =IF($K175="","",COUNTIFS($K$2:$K175,$K175)) -> #REF!
J176: =IF(#REF!="","",#REF!) -> #REF! | K176: =#REF! -> #REF! | L176: =IF(#REF!="","",#REF!) -> #REF! | M176: =IF(#REF!="","",#REF!) -> #REF! | N176: =IF($K176="","",COUNTIFS($K$2:$K176,$K176)) -> #REF!
J177: =IF(#REF!="","",#REF!) -> #REF! | K177: =#REF! -> #REF! | L177: =IF(#REF!="","",#REF!) -> #REF! | M177: =IF(#REF!="","",#REF!) -> #REF! | N177: =IF($K177="","",COUNTIFS($K$2:$K177,$K177)) -> #REF!
J178: =IF($A8="","",$A8) -> Dr. Mirza Rasheduzzaman | K178: =$G8 | L178: =IF($A8="","",$C8) -> mirza.rasheduzzaman@gmail.com | M178: =IF($A8="","",$D8) -> 01787736780 | N178: =IF($K178="","",COUNTIFS($K$2:$K178,$K178))
J179: =IF($A9="","",$A9) -> Dr. Mohammad Rifat Ahmmad Rashid | K179: =$G9 | L179: =IF($A9="","",$C9) -> rifat.rashid@ewubd.edu | M179: =IF($A9="","",$D9) -> 01314447616 | N179: =IF($K179="","",COUNTIFS($K$2:$K179,$K179))
J180: =IF($A10="","",$A10) -> Prof. Dr. Engr. Muhibul Haque Bhuyan | K180: =$G10 | L180: =IF($A10="","",$C10) -> muhibulhb@aiub.edu | M180: =IF($A10="","",$D10) -> 01815657346 | N180: =IF($K180="","",COUNTIFS($K$2:$K180,$K180))
J181: =IF(#REF!="","",#REF!) -> #REF! | K181: =#REF! -> #REF! | L181: =IF(#REF!="","",#REF!) -> #REF! | M181: =IF(#REF!="","",#REF!) -> #REF! | N181: =IF($K181="","",COUNTIFS($K$2:$K181,$K181)) -> #REF!
J182: =IF(#REF!="","",#REF!) -> #REF! | K182: =#REF! -> #REF! | L182: =IF(#REF!="","",#REF!) -> #REF! | M182: =IF(#REF!="","",#REF!) -> #REF! | N182: =IF($K182="","",COUNTIFS($K$2:$K182,$K182)) -> #REF!
J183: =IF(#REF!="","",#REF!) -> #REF! | K183: =#REF! -> #REF! | L183: =IF(#REF!="","",#REF!) -> #REF! | M183: =IF(#REF!="","",#REF!) -> #REF! | N183: =IF($K183="","",COUNTIFS($K$2:$K183,$K183)) -> #REF!
J184: =IF(#REF!="","",#REF!) -> #REF! | K184: =#REF! -> #REF! | L184: =IF(#REF!="","",#REF!) -> #REF! | M184: =IF(#REF!="","",#REF!) -> #REF! | N184: =IF($K184="","",COUNTIFS($K$2:$K184,$K184)) -> #REF!
J185: =IF(#REF!="","",#REF!) -> #REF! | K185: =#REF! -> #REF! | L185: =IF(#REF!="","",#REF!) -> #REF! | M185: =IF(#REF!="","",#REF!) -> #REF! | N185: =IF($K185="","",COUNTIFS($K$2:$K185,$K185)) -> #REF!
J186: =IF(#REF!="","",#REF!) -> #REF! | K186: =#REF! -> #REF! | L186: =IF(#REF!="","",#REF!) -> #REF! | M186: =IF(#REF!="","",#REF!) -> #REF! | N186: =IF($K186="","",COUNTIFS($K$2:$K186,$K186)) -> #REF!
J187: =IF(#REF!="","",#REF!) -> #REF! | K187: =#REF! -> #REF! | L187: =IF(#REF!="","",#REF!) -> #REF! | M187: =IF(#REF!="","",#REF!) -> #REF! | N187: =IF($K187="","",COUNTIFS($K$2:$K187,$K187)) -> #REF!
J188: =IF(#REF!="","",#REF!) -> #REF! | K188: =#REF! -> #REF! | L188: =IF(#REF!="","",#REF!) -> #REF! | M188: =IF(#REF!="","",#REF!) -> #REF! | N188: =IF($K188="","",COUNTIFS($K$2:$K188,$K188)) -> #REF!
J189: =IF(#REF!="","",#REF!) -> #REF! | K189: =#REF! -> #REF! | L189: =IF(#REF!="","",#REF!) -> #REF! | M189: =IF(#REF!="","",#REF!) -> #REF! | N189: =IF($K189="","",COUNTIFS($K$2:$K189,$K189)) -> #REF!
J190: =IF(#REF!="","",#REF!) -> #REF! | K190: =#REF! -> #REF! | L190: =IF(#REF!="","",#REF!) -> #REF! | M190: =IF(#REF!="","",#REF!) -> #REF! | N190: =IF($K190="","",COUNTIFS($K$2:$K190,$K190)) -> #REF!
J191: =IF(#REF!="","",#REF!) -> #REF! | K191: =#REF! -> #REF! | L191: =IF(#REF!="","",#REF!) -> #REF! | M191: =IF(#REF!="","",#REF!) -> #REF! | N191: =IF($K191="","",COUNTIFS($K$2:$K191,$K191)) -> #REF!
J192: =IF($A11="","",$A11) -> Dr. Khairul Alam | K192: =$G11 | L192: =IF($A11="","",$C11) -> kalam@ewubd.edu | M192: =IF($A11="","",$D11) -> 01713458911 | N192: =IF($K192="","",COUNTIFS($K$2:$K192,$K192))
J193: =IF(#REF!="","",#REF!) -> #REF! | K193: =#REF! -> #REF! | L193: =IF(#REF!="","",#REF!) -> #REF! | M193: =IF(#REF!="","",#REF!) -> #REF! | N193: =IF($K193="","",COUNTIFS($K$2:$K193,$K193)) -> #REF!
J194: =IF(#REF!="","",#REF!) -> #REF! | K194: =#REF! -> #REF! | L194: =IF(#REF!="","",#REF!) -> #REF! | M194: =IF(#REF!="","",#REF!) -> #REF! | N194: =IF($K194="","",COUNTIFS($K$2:$K194,$K194)) -> #REF!
J195: =IF(#REF!="","",#REF!) -> #REF! | K195: =#REF! -> #REF! | L195: =IF(#REF!="","",#REF!) -> #REF! | M195: =IF(#REF!="","",#REF!) -> #REF! | N195: =IF($K195="","",COUNTIFS($K$2:$K195,$K195)) -> #REF!
J196: =IF(#REF!="","",#REF!) -> #REF! | K196: =#REF! -> #REF! | L196: =IF(#REF!="","",#REF!) -> #REF! | M196: =IF(#REF!="","",#REF!) -> #REF! | N196: =IF($K196="","",COUNTIFS($K$2:$K196,$K196)) -> #REF!
J197: =IF(#REF!="","",#REF!) -> #REF! | K197: =#REF! -> #REF! | L197: =IF(#REF!="","",#REF!) -> #REF! | M197: =IF(#REF!="","",#REF!) -> #REF! | N197: =IF($K197="","",COUNTIFS($K$2:$K197,$K197)) -> #REF!
J198: =IF(#REF!="","",#REF!) -> #REF! | K198: =#REF! -> #REF! | L198: =IF(#REF!="","",#REF!) -> #REF! | M198: =IF(#REF!="","",#REF!) -> #REF! | N198: =IF($K198="","",COUNTIFS($K$2:$K198,$K198)) -> #REF!
J199: =IF(#REF!="","",#REF!) -> #REF! | K199: =#REF! -> #REF! | L199: =IF(#REF!="","",#REF!) -> #REF! | M199: =IF(#REF!="","",#REF!) -> #REF! | N199: =IF($K199="","",COUNTIFS($K$2:$K199,$K199)) -> #REF!
J200: =IF($A12="","",$A12) -> Dr. Sifat Momen | K200: =$G12 | L200: =IF($A12="","",$C12) -> sifat.momen@northsouth.edu | M200: =IF($A12="","",$D12) -> 01754119999 | N200: =IF($K200="","",COUNTIFS($K$2:$K200,$K200))
J201: =IF(#REF!="","",#REF!) -> #REF! | K201: =#REF! -> #REF! | L201: =IF(#REF!="","",#REF!) -> #REF! | M201: =IF(#REF!="","",#REF!) -> #REF! | N201: =IF($K201="","",COUNTIFS($K$2:$K201,$K201)) -> #REF!
J202: =IF(#REF!="","",#REF!) -> #REF! | K202: =#REF! -> #REF! | L202: =IF(#REF!="","",#REF!) -> #REF! | M202: =IF(#REF!="","",#REF!) -> #REF! | N202: =IF($K202="","",COUNTIFS($K$2:$K202,$K202)) -> #REF!
J203: =IF(#REF!="","",#REF!) -> #REF! | K203: =#REF! -> #REF! | L203: =IF(#REF!="","",#REF!) -> #REF! | M203: =IF(#REF!="","",#REF!) -> #REF! | N203: =IF($K203="","",COUNTIFS($K$2:$K203,$K203)) -> #REF!
J204: =IF(#REF!="","",#REF!) -> #REF! | K204: =#REF! -> #REF! | L204: =IF(#REF!="","",#REF!) -> #REF! | M204: =IF(#REF!="","",#REF!) -> #REF! | N204: =IF($K204="","",COUNTIFS($K$2:$K204,$K204)) -> #REF!
J205: =IF(#REF!="","",#REF!) -> #REF! | K205: =#REF! -> #REF! | L205: =IF(#REF!="","",#REF!) -> #REF! | M205: =IF(#REF!="","",#REF!) -> #REF! | N205: =IF($K205="","",COUNTIFS($K$2:$K205,$K205)) -> #REF!
J206: =IF($A13="","",$A13) -> Dr. Mohammad Nurul Huda | K206: =$G13 | L206: =IF($A13="","",$C13) -> mnh@cse.uiu.ac.bd | M206: =IF($A13="","",$D13) -> 01673476433 | N206: =IF($K206="","",COUNTIFS($K$2:$K206,$K206))
J207: =IF(#REF!="","",#REF!) -> #REF! | K207: =#REF! -> #REF! | L207: =IF(#REF!="","",#REF!) -> #REF! | M207: =IF(#REF!="","",#REF!) -> #REF! | N207: =IF($K207="","",COUNTIFS($K$2:$K207,$K207)) -> #REF!
J208: =IF(#REF!="","",#REF!) -> #REF! | K208: =#REF! -> #REF! | L208: =IF(#REF!="","",#REF!) -> #REF! | M208: =IF(#REF!="","",#REF!) -> #REF! | N208: =IF($K208="","",COUNTIFS($K$2:$K208,$K208)) -> #REF!
J209: =IF($A14="","",$A14) -> Dr. Mustafa Habib Chowdhury | K209: =$G14 | L209: =IF($A14="","",$C14) -> mchowdhury@iub.edu.bd | M209: =IF($A14="","",$D14) -> 01706635679 | N209: =IF($K209="","",COUNTIFS($K$2:$K209,$K209))
J210: =IF(#REF!="","",#REF!) -> #REF! | K210: =#REF! -> #REF! | L210: =IF(#REF!="","",#REF!) -> #REF! | M210: =IF(#REF!="","",#REF!) -> #REF! | N210: =IF($K210="","",COUNTIFS($K$2:$K210,$K210)) -> #REF!
J211: =IF(#REF!="","",#REF!) -> #REF! | K211: =#REF! -> #REF! | L211: =IF(#REF!="","",#REF!) -> #REF! | M211: =IF(#REF!="","",#REF!) -> #REF! | N211: =IF($K211="","",COUNTIFS($K$2:$K211,$K211)) -> #REF!
J212: =IF(#REF!="","",#REF!) -> #REF! | K212: =#REF! -> #REF! | L212: =IF(#REF!="","",#REF!) -> #REF! | M212: =IF(#REF!="","",#REF!) -> #REF! | N212: =IF($K212="","",COUNTIFS($K$2:$K212,$K212)) -> #REF!
J213: =IF($A15="","",$A15) -> Dr. Mohammad Shazzad Hossain | K213: =$G15 | L213: =IF($A15="","",$C15) -> shazzad.hossain@ulab.edu.bd | M213: =IF($A15="","",$D15) -> 01712030624 | N213: =IF($K213="","",COUNTIFS($K$2:$K213,$K213))
J214: =IF(#REF!="","",#REF!) -> #REF! | K214: =#REF! -> #REF! | L214: =IF(#REF!="","",#REF!) -> #REF! | M214: =IF(#REF!="","",#REF!) -> #REF! | N214: =IF($K214="","",COUNTIFS($K$2:$K214,$K214)) -> #REF!
J215: =IF(#REF!="","",#REF!) -> #REF! | K215: =#REF! -> #REF! | L215: =IF(#REF!="","",#REF!) -> #REF! | M215: =IF(#REF!="","",#REF!) -> #REF! | N215: =IF($K215="","",COUNTIFS($K$2:$K215,$K215)) -> #REF!
J216: =IF($A16="","",$A16) -> Dr. Rezwan Al Islam Khan | K216: =$G16 | L216: =IF($A16="","",$C16) -> rezwan.islam@ulab.edu.bd | M216: =IF($A16="","",$D16) -> 01712530199 | N216: =IF($K216="","",COUNTIFS($K$2:$K216,$K216))
J217: =IF($A17="","",$A17) -> Dr. Md. Ashraful Haque, PhD | K217: =$G17 | L217: =IF($A17="","",$C17) -> ashraful.haque1@ulab.edu.bd | M217: =IF($A17="","",$D17) -> 01675011109 | N217: =IF($K217="","",COUNTIFS($K$2:$K217,$K217))
J218: =IF($A18="","",$A18) -> Dr. Aminur Rahman | K218: =$G18 | L218: =IF($A18="","",$C18) -> aminur@bubt.edu.bd | M218: =IF($A18="","",$D18) -> 01716539541 | N218: =IF($K218="","",COUNTIFS($K$2:$K218,$K218))
J219: =IF($A19="","",$A19) -> Prof. Dr. Md. Shahriar Rahman | K219: =$G19 | L219: =IF($A19="","",$C19) -> mshahriar@cse.uiu.ac.bd | M219: =IF($A19="","",$D19) -> 01742092172 | N219: =IF($K219="","",COUNTIFS($K$2:$K219,$K219))
J220: =IF($A20="","",$A20) -> Dr. Anwarul Haque Joarder | K220: =$G20 | L220: =IF($A20="","",$C20) -> anwar.joarder@ulab.edu.bd | M220: =IF($A20="","",$D20) -> 01977000805 | N220: =IF($K220="","",COUNTIFS($K$2:$K220,$K220))
J221: =IF($A21="","",$A21) -> Dr. A. B. M. Sayeed Ud Doulah | K221: =$G21 | L221: =IF($A21="","",$C21) -> sayeed.doulah@seu.edu.bd | M221: =IF($A21="","",$D21) | N221: =IF($K221="","",COUNTIFS($K$2:$K221,$K221))
J222: =IF($A22="","",$A22) | K222: =$G22 | L222: =IF($A22="","",$C22) | M222: =IF($A22="","",$D22) | N222: =IF($K222="","",COUNTIFS($K$2:$K222,$K222))
J223: =IF($A23="","",$A23) | K223: =$G23 | L223: =IF($A23="","",$C23) | M223: =IF($A23="","",$D23) | N223: =IF($K223="","",COUNTIFS($K$2:$K223,$K223))
J224: =IF($A24="","",$A24) | K224: =$G24 | L224: =IF($A24="","",$C24) | M224: =IF($A24="","",$D24) | N224: =IF($K224="","",COUNTIFS($K$2:$K224,$K224))
J225: =IF($A25="","",$A25) | K225: =$G25 | L225: =IF($A25="","",$C25) | M225: =IF($A25="","",$D25) | N225: =IF($K225="","",COUNTIFS($K$2:$K225,$K225))
J226: =IF($A26="","",$A26) | K226: =$G26 | L226: =IF($A26="","",$C26) | M226: =IF($A26="","",$D26) | N226: =IF($K226="","",COUNTIFS($K$2:$K226,$K226))
J227: =IF($A27="","",$A27) | K227: =$G27 | L227: =IF($A27="","",$C27) | M227: =IF($A27="","",$D27) | N227: =IF($K227="","",COUNTIFS($K$2:$K227,$K227))
... J359: =IF($A159="","",$A159) | K359: =$G159 | L359: =IF($A159="","",$C159) | M359: =IF($A159="","",$D159) | N359: =IF($K359="","",COUNTIFS($K$2:$K359,$K359))

Sheet Papers
A1: ID | B1: Track | C1: Title | D1: Authors | E1: Emails | F1: Primary | G1: Session | H1: Assigned | I1: Order | J1: Chair Score (/50) | K1: Reviewer Score (/50) | L1: Total (/100) | M1: Rank
A2: 2 | B2: Computing | C2: Evaluating image upsampling strategies for downstream microscopy image classification | D2: Sakib Mohammad (Fairmont State University)*; Aalvee Asad Kausani (Fairmont State University); Md Noumil Tousif (Islamic University of Technology) | E2: smohammad@fairmontstate.edu; akausani@fairmontstate.edu; noumiltousif@iut-dhaka.edu | F2: smohammad@fairmontstate.edu | G2: T4P1 | H2: =IF(TRIM(G2)="","No","Yes") -> Yes | I2: =IF(TRIM(G2)="","",COUNTIFS($G$2:G2,G2)) -> 1 | J2: =IF(OR($A2="",TRIM($G2)=""),"",IFERROR(IF(INDEX(INDIRECT("'"&$G2&"'!F1:F100"),MATCH($A2,INDIRECT("'"&$G2&"'!A1:A100"),0))="","",INDEX(INDIRECT("'"&$G2&"'!F1:F100"),MATCH($A2,INDIRECT("'"&$G2&"'!A1:A100"),0))),"")) | K2: 35 | L2: =IF(COUNT(J2:K2)<2,"",J2+K2) | M2: =IF(L2="","",RANK(L2,$L$2:$L$201,0))
A3: 5 | B3: Computing | C3: A Hybrid Retrieval-Augmented Machine Learning Approach for AI-Generated Text Detection | D3: Md. Siam Ansary (Ahsanullah University of Science and Technology)*; SUMONA ISLAM ZERIN (Ahsanullah University of Science and Technology (AUST)) | E3: siamansary.aust@gmail.com; sumona.vnc@gmail.com | F3: siamansary.aust@gmail.com | G3: T4P1 | H3: =IF(TRIM(G3)="","No","Yes") -> Yes | I3: =IF(TRIM(G3)="","",COUNTIFS($G$2:G3,G3)) -> 2 | J3: =IF(OR($A3="",TRIM($G3)=""),"",IFERROR(IF(INDEX(INDIRECT("'"&$G3&"'!F1:F100"),MATCH($A3,INDIRECT("'"&$G3&"'!A1:A100"),0))="","",INDEX(INDIRECT("'"&$G3&"'!F1:F100"),MATCH($A3,INDIRECT("'"&$G3&"'!A1:A100"),0))),"")) | L3: =IF(COUNT(J3:K3)<2,"",J3+K3) | M3: =IF(L3="","",RANK(L3,$L$2:$L$201,0))
A4: 48 | B4: Computing | C4: CEC: A Non-Stationary Benchmarking Protocol for the Fair Evaluation of Metaheuristic Optimizers | D4: Hussain Mohammad Ricon (American International University-Bangladesh); Tabassum Alam (American International University-Bangladesh); Rifat Rudro (American International University-Bangladesh)*; Kamruddin Nur ( American International University-Bangladesh) | E4: 22-49911-3@student.aiub.edu; 22-49912-3@student.aiub.edu; mamun.rudro@aiub.edu; kamruddin@aiub.edu | F4: mamun.rudro@aiub.edu | G4: T4P4 | H4: =IF(TRIM(G4)="","No","Yes") -> Yes | I4: =IF(TRIM(G4)="","",COUNTIFS($G$2:G4,G4)) -> 1 | J4: =IF(OR($A4="",TRIM($G4)=""),"",IFERROR(IF(INDEX(INDIRECT("'"&$G4&"'!F1:F100"),MATCH($A4,INDIRECT("'"&$G4&"'!A1:A100"),0))="","",INDEX(INDIRECT("'"&$G4&"'!F1:F100"),MATCH($A4,INDIRECT("'"&$G4&"'!A1:A100"),0))),"")) | K4: 40 | L4: =IF(COUNT(J4:K4)<2,"",J4+K4) | M4: =IF(L4="","",RANK(L4,$L$2:$L$201,0))
A5: 49 | B5: Computing | C5: SPPC: Benchmarking Selenium, Playwright, Puppeteer, and Cypress for Energy-Efficient Web Automation | D5: MD. Zihaul Islam Zihan (American International University-Bangladesh); Al Israfil Niloy ( American International University-Bangladesh); Raid Ibney Hasan Arnob (American International University-Bangladesh); Rifat Rudro (American International University-Bangladesh)*; Kamruddin Nur (American International University-Bangladesh) | E5: 22-49229-3@student.aiub.edu; 22-49033-3@student.aiub.edu; 22-48357-3@student.aiub.edu; mamun.rudro@aiub.edu; kamruddin@aiub.edu | F5: mamun.rudro@aiub.edu | G5: T1P1 | H5: =IF(TRIM(G5)="","No","Yes") -> Yes | I5: =IF(TRIM(G5)="","",COUNTIFS($G$2:G5,G5)) -> 1 | J5: =IF(OR($A5="",TRIM($G5)=""),"",IFERROR(IF(INDEX(INDIRECT("'"&$G5&"'!F1:F100"),MATCH($A5,INDIRECT("'"&$G5&"'!A1:A100"),0))="","",INDEX(INDIRECT("'"&$G5&"'!F1:F100"),MATCH($A5,INDIRECT("'"&$G5&"'!A1:A100"),0))),"")) | L5: =IF(COUNT(J5:K5)<2,"",J5+K5) | M5: =IF(L5="","",RANK(L5,$L$2:$L$201,0))
A6: 58 | B6: Computing | C6: Explainable Machine Learning for Cross-Species Myeloid Biomarker Discovery in Glioblastoma | D6: MD Himel Kabir (American International University-Bangladesh); Shanjida Sultana (American International University-Bangladesh); MD Salauddin (American International University-Bangladesh); Rifat Rudro (American International University-Bangladesh)*; Kamruddin Nur (American International University-Bangladesh) | E6: 23-51481-1@student.aiub.edu; 23-51519-1@student.aiub.edu; 23-51479-1@student.aiub.edu; mamun.rudro@aiub.edu; kamruddin@aiub.edu | F6: mamun.rudro@aiub.edu | G6: T1P1 | H6: =IF(TRIM(G6)="","No","Yes") -> Yes | I6: =IF(TRIM(G6)="","",COUNTIFS($G$2:G6,G6)) -> 2 | J6: =IF(OR($A6="",TRIM($G6)=""),"",IFERROR(IF(INDEX(INDIRECT("'"&$G6&"'!F1:F100"),MATCH($A6,INDIRECT("'"&$G6&"'!A1:A100"),0))="","",INDEX(INDIRECT("'"&$G6&"'!F1:F100"),MATCH($A6,INDIRECT("'"&$G6&"'!A1:A100"),0))),"")) | L6: =IF(COUNT(J6:K6)<2,"",J6+K6) | M6: =IF(L6="","",RANK(L6,$L$2:$L$201,0))
A7: 59 | B7: Computing | C7: An Explainable Lightweight CBAM-CNN with Focal Loss for Brain Tumor MRI Classification | D7: Saiful Islam (American International University-Bangladesh); Safin Rahatil Tanim (American International University-Bangladesh); Kazi Tanvir (Universiti Kebangsaan Malaysia(UKM)); Kamruddin Nur (American International University-Bangladesh)* | E7: 22-47027-1@student.aiub.edu; 22-48551-3@student.aiub.edu; p170862@siswa.ukm.edu.my; kamruddin@aiub.edu | F7: kamruddin@aiub.edu | G7: T4P1 | H7: =IF(TRIM(G7)="","No","Yes") -> Yes | I7: =IF(TRIM(G7)="","",COUNTIFS($G$2:G7,G7)) -> 3 | J7: =IF(OR($A7="",TRIM($G7)=""),"",IFERROR(IF(INDEX(INDIRECT("'"&$G7&"'!F1:F100"),MATCH($A7,INDIRECT("'"&$G7&"'!A1:A100"),0))="","",INDEX(INDIRECT("'"&$G7&"'!F1:F100"),MATCH($A7,INDIRECT("'"&$G7&"'!A1:A100"),0))),"")) | L7: =IF(COUNT(J7:K7)<2,"",J7+K7) | M7: =IF(L7="","",RANK(L7,$L$2:$L$201,0))
A8: 61 | B8: Computing | C8: Beyond Fragmentation: A Causal Analysis of Unicode NFKC Normalization Effects in Dialectal Bengali NER | D8: Touhidur Rahman (American International University-Bangladesh); Alif Bin Islam (American International University-Bangladesh); Kazi Tanvir (Universiti Kebangsaan Malaysia(UKM)); Kamruddin Nur (American International University-Bangladesh)* | E8: 22-49381-3@student.aiub.edu; 22-49382-3@student.aiub.edu; p170862@siswa.ukm.edu.my; kamruddin@aiub.edu | F8: kamruddin@aiub.edu | G8: T2P1 | H8: =IF(TRIM(G8)="","No","Yes") -> Yes | I8: =IF(TRIM(G8)="","",COUNTIFS($G$2:G8,G8)) -> 1 | J8: =IF(OR($A8="",TRIM($G8)=""),"",IFERROR(IF(INDEX(INDIRECT("'"&$G8&"'!F1:F100"),MATCH($A8,INDIRECT("'"&$G8&"'!A1:A100"),0))="","",INDEX(INDIRECT("'"&$G8&"'!F1:F100"),MATCH($A8,INDIRECT("'"&$G8&"'!A1:A100"),0))),"")) -> 30 | L8: =IF(COUNT(J8:K8)<2,"",J8+K8) | M8: =IF(L8="","",RANK(L8,$L$2:$L$201,0))
A9: 64 | B9: Computing | C9: An Explainable Ensemble Learning Approach for Anemia Prediction Using Clinical and Biochemical Data | D9: Gulfame Jannat (American International University Bangladesh); MD. Toky Tajwer Mahin (American International University Bangladesh); MD. Sohanur Rahman Shohan ( American International University Bangladesh); Muhtasin Ifti (American International University Bangladesh); Aminun Nahar (American International University Bangladesh)*; Kamruddin Nur (American International University Bangladesh) | E9: 23-50293-1@student.aiub.edu; 22-48934-3@student.aiub.edu; 20-43672-2@student.aiub.edu; 23-50249-1@student.aiub.edu; aminun.nahar@aiub.edu; kamruddin@aiub.edu | F9: aminun.nahar@aiub.edu | G9: T4P4 | H9: =IF(TRIM(G9)="","No","Yes") -> Yes | I9: =IF(TRIM(G9)="","",COUNTIFS($G$2:G9,G9)) -> 2 | J9: =IF(OR($A9="",TRIM($G9)=""),"",IFERROR(IF(INDEX(INDIRECT("'"&$G9&"'!F1:F100"),MATCH($A9,INDIRECT("'"&$G9&"'!A1:A100"),0))="","",INDEX(INDIRECT("'"&$G9&"'!F1:F100"),MATCH($A9,INDIRECT("'"&$G9&"'!A1:A100"),0))),"")) | L9: =IF(COUNT(J9:K9)<2,"",J9+K9) | M9: =IF(L9="","",RANK(L9,$L$2:$L$201,0))
A10: 66 | B10: Computing | C10: Interpretable Psoriatic Lesion Classification via Multi-Cohort Gene Expression Profiling | D10: Shah Salehin Siddique Raduan (American International University-Bangladesh); Rayena Rahman (American International University-Bangladesh); Kamrun Nahar Sumaiya (American International University-Bangladesh); Kazi Tanvir (Universiti Kebangsaan Malaysia(UKM)); Kamruddin Nur (American International University-Bangladesh)* | E10: 23-52038-2@student.aiub.edu; 23-52055-2@student.aiub.edu; 23-52047-2@student.aiub.edu; p170862@siswa.ukm.edu.my; kamruddin@aiub.edu | F10: kamruddin@aiub.edu | G10: T2P1 | H10: =IF(TRIM(G10)="","No","Yes") -> Yes | I10: =IF(TRIM(G10)="","",COUNTIFS($G$2:G10,G10)) -> 2 | J10: =IF(OR($A10="",TRIM($G10)=""),"",IFERROR(IF(INDEX(INDIRECT("'"&$G10&"'!F1:F100"),MATCH($A10,INDIRECT("'"&$G10&"'!A1:A100"),0))="","",INDEX(INDIRECT("'"&$G10&"'!F1:F100"),MATCH($A10,INDIRECT("'"&$G10&"'!A1:A100"),0))),"")) | L10: =IF(COUNT(J10:K10)<2,"",J10+K10) | M10: =IF(L10="","",RANK(L10,$L$2:$L$201,0))
A11: 79 | B11: Computing | C11: Dual-Input ConvNeXt with Spatial Cross-Attention for Colonoscopy Mayo Scoring | D11: Md. Mamun Hossain ( Khwaja Yunus Ali University); Md.Abu Raihan ( Khwaja Yunus Ali University); Jarziz Ahmed ( Khwaja Yunus Ali University); F M Javed Mehedi Shamrat (Khwaja Yunus Ali University)*; Md. Asraf Ali (Khwaja Yunus Ali University) | E11: muhammed.mamun.131@gmail.com; raihan.cse@kyau.edu.bd; jarzizcse13th.kyau@gmail.com; shamrat.cse@kyau.edu.bd; asrafali@kyau.edu.bd | F11: shamrat.cse@kyau.edu.bd | G11: T4P6 | H11: =IF(TRIM(G11)="","No","Yes") -> Yes | I11: =IF(TRIM(G11)="","",COUNTIFS($G$2:G11,G11)) -> 1 | J11: =IF(OR($A11="",TRIM($G11)=""),"",IFERROR(IF(INDEX(INDIRECT("'"&$G11&"'!F1:F100"),MATCH($A11,INDIRECT("'"&$G11&"'!A1:A100"),0))="","",INDEX(INDIRECT("'"&$G11&"'!F1:F100"),MATCH($A11,INDIRECT("'"&$G11&"'!A1:A100"),0))),"")) | L11: =IF(COUNT(J11:K11)<2,"",J11+K11) | M11: =IF(L11="","",RANK(L11,$L$2:$L$201,0))
A12: 86 | B12: Computing | C12: DCAF-Net: Dual-Branch Convolutional Network with Spatial Cross-Attention Fusion for Thyroid Nodule Classification | D12: Syed Muntasin Fayaz (Khwaja Yunus Ali University); F M Javed Mehedi Shamrat (Khwaja Yunus Ali University)*; Md.Abu Raihan ( Khwaja Yunus Ali University); MD. Asraf Ali (Khwaja Yunus Ali University) | E12: muntasinfayaz@gmail.com; shamrat.cse@kyau.edu.bd; raihan.cse@kyau.edu.bd; asrafali@kyau.edu.bd | F12: shamrat.cse@kyau.edu.bd | G12: T4P4 | H12: =IF(TRIM(G12)="","No","Yes") -> Yes | I12: =IF(TRIM(G12)="","",COUNTIFS($G$2:G12,G12)) -> 3 | J12: =IF(OR($A12="",TRIM($G12)=""),"",IFERROR(IF(INDEX(INDIRECT("'"&$G12&"'!F1:F100"),MATCH($A12,INDIRECT("'"&$G12&"'!A1:A100"),0))="","",INDEX(INDIRECT("'"&$G12&"'!F1:F100"),MATCH($A12,INDIRECT("'"&$G12&"'!A1:A100"),0))),"")) | L12: =IF(COUNT(J12:K12)<2,"",J12+K12) | M12: =IF(L12="","",RANK(L12,$L$2:$L$201,0))
A13: 94 | B13: Computing | C13: TaxNet-Bangladesh: Building a Domain-Specific Tax Question-Answering System for Businesses in Bangladesh | D13: Raihan Kibria (University of Liberal Arts Bangladesh)*; Noshin Tabassum (University of Liberal Arts Bangladesh); Md. Nadimul Islam (University of Liberal Arts Bangladesh); Jannatul Ferdous Badhon (University of Liberal Arts Bangladesh); Monira Akter (University of Liberal Arts Bangladesh); MD KAVIUL HOSSAIN (University of Liberal Arts Bangladesh) | E13: raihan.kibria@ulab.edu.bd; noshin.tabassum.cse@ulab.edu.bd; nadimul.islam.cse@ulab.edu.bd; jannatul.ferdous3.cse@ulab.edu.bd; monira.akter.cse@ulab.edu.bd; kaviul.hossain@ulab.edu.bd | F13: raihan.kibria@ulab.edu.bd | G13: T1P2 | H13: =IF(TRIM(G13)="","No","Yes") -> Yes | I13: =IF(TRIM(G13)="","",COUNTIFS($G$2:G13,G13)) -> 1 | J13: =IF(OR($A13="",TRIM($G13)=""),"",IFERROR(IF(INDEX(INDIRECT("'"&$G13&"'!F1:F100"),MATCH($A13,INDIRECT("'"&$G13&"'!A1:A100"),0))="","",INDEX(INDIRECT("'"&$G13&"'!F1:F100"),MATCH($A13,INDIRECT("'"&$G13&"'!A1:A100"),0))),"")) | L13: =IF(COUNT(J13:K13)<2,"",J13+K13) | M13: =IF(L13="","",RANK(L13,$L$2:$L$201,0))
A14: 95 | B14: Computing | C14: MpoxFusionNet: Privacy-Aware Hybrid CNN-Transformer Fusion for Monkeypox Detection from Skin Lesion Images | D14: Anika Sarker Emo ( Khwaja Yunus Ali University); Shimanto Kumar ( Khwaja Yunus Ali University); F M Javed Mehedi Shamrat (Khwaja Yunus Ali University)*; Rashiduzzaman Shakil (Daffodil International University); Bonna Akter (University of Texas Rio Grande Valley); Md. Asraf Ali (Khwaja Yunus Ali University) | E14: anikaimo387@gmail.com; kshimanto70@gmail.com; shamrat.cse@kyau.edu.bd; rashiduzzaman.diucse@gmail.com; bonna.akter01@utrgv.edu; asrafali@kyau.edu.bd | F14: shamrat.cse@kyau.edu.bd | G14: T2P4 | H14: =IF(TRIM(G14)="","No","Yes") -> Yes | I14: =IF(TRIM(G14)="","",COUNTIFS($G$2:G14,G14)) -> 1 | J14: =IF(OR($A14="",TRIM($G14)=""),"",IFERROR(IF(INDEX(INDIRECT("'"&$G14&"'!F1:F100"),MATCH($A14,INDIRECT("'"&$G14&"'!A1:A100"),0))="","",INDEX(INDIRECT("'"&$G14&"'!F1:F100"),MATCH($A14,INDIRECT("'"&$G14&"'!A1:A100"),0))),"")) | L14: =IF(COUNT(J14:K14)<2,"",J14+K14) | M14: =IF(L14="","",RANK(L14,$L$2:$L$201,0))
A15: 100 | B15: Computing | C15: Multi-Task Swin Transformer for Automated Pneumonia Detection and Subtype Classification from Pediatric Chest X-Ray Images | D15: Md.Mahbubur Rahman (Patuakhali Science & Technology University); Pritha Kar (Patuakhali Science & Technology University )*; Romaiya Rechi ( Patuakhali Science & Technology University); Kaberi Chaki (Patuakhali Science & Technology University); Chinmay Bepery (Patuakhali Science & Technology University); Md. Atikqur Rahaman (Patuakhali Science & Technology University); Sarna Majumder (Patuakhali Science & Technology University) | E15: mahbub.cse@pstu.ac.bd; pritha18@cse.pstu.ac.bd; rechi18@cse.pstu.ac.bd; kaberi18@cse.pstu.ac.bd; chinmay.cse@pstu.ac.bd; atik.csit@pstu.ac.bd; saran.majumder90@gmail.com | F15: pritha18@cse.pstu.ac.bd | H15: =IF(TRIM(G15)="","No","Yes") -> No | I15: =IF(TRIM(G15)="","",COUNTIFS($G$2:G15,G15)) | J15: =IF(OR($A15="",TRIM($G15)=""),"",IFERROR(IF(INDEX(INDIRECT("'"&$G15&"'!F1:F100"),MATCH($A15,INDIRECT("'"&$G15&"'!A1:A100"),0))="","",INDEX(INDIRECT("'"&$G15&"'!F1:F100"),MATCH($A15,INDIRECT("'"&$G15&"'!A1:A100"),0))),"")) | L15: =IF(COUNT(J15:K15)<2,"",J15+K15) | M15: =IF(L15="","",RANK(L15,$L$2:$L$201,0))
A16: 104 | B16: Computing | C16: Quantum Machine Learning for Voice Pathology Detection: A Comparative Study with Classical Machine Learning and 1D-CNN Models | D16: Uttam Mahapatra (Uttara University)*; Md. Mehedi Hasan Tusar (Uttara University); Md Maniruz Zaman (Uttara University); Jiad Bin Asad (Uttara University); Md. Shamsul Islam (Uttara University); Amit Das (Uttara University) | E16: uttammahapatra211@gmail.com; its.mehedi.eee@gmail.com; mmzaman.ruet@gmail.com; jiadbinasad@gmail.com; islamshamsul127@gmail.com; amit.das.ruet@gmail.com | F16: uttammahapatra211@gmail.com | H16: =IF(TRIM(G16)="","No","Yes") -> No | I16: =IF(TRIM(G16)="","",COUNTIFS($G$2:G16,G16)) | J16: =IF(OR($A16="",TRIM($G16)=""),"",IFERROR(IF(INDEX(INDIRECT("'"&$G16&"'!F1:F100"),MATCH($A16,INDIRECT("'"&$G16&"'!A1:A100"),0))="","",INDEX(INDIRECT("'"&$G16&"'!F1:F100"),MATCH($A16,INDIRECT("'"&$G16&"'!A1:A100"),0))),"")) | L16: =IF(COUNT(J16:K16)<2,"",J16+K16) | M16: =IF(L16="","",RANK(L16,$L$2:$L$201,0))
A17: 124 | B17: Computing | C17: HybridOsteoX: A Knee Osteoporosis Explainable AI Framework Using Hybrid CNN-ViT Fusion | D17: Zarin Tasnim Rahman Tarin (North South University); Nawar Nooren Orpa (North South University)*; Sifat Momen (North South University) | E17: zarin.tarin@northsouth.edu; nawar.orpa@northsouth.edu; sifat.momen@northsouth.edu | F17: nawar.orpa@northsouth.edu | G17: T2P2 | H17: =IF(TRIM(G17)="","No","Yes") -> Yes | I17: =IF(TRIM(G17)="","",COUNTIFS($G$2:G17,G17)) -> 1 | J17: =IF(OR($A17="",TRIM($G17)=""),"",IFERROR(IF(INDEX(INDIRECT("'"&$G17&"'!F1:F100"),MATCH($A17,INDIRECT("'"&$G17&"'!A1:A100"),0))="","",INDEX(INDIRECT("'"&$G17&"'!F1:F100"),MATCH($A17,INDIRECT("'"&$G17&"'!A1:A100"),0))),"")) | L17: =IF(COUNT(J17:K17)<2,"",J17+K17) | M17: =IF(L17="","",RANK(L17,$L$2:$L$201,0))
A18: 127 | B18: Computing | C18: BanglaRhet: Benchmarking Classical and Transformer Models for Rhetorical and Persuasion Detection in Bangla Political Speech | D18: Rohit Kumar Sen (North East University Bangladesh)*; Anik Chowdhury (North East University Bangladesh) | E18: rohit.k.sen.neub@gmail.com; anikchowdhuryraj.neub@gmail.com | F18: rohit.k.sen.neub@gmail.com | G18: T2P2 | H18: =IF(TRIM(G18)="","No","Yes") -> Yes | I18: =IF(TRIM(G18)="","",COUNTIFS($G$2:G18,G18)) -> 2 | J18: =IF(OR($A18="",TRIM($G18)=""),"",IFERROR(IF(INDEX(INDIRECT("'"&$G18&"'!F1:F100"),MATCH($A18,INDIRECT("'"&$G18&"'!A1:A100"),0))="","",INDEX(INDIRECT("'"&$G18&"'!F1:F100"),MATCH($A18,INDIRECT("'"&$G18&"'!A1:A100"),0))),"")) | L18: =IF(COUNT(J18:K18)<2,"",J18+K18) | M18: =IF(L18="","",RANK(L18,$L$2:$L$201,0))
A19: 135 | B19: Computing | C19: FairHireATS: An Intersectional Bias Detection and Mitigation Framework for Automated Resume Screening | D19: Fahmida Salma (Sylhet Engineering College)*; Fariha Zarin (Sylhet Engineering College); Zarin Chowdhury (Sylhet Engineering College); Md. Lysuzzaman (Sylhet Engineering College) | E19: fahmidasalma071@sec.ac.bd; farihazrn@sec.ac.bd; ztasnim263@sec.ac.bd; l.zaman.cse@sec.ac.bd | F19: fahmidasalma071@sec.ac.bd | G19: T4P6 | H19: =IF(TRIM(G19)="","No","Yes") -> Yes | I19: =IF(TRIM(G19)="","",COUNTIFS($G$2:G19,G19)) -> 2 | J19: =IF(OR($A19="",TRIM($G19)=""),"",IFERROR(IF(INDEX(INDIRECT("'"&$G19&"'!F1:F100"),MATCH($A19,INDIRECT("'"&$G19&"'!A1:A100"),0))="","",INDEX(INDIRECT("'"&$G19&"'!F1:F100"),MATCH($A19,INDIRECT("'"&$G19&"'!A1:A100"),0))),"")) | L19: =IF(COUNT(J19:K19)<2,"",J19+K19) | M19: =IF(L19="","",RANK(L19,$L$2:$L$201,0))
A20: 138 | B20: Computing | C20: HalluciNet: A Multi-Granularity Contrastive Framework for Factual Hallucination Detection in Large Language Models | D20: Md. Siam Ansary (Ahsanullah University of Science and Technology)*; SUMONA ISLAM ZERIN (Ahsanullah University of Science and Technology) | E20: siamansary.aust@gmail.com; sumona.vnc@gmail.com | F20: siamansary.aust@gmail.com | G20: T4P1 | H20: =IF(TRIM(G20)="","No","Yes") -> Yes | I20: =IF(TRIM(G20)="","",COUNTIFS($G$2:G20,G20)) -> 4 | J20: =IF(OR($A20="",TRIM($G20)=""),"",IFERROR(IF(INDEX(INDIRECT("'"&$G20&"'!F1:F100"),MATCH($A20,INDIRECT("'"&$G20&"'!A1:A100"),0))="","",INDEX(INDIRECT("'"&$G20&"'!F1:F100"),MATCH($A20,INDIRECT("'"&$G20&"'!A1:A100"),0))),"")) | L20: =IF(COUNT(J20:K20)<2,"",J20+K20) | M20: =IF(L20="","",RANK(L20,$L$2:$L$201,0))
A21: 147 | B21: Computing | C21: SplitSeg: Generalizable Skin Lesion Segmentation with ResNeSt-UNet | D21: Saalim Araf (North South University)*; Khurshed . (North South University); Shaheer Shamsi (North South University); Saiba Adnan (North South University); Sifat Momen (North South University) | E21: saalim.araf@northsouth.edu; khurshed@northsouth.edu; shaheer.shamsi@northsouth.edu; saiba.adnan@northsouth.edu; sifat.momen@northsouth.edu | F21: saalim.araf@northsouth.edu | G21: T2P2 | H21: =IF(TRIM(G21)="","No","Yes") -> Yes | I21: =IF(TRIM(G21)="","",COUNTIFS($G$2:G21,G21)) -> 3 | J21: =IF(OR($A21="",TRIM($G21)=""),"",IFERROR(IF(INDEX(INDIRECT("'"&$G21&"'!F1:F100"),MATCH($A21,INDIRECT("'"&$G21&"'!A1:A100"),0))="","",INDEX(INDIRECT("'"&$G21&"'!F1:F100"),MATCH($A21,INDIRECT("'"&$G21&"'!A1:A100"),0))),"")) | L21: =IF(COUNT(J21:K21)<2,"",J21+K21) | M21: =IF(L21="","",RANK(L21,$L$2:$L$201,0))
A22: 162 | B22: Computing | C22: Distributed Transformer Inference for Sentiment Analysis: An HTCondor and DAGMan-Based Workflow Approach on AWS | D22: MD KAVIUL HOSSAIN (University of Liberal Arts Bangladesh); Nasir Uddin Ahmed (University of Liberal Arts Bangladesh)*; Fatema Khan (University of Liberal Arts Bangladesh) | E22: kaviul.hossain@ulab.edu.bd; nasir.uddin1@ulab.edu.bd; fatema.khan@ulab.edu.bd | F22: nasir.uddin1@ulab.edu.bd | G22: T1P2 | H22: =IF(TRIM(G22)="","No","Yes") -> Yes | I22: =IF(TRIM(G22)="","",COUNTIFS($G$2:G22,G22)) -> 2 | J22: =IF(OR($A22="",TRIM($G22)=""),"",IFERROR(IF(INDEX(INDIRECT("'"&$G22&"'!F1:F100"),MATCH($A22,INDIRECT("'"&$G22&"'!A1:A100"),0))="","",INDEX(INDIRECT("'"&$G22&"'!F1:F100"),MATCH($A22,INDIRECT("'"&$G22&"'!A1:A100"),0))),"")) | L22: =IF(COUNT(J22:K22)<2,"",J22+K22) | M22: =IF(L22="","",RANK(L22,$L$2:$L$201,0))
A23: 166 | B23: Computing | C23: Explainable Machine Learning and Country-Level Trade Segmentation for Global Electric Vehicle Trade | D23: Tashida Yeasmin (Atish Dipankar University of Science & Technology)*; Ismot Ara (Atish Dipankar University of Science & Technology) | E23: tashida@adust.edu.bd; ismot.ara@adust.edu.bd | F23: tashida@adust.edu.bd | G23: T4P6 | H23: =IF(TRIM(G23)="","No","Yes") -> Yes | I23: =IF(TRIM(G23)="","",COUNTIFS($G$2:G23,G23)) -> 3 | J23: =IF(OR($A23="",TRIM($G23)=""),"",IFERROR(IF(INDEX(INDIRECT("'"&$G23&"'!F1:F100"),MATCH($A23,INDIRECT("'"&$G23&"'!A1:A100"),0))="","",INDEX(INDIRECT("'"&$G23&"'!F1:F100"),MATCH($A23,INDIRECT("'"&$G23&"'!A1:A100"),0))),"")) | L23: =IF(COUNT(J23:K23)<2,"",J23+K23) | M23: =IF(L23="","",RANK(L23,$L$2:$L$201,0))
A24: 167 | B24: Computing | C24: Linux Malware Detection using API Call Graphs with Graph2Vec and GraphSAGE Model | D24: Sadman Chowdhury (Daffodil International University); Mohammad Sarwar Hossain Mollah (Daffodil International University)*; MD. RUHUL KUDDUS (Daffodil International University); Rakibul Hasan Nirob (Daffodil International University); Sanjana Noor Disha (Daffodil International University) | E24: chowdhury16-662@s.diu.edu.bd; headcis@daffodilvarsity.edu.bd; ruhul16-555@diu.edu.bd; nirob16-615@diu.edu.bd; disha2312091002@diu.edu.bd | F24: headcis@daffodilvarsity.edu.bd | G24: T4P6 | H24: =IF(TRIM(G24)="","No","Yes") -> Yes | I24: =IF(TRIM(G24)="","",COUNTIFS($G$2:G24,G24)) -> 4 | J24: =IF(OR($A24="",TRIM($G24)=""),"",IFERROR(IF(INDEX(INDIRECT("'"&$G24&"'!F1:F100"),MATCH($A24,INDIRECT("'"&$G24&"'!A1:A100"),0))="","",INDEX(INDIRECT("'"&$G24&"'!F1:F100"),MATCH($A24,INDIRECT("'"&$G24&"'!A1:A100"),0))),"")) | L24: =IF(COUNT(J24:K24)<2,"",J24+K24) | M24: =IF(L24="","",RANK(L24,$L$2:$L$201,0))
A25: 176 | B25: Computing | C25: Blockchain-Based Bug Bounty System with A Novel Weighted Reputation-Driven Consensus Mechanism | D25: Kazi Noor E Saba (University of Liberal Arts Bangladesh)*; Jumana Muntaha (University of Liberal Arts Bangladesh); Md.Akib Al Mahmud DIhan (University of Liberal Arts Bangladesh); Abida Binte Asif (University of Liberal Arts Bangladesh); Sami Hossain (University of Liberal Arts Bangladesh); Nafees Mansoor, PhD (University of Liberal Arts Bangladesh) | E25: noore.saba.cse@ulab.edu.bd; jumana.muntaha.cse@ulab.edu.bd; akib.almahmud.cse@ulab.edu.bd; abida.asif.cse@ulab.edu.bd; sami.hossain.cse@ulab.edu.bd; nafees@ieee.org | F25: noore.saba.cse@ulab.edu.bd | G25: T2P4 | H25: =IF(TRIM(G25)="","No","Yes") -> Yes | I25: =IF(TRIM(G25)="","",COUNTIFS($G$2:G25,G25)) -> 2 | J25: =IF(OR($A25="",TRIM($G25)=""),"",IFERROR(IF(INDEX(INDIRECT("'"&$G25&"'!F1:F100"),MATCH($A25,INDIRECT("'"&$G25&"'!A1:A100"),0))="","",INDEX(INDIRECT("'"&$G25&"'!F1:F100"),MATCH($A25,INDIRECT("'"&$G25&"'!A1:A100"),0))),"")) | L25: =IF(COUNT(J25:K25)<2,"",J25+K25) | M25: =IF(L25="","",RANK(L25,$L$2:$L$201,0))
A26: 177 | B26: Computing | C26: An Interpretable Machine Learning Approach for Maternity Risk Prediction and Assessment | D26: Shah Jafor Sadeek Quaderi (University of Liberal Arts Bangladesh)*; Nasir Uddin Ahmed (University of Liberal Arts Bangladesh); Md. Sahidullah (Asian University of Bangladesh) | E26: jafor.sadeek@ulab.edu.bd; nasir.uddin1@ulab.edu.bd; sahidullah.shafi.work@gmail.com | F26: jafor.sadeek@ulab.edu.bd | G26: T1P1 | H26: =IF(TRIM(G26)="","No","Yes") -> Yes | I26: =IF(TRIM(G26)="","",COUNTIFS($G$2:G26,G26)) -> 3 | J26: =IF(OR($A26="",TRIM($G26)=""),"",IFERROR(IF(INDEX(INDIRECT("'"&$G26&"'!F1:F100"),MATCH($A26,INDIRECT("'"&$G26&"'!A1:A100"),0))="","",INDEX(INDIRECT("'"&$G26&"'!F1:F100"),MATCH($A26,INDIRECT("'"&$G26&"'!A1:A100"),0))),"")) | L26: =IF(COUNT(J26:K26)<2,"",J26+K26) | M26: =IF(L26="","",RANK(L26,$L$2:$L$201,0))
A27: 181 | B27: Computing | C27: Transformer Based Approaches for Intent Detection and Slot Filling in Bangla and Sylhety Virtual Assistants | D27: Proyash Das (Metropolitan University)*; Mowly Ray (Metropolitan University); Md. Mushtaq Shahriyar Rafee (Metropolitan University) | E27: dasproyash10@gmail.com; mowlyray421@gmail.com; rafee@metrouni.edu.bd | F27: dasproyash10@gmail.com | H27: =IF(TRIM(G27)="","No","Yes") -> No | I27: =IF(TRIM(G27)="","",COUNTIFS($G$2:G27,G27)) | J27: =IF(OR($A27="",TRIM($G27)=""),"",IFERROR(IF(INDEX(INDIRECT("'"&$G27&"'!F1:F100"),MATCH($A27,INDIRECT("'"&$G27&"'!A1:A100"),0))="","",INDEX(INDIRECT("'"&$G27&"'!F1:F100"),MATCH($A27,INDIRECT("'"&$G27&"'!A1:A100"),0))),"")) | L27: =IF(COUNT(J27:K27)<2,"",J27+K27) | M27: =IF(L27="","",RANK(L27,$L$2:$L$201,0))
A28: 193 | B28: Computing | C28: A Leakage-Aware Comparative Analysis of Machine Learning Models for IMU-Based Human Activity Recognition Systems | D28: Arnob Aich (AIUB)*; Shamiul Islam (AIUB); Md.Sadman Hossain (AIUB); Md.Nasif Rafidi (AIUB); Samiha Islam Abrita (AIUB) | E28: 23-51390-1@student.aiub.edu; 23-51353-1@student.aiub.edu; 23-55242-3@student.aiub.edu; 23-51361-1@student.aiub.edu; abrita@aiub.edu | F28: 23-51390-1@student.aiub.edu | H28: =IF(TRIM(G28)="","No","Yes") -> No | I28: =IF(TRIM(G28)="","",COUNTIFS($G$2:G28,G28)) | J28: =IF(OR($A28="",TRIM($G28)=""),"",IFERROR(IF(INDEX(INDIRECT("'"&$G28&"'!F1:F100"),MATCH($A28,INDIRECT("'"&$G28&"'!A1:A100"),0))="","",INDEX(INDIRECT("'"&$G28&"'!F1:F100"),MATCH($A28,INDIRECT("'"&$G28&"'!A1:A100"),0))),"")) | L28: =IF(COUNT(J28:K28)<2,"",J28+K28) | M28: =IF(L28="","",RANK(L28,$L$2:$L$201,0))
A29: 215 | B29: Computing | C29: An Integrated Edge-AI Framework for Interpretable Respiratory Screening via Adaptive Cough Analysis in Low-Resource Settings | D29: Md. Mehedi Hassan (Bangladesh University of Engineering and Technology)*; Fariha Hasan Chowdhury (Bangladesh University of Engineering and Technology); Sumaiya Islam Shotota (Bangladesh University of Engineering and Technology); Nafisa Akter (Bangladesh University of Engineering and Technology) | E29: m.hassan.bme@gmail.com; fari.hasanchowdhury@gmail.com; shotota25@gmail.com; nafisaakterrichi@gmail.com | F29: m.hassan.bme@gmail.com | G29: T4P4 | H29: =IF(TRIM(G29)="","No","Yes") -> Yes | I29: =IF(TRIM(G29)="","",COUNTIFS($G$2:G29,G29)) -> 4 | J29: =IF(OR($A29="",TRIM($G29)=""),"",IFERROR(IF(INDEX(INDIRECT("'"&$G29&"'!F1:F100"),MATCH($A29,INDIRECT("'"&$G29&"'!A1:A100"),0))="","",INDEX(INDIRECT("'"&$G29&"'!F1:F100"),MATCH($A29,INDIRECT("'"&$G29&"'!A1:A100"),0))),"")) | L29: =IF(COUNT(J29:K29)<2,"",J29+K29) | M29: =IF(L29="","",RANK(L29,$L$2:$L$201,0))
A30: 232 | B30: Computing | C30: Attention-Enhanced U-Net with Boundary-Aware Hybrid Loss for Low-Grade Glioma Segmentation in Multi-Sequence MRI | D30: Md. Abu Farhad (Rajshahi University of Engineering & Technology)*; Anjuman Risny (Bangladesh Agricultural University); A. F. M. Minhazur Rahman (Rajshahi University of Engineering & Technology) | E30: abufarhad15@gmail.com; anjuman.bau@gmail.com; m.r.saurov@gmail.com | F30: abufarhad15@gmail.com | H30: =IF(TRIM(G30)="","No","Yes") -> No | I30: =IF(TRIM(G30)="","",COUNTIFS($G$2:G30,G30)) | J30: =IF(OR($A30="",TRIM($G30)=""),"",IFERROR(IF(INDEX(INDIRECT("'"&$G30&"'!F1:F100"),MATCH($A30,INDIRECT("'"&$G30&"'!A1:A100"),0))="","",INDEX(INDIRECT("'"&$G30&"'!F1:F100"),MATCH($A30,INDIRECT("'"&$G30&"'!A1:A100"),0))),"")) | L30: =IF(COUNT(J30:K30)<2,"",J30+K30) | M30: =IF(L30="","",RANK(L30,$L$2:$L$201,0))
A31: 238 | B31: Computing | C31: FormSense: A Continuous Fatigue and Form Tracking Application for Resistance Workout Monitoring Utilizing Phase-Graded IMU Analysis | D31: Abdullah Al Mahi (Military Institute of Science and Technology); Munawar Arif Nitol (Military Institute of Science and technology)*; Md. Mehedi Hasan Bhuiyan (Military Institute of Science and Technology); Sadman Rahman (Military Institute of Science and Technology); Kazi Newaj Faisal (Military Institute of Science and Technology) | E31: abdullahmahi526@gmail.com; munawarmisteece@gmail.com; mehedihasan.bhuiyan04@gmail.com; sdmrnwashere@gmail.com; newajfaisal@gmail.com | F31: munawarmisteece@gmail.com | G31: T2P4 | H31: =IF(TRIM(G31)="","No","Yes") -> Yes | I31: =IF(TRIM(G31)="","",COUNTIFS($G$2:G31,G31)) -> 3 | J31: =IF(OR($A31="",TRIM($G31)=""),"",IFERROR(IF(INDEX(INDIRECT("'"&$G31&"'!F1:F100"),MATCH($A31,INDIRECT("'"&$G31&"'!A1:A100"),0))="","",INDEX(INDIRECT("'"&$G31&"'!F1:F100"),MATCH($A31,INDIRECT("'"&$G31&"'!A1:A100"),0))),"")) | L31: =IF(COUNT(J31:K31)<2,"",J31+K31) | M31: =IF(L31="","",RANK(L31,$L$2:$L$201,0))
A32: 242 | B32: Computing | C32: TriFuseNet: A Three-Stream Cross-Attention Network for Few-Shot Multimodal Idiom Ranking | D32: Farhana Sultana Ananna (University of Chittagong)*; Puja Chakraborty (East West University); Shima Chakraborty (University of Chittagong); Shahida begum (East West University) | E32: 20701080@std.cu.ac.bd; puja.chakraborty@ewubd.edu; shimacse@cu.ac.bd; imashahida92@gmail.com | F32: 20701080@std.cu.ac.bd | H32: =IF(TRIM(G32)="","No","Yes") -> No | I32: =IF(TRIM(G32)="","",COUNTIFS($G$2:G32,G32)) | J32: =IF(OR($A32="",TRIM($G32)=""),"",IFERROR(IF(INDEX(INDIRECT("'"&$G32&"'!F1:F100"),MATCH($A32,INDIRECT("'"&$G32&"'!A1:A100"),0))="","",INDEX(INDIRECT("'"&$G32&"'!F1:F100"),MATCH($A32,INDIRECT("'"&$G32&"'!A1:A100"),0))),"")) | L32: =IF(COUNT(J32:K32)<2,"",J32+K32) | M32: =IF(L32="","",RANK(L32,$L$2:$L$201,0))
A33: 243 | B33: Computing | C33: ResNet and LSTM Based Hybrid Deep Learning Model for Reliable and Interpretable Epileptic Seizure Classification | D33: Junaed Ahmed Antor (Yangzhou University); Qingzhen Han (Yangzhou University); Touhid Alam (American International University-Bangladesh)* | E33: junaedm333@gmail.com; hanqzh@yzu.edu.cn; 22-46330-1@student.aiub.edu | F33: 22-46330-1@student.aiub.edu | G33: T4P1 | H33: =IF(TRIM(G33)="","No","Yes") -> Yes | I33: =IF(TRIM(G33)="","",COUNTIFS($G$2:G33,G33)) -> 5 | J33: =IF(OR($A33="",TRIM($G33)=""),"",IFERROR(IF(INDEX(INDIRECT("'"&$G33&"'!F1:F100"),MATCH($A33,INDIRECT("'"&$G33&"'!A1:A100"),0))="","",INDEX(INDIRECT("'"&$G33&"'!F1:F100"),MATCH($A33,INDIRECT("'"&$G33&"'!A1:A100"),0))),"")) | L33: =IF(COUNT(J33:K33)<2,"",J33+K33) | M33: =IF(L33="","",RANK(L33,$L$2:$L$201,0))
A34: 250 | B34: Computing | C34: An Interpretable Stacking Ensemble for Chronic Kidney Disease Screening and KDIGO Severity Staging | D34: Sadman Khalid (University of Liberal Arts Bangladesh); Jannatul Adoun Lam (University of Liberal Arts Bangladesh); Abdullah Al ZIyad ( University of Liberal Arts Bangladesh); Jannatul Ferdous Ruma (ULAB)* | E34: sadman.khalid.cse@ulab.edu.bd; janntul.adoun.cse@ulab.edu.bd; abdullah.al.ziyad.cse@ulab.edu.bd; jannatul.ferdous1@ulab.edu.bd | F34: jannatul.ferdous1@ulab.edu.bd | G34: T4P1 | H34: =IF(TRIM(G34)="","No","Yes") -> Yes | I34: =IF(TRIM(G34)="","",COUNTIFS($G$2:G34,G34)) -> 6 | J34: =IF(OR($A34="",TRIM($G34)=""),"",IFERROR(IF(INDEX(INDIRECT("'"&$G34&"'!F1:F100"),MATCH($A34,INDIRECT("'"&$G34&"'!A1:A100"),0))="","",INDEX(INDIRECT("'"&$G34&"'!F1:F100"),MATCH($A34,INDIRECT("'"&$G34&"'!A1:A100"),0))),"")) | L34: =IF(COUNT(J34:K34)<2,"",J34+K34) | M34: =IF(L34="","",RANK(L34,$L$2:$L$201,0))
A35: 251 | B35: Computing | C35: Continuous Bengali Sign Language Recognition from Sentence-Level Videos Using Deep Learning Architectures | D35: Md. Minhazul Islam (University of Liberal Arts Bangladesh); Shakhar Das Rony (University of Liberal Arts Bangladesh); Tamim Hasan ( University of Liberal Arts Bangladesh); Jannatul Ferdous Ruma (University of Liberal Arts Bangladesh)* | E35: minhazul.islam1.cse@ulab.edu.bd; shakhar.das.cse@ulab.edu.bd; tamim.hasan1.cse@ulab.edu.bd; jannatul.ferdous1@ulab.edu.bd | F35: jannatul.ferdous1@ulab.edu.bd | G35: T4P5 | H35: =IF(TRIM(G35)="","No","Yes") -> Yes | I35: =IF(TRIM(G35)="","",COUNTIFS($G$2:G35,G35)) -> 1 | J35: =IF(OR($A35="",TRIM($G35)=""),"",IFERROR(IF(INDEX(INDIRECT("'"&$G35&"'!F1:F100"),MATCH($A35,INDIRECT("'"&$G35&"'!A1:A100"),0))="","",INDEX(INDIRECT("'"&$G35&"'!F1:F100"),MATCH($A35,INDIRECT("'"&$G35&"'!A1:A100"),0))),"")) | L35: =IF(COUNT(J35:K35)<2,"",J35+K35) | M35: =IF(L35="","",RANK(L35,$L$2:$L$201,0))
A36: 254 | B36: Computing | C36: BioCal RA: A Trustworthy and Explainable Multi-Agent Research Assistant for Biomedical Field | D36: Salvir Rahman Ratul (University of Liberal Arts Bangladesh)*; Navid Rahman (University of Liberal Arts Bangladesh); Shafwan Shadid Khan (University of Liberal Arts Bangladesh); Argho Das (University of Liberal Arts Bangladesh); Nancy Drong (University of Liberal Arts Bangladesh); Rubaiya Hafiz (University of Liberal Arts Bangladesh) | E36: salvir.rahman.cse@ulab.edu.bd; navid.rahman.cse@ulab.edu.bd; shafwan.shadid.cse@ulab.edu.bd; argho.das.cse@ulab.edu.bd; nancy.drong.cse@ulab.edu.bd; rubaiya.hafiz@ulab.edu.bd | F36: salvir.rahman.cse@ulab.edu.bd | G36: T2P3 | H36: =IF(TRIM(G36)="","No","Yes") -> Yes | I36: =IF(TRIM(G36)="","",COUNTIFS($G$2:G36,G36)) -> 1 | J36: =IF(OR($A36="",TRIM($G36)=""),"",IFERROR(IF(INDEX(INDIRECT("'"&$G36&"'!F1:F100"),MATCH($A36,INDIRECT("'"&$G36&"'!A1:A100"),0))="","",INDEX(INDIRECT("'"&$G36&"'!F1:F100"),MATCH($A36,INDIRECT("'"&$G36&"'!A1:A100"),0))),"")) | L36: =IF(COUNT(J36:K36)<2,"",J36+K36) | M36: =IF(L36="","",RANK(L36,$L$2:$L$201,0))
A37: 262 | B37: Computing | C37: MentalScreen: A Hybrid PHQ-9/GAD-7 and MentalRoBERTa Agentic Framework for Multi-Label Mental Health Detection with Deterministic Crisis Routing | D37: Md. Rakibul Hasan Nishat (Rajshahi University of Engineering & Technology)*; S. M. Khalid Bin Zahid (Rajshahi University of Engineering & Technology); Abdul Hasib (Rajshahi University of Engineering & Technology); Md. Firoj Ali (Rajshahi University of Engineering & Technology); Md. Ariful Islam Sagor (Rajshahi University of Engineering & Technology) | E37: rakibulnishat1864@gmail.com; smkhalidbz@gmail.com; sm.abdulhasib.bd@gmail.com; firoj@mte.ruet.ac.bd; ariful.islam200069@gmail.com | F37: rakibulnishat1864@gmail.com | G37: T2P1 | H37: =IF(TRIM(G37)="","No","Yes") -> Yes | I37: =IF(TRIM(G37)="","",COUNTIFS($G$2:G37,G37)) -> 3 | J37: =IF(OR($A37="",TRIM($G37)=""),"",IFERROR(IF(INDEX(INDIRECT("'"&$G37&"'!F1:F100"),MATCH($A37,INDIRECT("'"&$G37&"'!A1:A100"),0))="","",INDEX(INDIRECT("'"&$G37&"'!F1:F100"),MATCH($A37,INDIRECT("'"&$G37&"'!A1:A100"),0))),"")) | L37: =IF(COUNT(J37:K37)<2,"",J37+K37) | M37: =IF(L37="","",RANK(L37,$L$2:$L$201,0))
A38: 263 | B38: Computing | C38: Illusion of Sequence: Rigorously Validated Null Result for Recurrent and Attention-Based Memory-Forensic Ransomware Family Classification | D38: Abdul Hasib (University of Frontier Technology, Bangladesh.)*; Nasif Shahriar Alif (Central Queensland University, Australia.); Md. Rakibul Hasan Nishat (Rajshahi University of Engineering & Technology.); Md. Shakil Ahmed (Green University of Bangladesh.); Arjina Nasrin Khan (University of Frontier Technology, Bangladesh.) | E38: sm.abdulhasib.bd@gmail.com; nasifcqu@gmail.com; rakibulnishat1864@gmail.com; shakil.ahmed.1218@gmail.com; arjinanasrinkhan@gmail.com | F38: sm.abdulhasib.bd@gmail.com | G38: T4P4 | H38: =IF(TRIM(G38)="","No","Yes") -> Yes | I38: =IF(TRIM(G38)="","",COUNTIFS($G$2:G38,G38)) -> 5 | J38: =IF(OR($A38="",TRIM($G38)=""),"",IFERROR(IF(INDEX(INDIRECT("'"&$G38&"'!F1:F100"),MATCH($A38,INDIRECT("'"&$G38&"'!A1:A100"),0))="","",INDEX(INDIRECT("'"&$G38&"'!F1:F100"),MATCH($A38,INDIRECT("'"&$G38&"'!A1:A100"),0))),"")) | L38: =IF(COUNT(J38:K38)<2,"",J38+K38) | M38: =IF(L38="","",RANK(L38,$L$2:$L$201,0))
A39: 265 | B39: Computing | C39: VNetLS: Supervised 3D VNet-Based MRI Enhancement with Loss Optimization | D39: Syeda Sunehra Sakhawat ( University of Liberal Arts Bangladesh); Nusrat Tithy (University of Liberal Arts Bangladesh)*; Romana Sultana (University of Liberal Arts Bangladesh); Kazi Ifat Jahan Zim (University of Liberal Arts Bangladesh); Meherun Nessa Eva (University of Liberal Arts Bangladesh); Ehasan Ahmed ( University of Liberal Arts Bangladesh); Nafees Mansoor ( University of Liberal Arts Bangladesh) | E39: sunehra.sakhawat.cse@ulab.edu.bd; nusrat.jannat.cse@ulab.edu.bd; romana.sultana.cse@ulab.edu.bd; ifat.jahan.cse@ulab.edu.bd; meherun.nessa.cse@ulab.edu.bd; ehasan.ahmed.cse@ulab.edu.bd; nafees.mansoor@ulab.edu.bd | F39: nusrat.jannat.cse@ulab.edu.bd | G39: T4P5 | H39: =IF(TRIM(G39)="","No","Yes") -> Yes | I39: =IF(TRIM(G39)="","",COUNTIFS($G$2:G39,G39)) -> 2 | J39: =IF(OR($A39="",TRIM($G39)=""),"",IFERROR(IF(INDEX(INDIRECT("'"&$G39&"'!F1:F100"),MATCH($A39,INDIRECT("'"&$G39&"'!A1:A100"),0))="","",INDEX(INDIRECT("'"&$G39&"'!F1:F100"),MATCH($A39,INDIRECT("'"&$G39&"'!A1:A100"),0))),"")) | L39: =IF(COUNT(J39:K39)<2,"",J39+K39) | M39: =IF(L39="","",RANK(L39,$L$2:$L$201,0))
A40: 266 | B40: Computing | C40: Cartographer: Transforming Code Repositories into LLM-Optimized Semantic Graphs | D40: Ehasan Ahmed (University of Liberal Arts Bangladesh)*; Nafess Mansoor (University of Liberal Arts Bangladesh) | E40: ehasan.ahmed.cse@ulab.edu.bd; nafees.mansoor@ulab.edu.bd | F40: ehasan.ahmed.cse@ulab.edu.bd | G40: T4P5 | H40: =IF(TRIM(G40)="","No","Yes") -> Yes | I40: =IF(TRIM(G40)="","",COUNTIFS($G$2:G40,G40)) -> 3 | J40: =IF(OR($A40="",TRIM($G40)=""),"",IFERROR(IF(INDEX(INDIRECT("'"&$G40&"'!F1:F100"),MATCH($A40,INDIRECT("'"&$G40&"'!A1:A100"),0))="","",INDEX(INDIRECT("'"&$G40&"'!F1:F100"),MATCH($A40,INDIRECT("'"&$G40&"'!A1:A100"),0))),"")) | L40: =IF(COUNT(J40:K40)<2,"",J40+K40) | M40: =IF(L40="","",RANK(L40,$L$2:$L$201,0))
A41: 273 | B41: Computing | C41: A Lightweight Hybrid Quantum-Classical CNN for Brain Tumor MRI Classification | D41: Tamanna Khatun (University of Liberal Arts Bangladesh)*; Nafees Mansoor (University of Liberal Arts Bangladesh) | E41: tamanna.khatun.cse@ulab.edu.bd; nafees.mansoor@ulab.edu.bd | F41: tamanna.khatun.cse@ulab.edu.bd | G41: T4P3 | H41: =IF(TRIM(G41)="","No","Yes") -> Yes | I41: =IF(TRIM(G41)="","",COUNTIFS($G$2:G41,G41)) -> 1 | J41: =IF(OR($A41="",TRIM($G41)=""),"",IFERROR(IF(INDEX(INDIRECT("'"&$G41&"'!F1:F100"),MATCH($A41,INDIRECT("'"&$G41&"'!A1:A100"),0))="","",INDEX(INDIRECT("'"&$G41&"'!F1:F100"),MATCH($A41,INDIRECT("'"&$G41&"'!A1:A100"),0))),"")) | L41: =IF(COUNT(J41:K41)<2,"",J41+K41) | M41: =IF(L41="","",RANK(L41,$L$2:$L$201,0))
A42: 275 | B42: Computing | C42: Multi-Representation Fusion with Subspace-Aware SMOTE for Source Code Vulnerability Detection | D42: Talat Mahmud Lam (University of Liberal Arts Bangladesh); Sadia Nuzat Prova (University of Liberal Arts Bangladesh); Shahin Alam (University of Liberal Arts Bangladesh ); Umme Asma Busra (University of Liberal Arts Bangladesh); Md. Nazmul Abdal (University of Liberal Arts Bangladesh )* | E42: talat.mahmud.cse@ulab.edu.bd; sadia.nuzat.cse@ulab.edu.bd; shahin.alam.cse@ulab.edu.bd; umme.asma.cse@ulab.edu.bd; nazmul.abdal@ulab.edu.bd | F42: nazmul.abdal@ulab.edu.bd | G42: T2P3 | H42: =IF(TRIM(G42)="","No","Yes") -> Yes | I42: =IF(TRIM(G42)="","",COUNTIFS($G$2:G42,G42)) -> 2 | J42: =IF(OR($A42="",TRIM($G42)=""),"",IFERROR(IF(INDEX(INDIRECT("'"&$G42&"'!F1:F100"),MATCH($A42,INDIRECT("'"&$G42&"'!A1:A100"),0))="","",INDEX(INDIRECT("'"&$G42&"'!F1:F100"),MATCH($A42,INDIRECT("'"&$G42&"'!A1:A100"),0))),"")) | L42: =IF(COUNT(J42:K42)<2,"",J42+K42) | M42: =IF(L42="","",RANK(L42,$L$2:$L$201,0))
A43: 305 | B43: Computing | C43: Explainable Digital Addiction Severity Prediction Using Machine Learning, NLP, and Large Language Models | D43: Tasnim Sharif Rowla (North South University); Jawata Afnan (North South University); Nishat Salsabil (North South University); Riasat Khan (North South University)* | E43: tasnim.rowla@northsouth.edu; jawata.afnan@northsouth.edu; nishat.salsabil01@northsouth.edu; riasat.khan@northsouth.edu | F43: riasat.khan@northsouth.edu | G43: T4P1 | H43: =IF(TRIM(G43)="","No","Yes") -> Yes | I43: =IF(TRIM(G43)="","",COUNTIFS($G$2:G43,G43)) -> 7 | J43: =IF(OR($A43="",TRIM($G43)=""),"",IFERROR(IF(INDEX(INDIRECT("'"&$G43&"'!F1:F100"),MATCH($A43,INDIRECT("'"&$G43&"'!A1:A100"),0))="","",INDEX(INDIRECT("'"&$G43&"'!F1:F100"),MATCH($A43,INDIRECT("'"&$G43&"'!A1:A100"),0))),"")) | L43: =IF(COUNT(J43:K43)<2,"",J43+K43) | M43: =IF(L43="","",RANK(L43,$L$2:$L$201,0))
A44: 310 | B44: Computing | C44: Predicting the Effect of Drugs on Neonatal using Machine Learning and Explainable AI | D44: Md. Zehadul Islam (Green University of Bangladesh); Md. Abdullah Al Moin (Green University of Bangladesh); Md. Abu Hurayra (Green University of Bangladesh); Md. Solaiman Mia (Green University of Bangladesh)* | E44: zehadul.ace@gmail.com; abdullah.al.moin.cse@gmail.com; hurayra.55.nox@gmail.com; solaiman@cse.green.edu.bd | F44: solaiman@cse.green.edu.bd | G44: T4P2 | H44: =IF(TRIM(G44)="","No","Yes") -> Yes | I44: =IF(TRIM(G44)="","",COUNTIFS($G$2:G44,G44)) -> 1 | J44: =IF(OR($A44="",TRIM($G44)=""),"",IFERROR(IF(INDEX(INDIRECT("'"&$G44&"'!F1:F100"),MATCH($A44,INDIRECT("'"&$G44&"'!A1:A100"),0))="","",INDEX(INDIRECT("'"&$G44&"'!F1:F100"),MATCH($A44,INDIRECT("'"&$G44&"'!A1:A100"),0))),"")) | L44: =IF(COUNT(J44:K44)<2,"",J44+K44) | M44: =IF(L44="","",RANK(L44,$L$2:$L$201,0))
A45: 312 | B45: Computing | C45: A Leak-Free, Explainable Machine Learning Framework for Predicting Internet Gaming Disorder Tolerance: Re-Evaluating SMOTE, Chi-Square Feature Selection, and LIME under Rigorous Validation | D45: Firoz Hasan (Daffodil International University)*; Rubina Khatun (University of Rajshahi); Dewan Mamun Raza (Daffodil International University) | E45: firoz.cse@diu.edu.bd; babyru17@gmail.com; dewan.csediu@gmail.com | F45: firoz.cse@diu.edu.bd | H45: =IF(TRIM(G45)="","No","Yes") -> No | I45: =IF(TRIM(G45)="","",COUNTIFS($G$2:G45,G45)) | J45: =IF(OR($A45="",TRIM($G45)=""),"",IFERROR(IF(INDEX(INDIRECT("'"&$G45&"'!F1:F100"),MATCH($A45,INDIRECT("'"&$G45&"'!A1:A100"),0))="","",INDEX(INDIRECT("'"&$G45&"'!F1:F100"),MATCH($A45,INDIRECT("'"&$G45&"'!A1:A100"),0))),"")) | L45: =IF(COUNT(J45:K45)<2,"",J45+K45) | M45: =IF(L45="","",RANK(L45,$L$2:$L$201,0))
A46: 322 | B46: Computing | C46: NOVA-Net: A Noise-Aware Deep Network for Robust Human Activity Recognition from Surveillance Videos | D46: Atia Sadilka (Rajshahi University of Engineering and Technology); Asifur Rahman Siyam (Rajshahi University of Engineering and Technology )*; Md. Nuhi-Alamin (Rajshahi University of Engineering and Technology) | E46: atiasadika63@gmail.com; asif.siyam72@gmail.com; nuhialamin@eee.ruet.ac.bd | F46: asif.siyam72@gmail.com | G46: T2P3 | H46: =IF(TRIM(G46)="","No","Yes") -> Yes | I46: =IF(TRIM(G46)="","",COUNTIFS($G$2:G46,G46)) -> 3 | J46: =IF(OR($A46="",TRIM($G46)=""),"",IFERROR(IF(INDEX(INDIRECT("'"&$G46&"'!F1:F100"),MATCH($A46,INDIRECT("'"&$G46&"'!A1:A100"),0))="","",INDEX(INDIRECT("'"&$G46&"'!F1:F100"),MATCH($A46,INDIRECT("'"&$G46&"'!A1:A100"),0))),"")) | L46: =IF(COUNT(J46:K46)<2,"",J46+K46) | M46: =IF(L46="","",RANK(L46,$L$2:$L$201,0))
A47: 327 | B47: Computing | C47: Explainable Machine Learning and Causal Analysis for Obesity Prediction Using Knowledge Graphs | D47: Tashida Yeasmin (Atish Dipankar University of Science & Technology)* | E47: tashida@adust.edu.bd | F47: tashida@adust.edu.bd | G47: T4P2 | H47: =IF(TRIM(G47)="","No","Yes") -> Yes | I47: =IF(TRIM(G47)="","",COUNTIFS($G$2:G47,G47)) -> 2 | J47: =IF(OR($A47="",TRIM($G47)=""),"",IFERROR(IF(INDEX(INDIRECT("'"&$G47&"'!F1:F100"),MATCH($A47,INDIRECT("'"&$G47&"'!A1:A100"),0))="","",INDEX(INDIRECT("'"&$G47&"'!F1:F100"),MATCH($A47,INDIRECT("'"&$G47&"'!A1:A100"),0))),"")) | L47: =IF(COUNT(J47:K47)<2,"",J47+K47) | M47: =IF(L47="","",RANK(L47,$L$2:$L$201,0))
A48: 332 | B48: Computing | C48: Meta-Learning for Few-Shot Personalization of Error-Related Potential Brain-Computer Interfaces | D48: Md Shahidul Islam Dipu (Rajshahi University of Engineering and Technology)*; Barshon Sen (Rajshahi University of Engineering and Technology) | E48: shahidul03579@gmail.com; sen.barshon@gmail.com | F48: shahidul03579@gmail.com | G48: T4P1 | H48: =IF(TRIM(G48)="","No","Yes") -> Yes | I48: =IF(TRIM(G48)="","",COUNTIFS($G$2:G48,G48)) -> 8 | J48: =IF(OR($A48="",TRIM($G48)=""),"",IFERROR(IF(INDEX(INDIRECT("'"&$G48&"'!F1:F100"),MATCH($A48,INDIRECT("'"&$G48&"'!A1:A100"),0))="","",INDEX(INDIRECT("'"&$G48&"'!F1:F100"),MATCH($A48,INDIRECT("'"&$G48&"'!A1:A100"),0))),"")) | L48: =IF(COUNT(J48:K48)<2,"",J48+K48) | M48: =IF(L48="","",RANK(L48,$L$2:$L$201,0))
A49: 346 | B49: Computing | C49: High-Throughput Meritocratic Consensus: A Native Go Implementation of Reputation-Based Ordering for Hyperledger Fabric | D49: Takia Nawrin (University of Liberal Arts Bangladesh)*; Md. Yusuf (University of Liberal Arts Bangladesh); Maftun Ahommed (University of Liberal Arts Bangladesh); Nafees Mansoor (University of Liberal Arts Bangladesh) | E49: takia.nawrin.cse@ulab.edu.bd; md.yusuf.cse@ulab.edu.bd; maftun.ahommed.cse@ulab.edu.bd; nafees@ieee.org | F49: takia.nawrin.cse@ulab.edu.bd | G49: T2P4 | H49: =IF(TRIM(G49)="","No","Yes") -> Yes | I49: =IF(TRIM(G49)="","",COUNTIFS($G$2:G49,G49)) -> 4 | J49: =IF(OR($A49="",TRIM($G49)=""),"",IFERROR(IF(INDEX(INDIRECT("'"&$G49&"'!F1:F100"),MATCH($A49,INDIRECT("'"&$G49&"'!A1:A100"),0))="","",INDEX(INDIRECT("'"&$G49&"'!F1:F100"),MATCH($A49,INDIRECT("'"&$G49&"'!A1:A100"),0))),"")) | L49: =IF(COUNT(J49:K49)<2,"",J49+K49) | M49: =IF(L49="","",RANK(L49,$L$2:$L$201,0))
A50: 347 | B50: Computing | C50: NeuroXplain: An Explainable Transfer Learning Framework for Alzheimer’s Disease Classification | D50: Md Sifatuzzaman Mia (Daffodil International University )*; Md. Abu Yousuf (Multimedia University ); MD. Jahid Sikder (Daffodil International University); Md. Nabid Rezuan (Daffodil International University); Md. Sadekur Rahman (Daffodil International University) | E50: mia23105101363@diu.edu.bd; yousuf.md.abu@student.mmu.edu.my; sikder2305101759@diu.edu.bd; rezuan23105101144@diu.edu.bd; sadekur.cse@daffodilvarsity.edu.bd | F50: mia23105101363@diu.edu.bd | H50: =IF(TRIM(G50)="","No","Yes") -> No | I50: =IF(TRIM(G50)="","",COUNTIFS($G$2:G50,G50)) | J50: =IF(OR($A50="",TRIM($G50)=""),"",IFERROR(IF(INDEX(INDIRECT("'"&$G50&"'!F1:F100"),MATCH($A50,INDIRECT("'"&$G50&"'!A1:A100"),0))="","",INDEX(INDIRECT("'"&$G50&"'!F1:F100"),MATCH($A50,INDIRECT("'"&$G50&"'!A1:A100"),0))),"")) | L50: =IF(COUNT(J50:K50)<2,"",J50+K50) | M50: =IF(L50="","",RANK(L50,$L$2:$L$201,0))
A51: 354 | B51: Computing | C51: Integrated Machine Learning and Deep Learning Pipeline for Discovering Diagnostic and Prognostic Biomarkers of Colon Cancer | D51: Mst. Moriam Khatun Mim (Green University of Bangladesh); Md. Sakhawat Hossain Rabbi (Green University of Bangladesh); Susmita Paul Tisha (Green University of Bangladesh); Mahenoor Akhter (Green University of Bangladesh); Wahia Tasnim (Green University of Bangladesh); Humayan Kabir Rana (Green University of Bangladesh)* | E51: mimmariam89766@gmail.com; rabbi.201002311@green.ac.bd; scpaultisha20@gmail.com; mahinoorakther136@gmail.com; wahia@ads.green.edu.bd; humayan@cse.green.edu.bd | F51: humayan@cse.green.edu.bd | G51: T4P6 | H51: =IF(TRIM(G51)="","No","Yes") -> Yes | I51: =IF(TRIM(G51)="","",COUNTIFS($G$2:G51,G51)) -> 5 | J51: =IF(OR($A51="",TRIM($G51)=""),"",IFERROR(IF(INDEX(INDIRECT("'"&$G51&"'!F1:F100"),MATCH($A51,INDIRECT("'"&$G51&"'!A1:A100"),0))="","",INDEX(INDIRECT("'"&$G51&"'!F1:F100"),MATCH($A51,INDIRECT("'"&$G51&"'!A1:A100"),0))),"")) | L51: =IF(COUNT(J51:K51)<2,"",J51+K51) | M51: =IF(L51="","",RANK(L51,$L$2:$L$201,0))
A52: 355 | B52: Computing | C52: Temporal Capability Cryptography: Cryptographic State Evolution for Forward Authorization in Distributed Systems | D52: Arunangshu Mojumder Raatul (University of Liberal Arts Bangladesh)*; Nafees Mansoor (University of Liberal Arts Bangladesh) | E52: arunangshu.mojumder.cse@ulab.edu.bd; nafees.mansoor@ulab.edu.bd | F52: arunangshu.mojumder.cse@ulab.edu.bd | G52: T4P4 | H52: =IF(TRIM(G52)="","No","Yes") -> Yes | I52: =IF(TRIM(G52)="","",COUNTIFS($G$2:G52,G52)) -> 6 | J52: =IF(OR($A52="",TRIM($G52)=""),"",IFERROR(IF(INDEX(INDIRECT("'"&$G52&"'!F1:F100"),MATCH($A52,INDIRECT("'"&$G52&"'!A1:A100"),0))="","",INDEX(INDIRECT("'"&$G52&"'!F1:F100"),MATCH($A52,INDIRECT("'"&$G52&"'!A1:A100"),0))),"")) | L52: =IF(COUNT(J52:K52)<2,"",J52+K52) | M52: =IF(L52="","",RANK(L52,$L$2:$L$201,0))
A53: 357 | B53: Computing | C53: Comparative Study of Classical and Learning-Based Tissue Tracking Algorithms on Infrared Surgical Tattoo Sequences for Minimally Invasive Surgery | D53: Zinia Ahmed Toushy (Brac University); Tahsina Rahman (Brac University)*; Sadia Ferdous (Brac University); Muaz Mohammad Zimam (Brac University); Nafis Imtiaz Fuad (Brac University); Amitabha Chakrabarty (Brac University); Azwad Aziz (Brac University) | E53: zinia.ahmed.toushy@g.bracu.ac.bd; tahsina.rahman1@g.bracu.ac.bd; sadia.ferdous@g.bracu.ac.bd; muaz.mohammad.zimam1@g.bracu.ac.bd; nafis.imtiaz.fuad@g.bracu.ac.bd; amitabha@bracu.ac.bd; azwad.aziz@g.bracu.ac.bd | F53: tahsina.rahman1@g.bracu.ac.bd | H53: =IF(TRIM(G53)="","No","Yes") -> No | I53: =IF(TRIM(G53)="","",COUNTIFS($G$2:G53,G53)) | J53: =IF(OR($A53="",TRIM($G53)=""),"",IFERROR(IF(INDEX(INDIRECT("'"&$G53&"'!F1:F100"),MATCH($A53,INDIRECT("'"&$G53&"'!A1:A100"),0))="","",INDEX(INDIRECT("'"&$G53&"'!F1:F100"),MATCH($A53,INDIRECT("'"&$G53&"'!A1:A100"),0))),"")) | L53: =IF(COUNT(J53:K53)<2,"",J53+K53) | M53: =IF(L53="","",RANK(L53,$L$2:$L$201,0))
A54: 358 | B54: Computing | C54: AdaLLM: A Subject-Adaptive RAG Framework Designed for the Question Answering Process of NCTB’s Class-8 Science & BGS Subjects | D54: Raihan Kibria (University of Liberal Arts Bangladesh)*; Samia Rahman (University of Liberal Arts Bangladesh); Redwan Ahamad Samir (University of Liberal Arts Bangladesh); Md Omur Faruk (University of Liberal Arts Bangladesh); Raiyan Islam (University of Liberal Arts Bangladesh); MD KAVIUL HOSSAIN (University of Liberal Arts Bangladesh) | E54: raihan.kibria@ulab.edu.bd; samia.rahman.cse@ulab.edu.bd; redwansamir90@gmail.com; omurfaruk199823@gmail.com; raiyanislam875@gmail.com; kaviul.hossain@ulab.edu.bd | F54: raihan.kibria@ulab.edu.bd | G54: T2P3 | H54: =IF(TRIM(G54)="","No","Yes") -> Yes | I54: =IF(TRIM(G54)="","",COUNTIFS($G$2:G54,G54)) -> 4 | J54: =IF(OR($A54="",TRIM($G54)=""),"",IFERROR(IF(INDEX(INDIRECT("'"&$G54&"'!F1:F100"),MATCH($A54,INDIRECT("'"&$G54&"'!A1:A100"),0))="","",INDEX(INDIRECT("'"&$G54&"'!F1:F100"),MATCH($A54,INDIRECT("'"&$G54&"'!A1:A100"),0))),"")) | L54: =IF(COUNT(J54:K54)<2,"",J54+K54) | M54: =IF(L54="","",RANK(L54,$L$2:$L$201,0))
A55: 362 | B55: Computing | C55: Graph Attention Versus Tabular Models for Early Liver Fibrosis Staging: A Leakage-Controlled Multi-Cohort Benchmark | D55: Samiha Zaman (BRAC University)*; Rudra Joyti Maitra Soham (BRAC University); Ismaeel Ghani (BRAC University); Lubaina Afra Islam (BRAC University); Samira Ahmed (BRAC University); Azwad Aziz (BRAC University); Amitabha Chakrabarty (BRAC University) | E55: samihabintezaman25@gmail.com; rudrajoyti.maitra.soham@g.bracu.ac.bd; ismaeel.ghani@g.bracu.ac.bd; lubaina.afra.islam@g.bracu.ac.bd; samira.ahmed.naahee@g.bracu.ac.bd; azwad.aziz@g.bracu.ac.bd; amitabha@bracu.ac.bd | F55: samihabintezaman25@gmail.com | G55: T4P5 | H55: =IF(TRIM(G55)="","No","Yes") -> Yes | I55: =IF(TRIM(G55)="","",COUNTIFS($G$2:G55,G55)) -> 4 | J55: =IF(OR($A55="",TRIM($G55)=""),"",IFERROR(IF(INDEX(INDIRECT("'"&$G55&"'!F1:F100"),MATCH($A55,INDIRECT("'"&$G55&"'!A1:A100"),0))="","",INDEX(INDIRECT("'"&$G55&"'!F1:F100"),MATCH($A55,INDIRECT("'"&$G55&"'!A1:A100"),0))),"")) | L55: =IF(COUNT(J55:K55)<2,"",J55+K55) | M55: =IF(L55="","",RANK(L55,$L$2:$L$201,0))
A56: 373 | B56: Computing | C56: A Zero-Initialized Residual MLP Head for Lung Cancer CT Scan Image Classification: A Comparative Study using five CNN Backbones | D56: Md. Ahsan Ullah (University of Liberal Arts Bangladesh)*; Lasker Ershad Ali (Khulna University); Atanu Shuvam Roy (University of Liberal Arts Bangladesh); T. M. A. K. Azad (University of Liberal Arts Bangladesh); Arnab Mukherjee (International University of Business Agriculture and Technology); G. M. Mamun-Al-Imran (Khulna University) | E56: ahsan.ullah@ulab.edu.bd; ershad@math.ku.ac.bd; atanu.shuvam@ulab.edu.bd; abul.kalam@ulab.edu.bd; arnab.math@iubat.edu; mamun.imran@math.ku.ac.bd | F56: ahsan.ullah@ulab.edu.bd | G56: T4P6 | H56: =IF(TRIM(G56)="","No","Yes") -> Yes | I56: =IF(TRIM(G56)="","",COUNTIFS($G$2:G56,G56)) -> 6 | J56: =IF(OR($A56="",TRIM($G56)=""),"",IFERROR(IF(INDEX(INDIRECT("'"&$G56&"'!F1:F100"),MATCH($A56,INDIRECT("'"&$G56&"'!A1:A100"),0))="","",INDEX(INDIRECT("'"&$G56&"'!F1:F100"),MATCH($A56,INDIRECT("'"&$G56&"'!A1:A100"),0))),"")) | L56: =IF(COUNT(J56:K56)<2,"",J56+K56) | M56: =IF(L56="","",RANK(L56,$L$2:$L$201,0))
A57: 375 | B57: Computing | C57: Adapting BitNet b1.58 techniques in Convolutional Neural Networks for Efficient Deep Learning | D57: Jayed Bin Jamil (BRAC University)*; Lazin Shimran (BRAC University); Maimuna Esha (BRAC University); Amitabha Chakrabarty (BRAC University); Swakkhar Shatabda (BRAC University); Atanu Roy (BRAC University); Azwad Aziz (BRAC University) | E57: jayed.bin.jamil@g.bracu.ac.bd; lazin.shimran@g.bracu.ac.bd; maimuna.fairuz.esha@g.bracu.ac.bd; amitabha@bracu.ac.bd; swakkhar.shatabda@bracu.ac.bd; atanu.roy@bracu.ac.bd; azwad.aziz@bracu.ac.bd | F57: jayed.bin.jamil@g.bracu.ac.bd | G57: T2P2 | H57: =IF(TRIM(G57)="","No","Yes") -> Yes | I57: =IF(TRIM(G57)="","",COUNTIFS($G$2:G57,G57)) -> 4 | J57: =IF(OR($A57="",TRIM($G57)=""),"",IFERROR(IF(INDEX(INDIRECT("'"&$G57&"'!F1:F100"),MATCH($A57,INDIRECT("'"&$G57&"'!A1:A100"),0))="","",INDEX(INDIRECT("'"&$G57&"'!F1:F100"),MATCH($A57,INDIRECT("'"&$G57&"'!A1:A100"),0))),"")) | L57: =IF(COUNT(J57:K57)<2,"",J57+K57) | M57: =IF(L57="","",RANK(L57,$L$2:$L$201,0))
A58: 376 | B58: Computing | C58: Kidney-Net:Feature-Centric and Minimal Biomarker-Based Prediction of Chronic Kidney Disease Using Machine Learning | D58: Md.Rafiul Islam (American International University Bangladesh)*; Famid Rabbi (American International University Bangladesh); Tasmin Akther Tasu (American International University Bangladesh); Anika Tahsin (American International University Bangladesh); Samia Afroze Simla (American International University Bangladesh); Tawfiqul Hasan (American International University Bangladesh); Sultanul Arifeen Hamim (American International University Bangladesh); Jungpil Shin (University of Aizu) | E58: 23-52452-2@student.aiub.edu; 23-54436-3@student.aiub.edu; 23-54361-3@student.aiub.edu; 23-50984-1@student.aiub.edu; 23-54500-3@student.aiub.edu; 23-54422-3@student.aiub.edu; hamim@aiub.edu; jpshin@u-aizu.ac.jp | F58: 23-52452-2@student.aiub.edu | G58: T4P1 | H58: =IF(TRIM(G58)="","No","Yes") -> Yes | I58: =IF(TRIM(G58)="","",COUNTIFS($G$2:G58,G58)) -> 9 | J58: =IF(OR($A58="",TRIM($G58)=""),"",IFERROR(IF(INDEX(INDIRECT("'"&$G58&"'!F1:F100"),MATCH($A58,INDIRECT("'"&$G58&"'!A1:A100"),0))="","",INDEX(INDIRECT("'"&$G58&"'!F1:F100"),MATCH($A58,INDIRECT("'"&$G58&"'!A1:A100"),0))),"")) | L58: =IF(COUNT(J58:K58)<2,"",J58+K58) | M58: =IF(L58="","",RANK(L58,$L$2:$L$201,0))
A59: 377 | B59: Computing | C59: Graph-Enhanced Causal Reinforcement Learning for Proactive Customer Retention: A Comparative Benchmark | D59: Kazi Tasfin Mahmud (BRAC University)*; Md. Zarif Latif (BRAC University); Sidratul Muntaha (BRAC University); Puja Banik (BRAC University); Azwad Aziz (BRAC University); Amitabha Chakrabarty (BRAC University) | E59: kazi.tasfin.mahmud@g.bracu.ac.bd; md.zarif.latif@g.bracu.ac.bd; sidratul.muntaha1@g.bracu.ac.bd; puja.banik@g.bracu.ac.bd; azwad.aziz@bracu.ac.bd; amitabha@bracu.ac.bd | F59: kazi.tasfin.mahmud@g.bracu.ac.bd | G59: T2P1 | H59: =IF(TRIM(G59)="","No","Yes") -> Yes | I59: =IF(TRIM(G59)="","",COUNTIFS($G$2:G59,G59)) -> 4 | J59: =IF(OR($A59="",TRIM($G59)=""),"",IFERROR(IF(INDEX(INDIRECT("'"&$G59&"'!F1:F100"),MATCH($A59,INDIRECT("'"&$G59&"'!A1:A100"),0))="","",INDEX(INDIRECT("'"&$G59&"'!F1:F100"),MATCH($A59,INDIRECT("'"&$G59&"'!A1:A100"),0))),"")) | L59: =IF(COUNT(J59:K59)<2,"",J59+K59) | M59: =IF(L59="","",RANK(L59,$L$2:$L$201,0))
A60: 378 | B60: Computing | C60: A Multimodal Framework for Early-Stage Crop Disease Diagnosis Using Visual and Environmental Data | D60: Ishmam Bhuiyan (BRAC University)*; Abrar Masud (Brac University); Shafin Ahmed (Brac University); Aswad Khan (Brac University); Azwad Aziz (Brac University); Amitabha Chakrabarty (Brac Unviersity) | E60: rafsanrashid7@gmail.com; abrar.masud@g.bracu.ac.bd; shafin.ahmed3@g.bracu.ac.bd; aswad.khan@g.bracu.ac.bd; azwad.aziz@g.bracu.ac.bd; amitabha@bracu.ac.bd | F60: rafsanrashid7@gmail.com | H60: =IF(TRIM(G60)="","No","Yes") -> No | I60: =IF(TRIM(G60)="","",COUNTIFS($G$2:G60,G60)) | J60: =IF(OR($A60="",TRIM($G60)=""),"",IFERROR(IF(INDEX(INDIRECT("'"&$G60&"'!F1:F100"),MATCH($A60,INDIRECT("'"&$G60&"'!A1:A100"),0))="","",INDEX(INDIRECT("'"&$G60&"'!F1:F100"),MATCH($A60,INDIRECT("'"&$G60&"'!A1:A100"),0))),"")) | L60: =IF(COUNT(J60:K60)<2,"",J60+K60) | M60: =IF(L60="","",RANK(L60,$L$2:$L$201,0))
A61: 383 | B61: Computing | C61: A Lightweight Framework for Foldable Protein Sequence Generation via Confidence-Guided Selection | D61: Shahriar Shirso (Brac)*; Suprio Mugdha (Brac); Anika Trishna (Brac); SInka Aishi (Brac); Amitabha Chakravarthy (Brac); Azwad Aziz (Brac) | E61: shahriar.khan.shirso@g.bracu.ac.bd; suprio.biswas.mugdha@g.bracu.ac.bd; anika.anis.trishna@g.bracu.ac.bd; sinka.siddiki.aishi@g.bracu.ac.bd; amitabha@bracu.ac.bd; azwad.aziz@bracu.ac.bd | F61: shahriar.khan.shirso@g.bracu.ac.bd | H61: =IF(TRIM(G61)="","No","Yes") -> No | I61: =IF(TRIM(G61)="","",COUNTIFS($G$2:G61,G61)) | J61: =IF(OR($A61="",TRIM($G61)=""),"",IFERROR(IF(INDEX(INDIRECT("'"&$G61&"'!F1:F100"),MATCH($A61,INDIRECT("'"&$G61&"'!A1:A100"),0))="","",INDEX(INDIRECT("'"&$G61&"'!F1:F100"),MATCH($A61,INDIRECT("'"&$G61&"'!A1:A100"),0))),"")) | L61: =IF(COUNT(J61:K61)<2,"",J61+K61) | M61: =IF(L61="","",RANK(L61,$L$2:$L$201,0))
A62: 24 | B62: Smart Systems | C62: Robust Anomaly Detection in Multi-Pollutant Time Series Using Median–MAD and Hybrid Sequence Model | D62: Ohcitya Bhattacharjee (Chittagong University of Engineering & Technology); Pratya Chowdhury (Chittagong University of Engineering & Technology); Md.Ruhul Amin Shazid (Bangladesh University of Business and Technology (BUBT))* | E62: bhattacharjeeohcitya@gmail.com; chowdhurypratya0066@gmail.com; ruhulaminshazid@gmail.com | F62: ruhulaminshazid@gmail.com | H62: =IF(TRIM(G62)="","No","Yes") -> No | I62: =IF(TRIM(G62)="","",COUNTIFS($G$2:G62,G62)) | J62: =IF(OR($A62="",TRIM($G62)=""),"",IFERROR(IF(INDEX(INDIRECT("'"&$G62&"'!F1:F100"),MATCH($A62,INDIRECT("'"&$G62&"'!A1:A100"),0))="","",INDEX(INDIRECT("'"&$G62&"'!F1:F100"),MATCH($A62,INDIRECT("'"&$G62&"'!A1:A100"),0))),"")) | L62: =IF(COUNT(J62:K62)<2,"",J62+K62) | M62: =IF(L62="","",RANK(L62,$L$2:$L$201,0))
A63: 278 | B63: Smart Systems | C63: The Tokenization Tax: Quantifying and Mitigating Subword Fragmentation Costs for Bangla in Multilingual LLMs | D63: Yasar Al Samin (Islamic University of Technology, Dhaka)*; Zaeed Ahmad (Islamic University of Technology, Dhaka); Tanjim Mahbub (Islamic University of Technology, Dhaka); Tashmim Hossain Maisha (Islamic University of Technology, Dhaka); Mosaraf Hosan Nishat (Islamic University of Technology, Dhaka); Muhammad Usama Islam (Metropolitan State University, Minnesota) | E63: yasaralsamin@iut-dhaka.edu; zaeed@iut-dhaka.edu; tanjimmahbub@iut-dhaka.edu; tashmimmaisha@iut-dhaka.edu; mosarafhosan@iut-dhaka.edu; muhammadusama.islam@metrostate.edu | F63: yasaralsamin@iut-dhaka.edu | H63: =IF(TRIM(G63)="","No","Yes") -> No | I63: =IF(TRIM(G63)="","",COUNTIFS($G$2:G63,G63)) | J63: =IF(OR($A63="",TRIM($G63)=""),"",IFERROR(IF(INDEX(INDIRECT("'"&$G63&"'!F1:F100"),MATCH($A63,INDIRECT("'"&$G63&"'!A1:A100"),0))="","",INDEX(INDIRECT("'"&$G63&"'!F1:F100"),MATCH($A63,INDIRECT("'"&$G63&"'!A1:A100"),0))),"")) | L63: =IF(COUNT(J63:K63)<2,"",J63+K63) | M63: =IF(L63="","",RANK(L63,$L$2:$L$201,0))
A64: 283 | B64: Smart Systems | C64: An Integrated Gradient-boosting and Session-based Deep Learning Framework for Demand forecasting and Customer Personalization | D64: Sultana Razia (Greenwhich University)* | E64: sultanarofficial@gmail.com | F64: sultanarofficial@gmail.com | G64: T4P5 | H64: =IF(TRIM(G64)="","No","Yes") -> Yes | I64: =IF(TRIM(G64)="","",COUNTIFS($G$2:G64,G64)) -> 5 | J64: =IF(OR($A64="",TRIM($G64)=""),"",IFERROR(IF(INDEX(INDIRECT("'"&$G64&"'!F1:F100"),MATCH($A64,INDIRECT("'"&$G64&"'!A1:A100"),0))="","",INDEX(INDIRECT("'"&$G64&"'!F1:F100"),MATCH($A64,INDIRECT("'"&$G64&"'!A1:A100"),0))),"")) | L64: =IF(COUNT(J64:K64)<2,"",J64+K64) | M64: =IF(L64="","",RANK(L64,$L$2:$L$201,0))
A65: 303 | B65: Smart Systems | C65: ESP32-Based IoT Smart Poultry Farm with MQTT and Hybrid Power | D65: Aditya Das Gupta (Barisal Engineering College, University of Dhaka)*; Amit Kumar Kar ( Barisal Engineering College, University of Dhaka); Shihab- Al -Rashid ( Barisal Engineering College, University of Dhaka); Mahfujur Rahman Reaz (Barisal Engineering College, University of Dhaka); Piyal Das (Port City International University) | E65: aditya.duengg@bec.edu.bd; amitkar763@gmail.com; shihab.duengg@bec.edu.bd; mahfujreaz.duengg@bec.edu.bd; piyaldas9210@gmail.com | F65: aditya.duengg@bec.edu.bd | H65: =IF(TRIM(G65)="","No","Yes") -> No | I65: =IF(TRIM(G65)="","",COUNTIFS($G$2:G65,G65)) | J65: =IF(OR($A65="",TRIM($G65)=""),"",IFERROR(IF(INDEX(INDIRECT("'"&$G65&"'!F1:F100"),MATCH($A65,INDIRECT("'"&$G65&"'!A1:A100"),0))="","",INDEX(INDIRECT("'"&$G65&"'!F1:F100"),MATCH($A65,INDIRECT("'"&$G65&"'!A1:A100"),0))),"")) | L65: =IF(COUNT(J65:K65)<2,"",J65+K65) | M65: =IF(L65="","",RANK(L65,$L$2:$L$201,0))
A66: 323 | B66: Smart Systems | C66: Computer Vision and Kalman Filtering for Driverless Vehicle Steering Angle Computation | D66: Abdullah Al Niloy (Canadian University of Bangladesh)*; Md Sabbir Hossain (Canadian University of Bangladesh); Md. Akhtaruzzaman (Canadian University of Bangladesh); Md. Ziad Hosain (Canadian University of Bangladesh); Md. Mahmudul Hasan (Canadian University of Bangladesh); Md. Siddik (Independent University) | E66: abdullah0186373@gmail.com; sabbirhossain756389@gmail.com; mdakhtaruzzamanhridoy@gmail.com; ziad.hosain@gmail.com; mahmudulhasan14222@gmail.com; jahidsiddik85@gmail.com | F66: abdullah0186373@gmail.com | G66: T4P2 | H66: =IF(TRIM(G66)="","No","Yes") -> Yes | I66: =IF(TRIM(G66)="","",COUNTIFS($G$2:G66,G66)) -> 3 | J66: =IF(OR($A66="",TRIM($G66)=""),"",IFERROR(IF(INDEX(INDIRECT("'"&$G66&"'!F1:F100"),MATCH($A66,INDIRECT("'"&$G66&"'!A1:A100"),0))="","",INDEX(INDIRECT("'"&$G66&"'!F1:F100"),MATCH($A66,INDIRECT("'"&$G66&"'!A1:A100"),0))),"")) | L66: =IF(COUNT(J66:K66)<2,"",J66+K66) | M66: =IF(L66="","",RANK(L66,$L$2:$L$201,0))
A67: 341 | B67: Smart Systems | C67: An Integrated Dual-Module Cyber Physical System for Motorcycle Safety: Utilizing Pre-Ride Safety, Crash Detection and Swift Response with Mobile Application Companion | D67: Md Hasan (BUET)*; Erom Hasan Niha (BUET); Md. Amir Hamza (BUET); Ayon Kumer Dea (BUET) | E67: 2006146@eee.buet.ac.bd; 2006144@eee.buet.ac.bd; 2006145@eee.buet.ac.bd; 2006147@eee.buet.ac.bd | F67: 2006146@eee.buet.ac.bd | G67: T4P2 | H67: =IF(TRIM(G67)="","No","Yes") -> Yes | I67: =IF(TRIM(G67)="","",COUNTIFS($G$2:G67,G67)) -> 4 | J67: =IF(OR($A67="",TRIM($G67)=""),"",IFERROR(IF(INDEX(INDIRECT("'"&$G67&"'!F1:F100"),MATCH($A67,INDIRECT("'"&$G67&"'!A1:A100"),0))="","",INDEX(INDIRECT("'"&$G67&"'!F1:F100"),MATCH($A67,INDIRECT("'"&$G67&"'!A1:A100"),0))),"")) | L67: =IF(COUNT(J67:K67)<2,"",J67+K67) | M67: =IF(L67="","",RANK(L67,$L$2:$L$201,0))
A68: 367 | B68: Smart Systems | C68: A Low-Cost IoT-Based Smart Home Automation and Security System with Energy-Efficient Operation for Sustainable Living in Developing Regions | D68: Md. Masum Latif Chowdhury (University of Liberal Arts Bangladesh (ULAB))*; Md. Rajib Hossain (University of Liberal Arts Bangladesh (ULAB)); Nur Atika Mim (University of Liberal Arts Bangladesh (ULAB)); Sabbir Sarder (University of Liberal Arts Bangladesh (ULAB)); Md Raiyan Ahmed Panto (University of Liberal Arts Bangladesh (ULAB)); A O M Shamsuddoha (University of Liberal Arts Bangladesh (ULAB)) | E68: masum.latif.eee@ulab.edu.bd; rajib.hossain.eee@ulab.edu.bd; nur.atika.eee@ulab.edu.bd; sabbir.sarder.eee@ulab.edu.bd; raiyan.ahmed.eee@ulab.edu.bd; shamsud.doha@ulab.edu.bd | F68: masum.latif.eee@ulab.edu.bd | G68: T2P4 | H68: =IF(TRIM(G68)="","No","Yes") -> Yes | I68: =IF(TRIM(G68)="","",COUNTIFS($G$2:G68,G68)) -> 5 | J68: =IF(OR($A68="",TRIM($G68)=""),"",IFERROR(IF(INDEX(INDIRECT("'"&$G68&"'!F1:F100"),MATCH($A68,INDIRECT("'"&$G68&"'!A1:A100"),0))="","",INDEX(INDIRECT("'"&$G68&"'!F1:F100"),MATCH($A68,INDIRECT("'"&$G68&"'!A1:A100"),0))),"")) | L68: =IF(COUNT(J68:K68)<2,"",J68+K68) | M68: =IF(L68="","",RANK(L68,$L$2:$L$201,0))
A69: 33 | B69: Wireless and Optical Communication | C69: Performance Analysis of RIS-Assisted 6G Wireless Systems with Hybrid Architectures and Hardware Constraints | D69: Md Hossam-E-Haider (Military Institute of Science & Technology); Md. Rafiul Islam Talukder (Military Institute of Science & Technology); Md. Mehedi Hasan Khan Apurbo (Military Institute of Science & Technology); Samia Rahman (Military Institute of Science & Technology )*; Nusrat Jahan Neela Monika (Military Institute of Science & Technology) | E69: haider@eece.mist.ac.bd; rafiulriad44@gmail.com; apurpohossain472@gmail.com; rsamia5594@gmail.com; nusratnila204@gmail.com | F69: rsamia5594@gmail.com | G69: T1P3 | H69: =IF(TRIM(G69)="","No","Yes") -> Yes | I69: =IF(TRIM(G69)="","",COUNTIFS($G$2:G69,G69)) -> 1 | J69: =IF(OR($A69="",TRIM($G69)=""),"",IFERROR(IF(INDEX(INDIRECT("'"&$G69&"'!F1:F100"),MATCH($A69,INDIRECT("'"&$G69&"'!A1:A100"),0))="","",INDEX(INDIRECT("'"&$G69&"'!F1:F100"),MATCH($A69,INDIRECT("'"&$G69&"'!A1:A100"),0))),"")) | L69: =IF(COUNT(J69:K69)<2,"",J69+K69) | M69: =IF(L69="","",RANK(L69,$L$2:$L$201,0))
A70: 80 | B70: Wireless and Optical Communication | C70: An Explainable Telecom Network Fault Prediction Using BiLSTM-Attention Framework and SHAP | D70: Shuvro Debnath (CUET, Chittagong university of engineering and technology); Suriaya Perven (CUET, Chittagong university of engineering and technology); Mostofa Khalid Bin Sams (CUET, Chittagong university of engineering and technology); Mahfuzulhoq Chowdhury (Chittagong University of Engineering & Technology)* | E70: u2104108@student.cuet.ac.bd; u2104103@student.cuet.ac.bd; u2103092@student.cuet.ac.bd; mahfuz_csecuet@yahoo.com | F70: mahfuz_csecuet@yahoo.com | H70: =IF(TRIM(G70)="","No","Yes") -> No | I70: =IF(TRIM(G70)="","",COUNTIFS($G$2:G70,G70)) | J70: =IF(OR($A70="",TRIM($G70)=""),"",IFERROR(IF(INDEX(INDIRECT("'"&$G70&"'!F1:F100"),MATCH($A70,INDIRECT("'"&$G70&"'!A1:A100"),0))="","",INDEX(INDIRECT("'"&$G70&"'!F1:F100"),MATCH($A70,INDIRECT("'"&$G70&"'!A1:A100"),0))),"")) | L70: =IF(COUNT(J70:K70)<2,"",J70+K70) | M70: =IF(L70="","",RANK(L70,$L$2:$L$201,0))
A71: 97 | B71: Wireless and Optical Communication | C71: Adaptive LMS Based Channel Estimation for OFDM Systems under Time Varying Doppler Fading | D71: MD IFTAKHAR AHSAN JARIF (American International University Bangladesh (AIUB))*; Bishwajit Banik Pathik (American International University-Bangladesh(AIUB)) | E71: 23-50727-1@student.aiub.edu; bishwajit@aiub.edu | F71: 23-50727-1@student.aiub.edu | H71: =IF(TRIM(G71)="","No","Yes") -> No | I71: =IF(TRIM(G71)="","",COUNTIFS($G$2:G71,G71)) | J71: =IF(OR($A71="",TRIM($G71)=""),"",IFERROR(IF(INDEX(INDIRECT("'"&$G71&"'!F1:F100"),MATCH($A71,INDIRECT("'"&$G71&"'!A1:A100"),0))="","",INDEX(INDIRECT("'"&$G71&"'!F1:F100"),MATCH($A71,INDIRECT("'"&$G71&"'!A1:A100"),0))),"")) | L71: =IF(COUNT(J71:K71)<2,"",J71+K71) | M71: =IF(L71="","",RANK(L71,$L$2:$L$201,0))
A72: 116 | B72: Wireless and Optical Communication | C72: Novel Microstrip-fed Implantable Antenna Design Operating at 5.85 GHz for Medical Applications | D72: Dr. Mohammad Khan (North South University)*; Sadman Ishraq (North South University); MA Sheam (North South University); Ayatullah Hasnat Behesti (North South University) | E72: monirkhan.qmul@gmail.com; sadman.ishraq@northsouth.edu; sheam1720@gmail.com; ayatullah.behesti@northsouth.edu | F72: monirkhan.qmul@gmail.com | G72: T1P3 | H72: =IF(TRIM(G72)="","No","Yes") -> Yes | I72: =IF(TRIM(G72)="","",COUNTIFS($G$2:G72,G72)) -> 2 | J72: =IF(OR($A72="",TRIM($G72)=""),"",IFERROR(IF(INDEX(INDIRECT("'"&$G72&"'!F1:F100"),MATCH($A72,INDIRECT("'"&$G72&"'!A1:A100"),0))="","",INDEX(INDIRECT("'"&$G72&"'!F1:F100"),MATCH($A72,INDIRECT("'"&$G72&"'!A1:A100"),0))),"")) | L72: =IF(COUNT(J72:K72)<2,"",J72+K72) | M72: =IF(L72="","",RANK(L72,$L$2:$L$201,0))
A73: 136 | B73: Wireless and Optical Communication | C73: An X-Band 2×2 MIMO Antenna Array with Enhanced Beamforming and Radiation Performance | D73: Sohanur Sohag (Uttara University )*; Anoy Roy (Chittagong university of engineering and technology); Rahul Barua (National University); Nea Jaw Rakhine (University of Chittagong); Md. Rakib Uddin (Uttara University); Md. Ashraful Haque (University of Liberal Arts Bangladesh ) | E73: sohanur.rs1@uttarauniversity.edu.bd; anoyroy.eee@gmail.com; rahulbarua349@gmail.com; neajawrakhine@gmail.com; rakibuddin2202@gmail.com; limon.ashraf@gmail.com | F73: sohanur.rs1@uttarauniversity.edu.bd | G73: T1P3 | H73: =IF(TRIM(G73)="","No","Yes") -> Yes | I73: =IF(TRIM(G73)="","",COUNTIFS($G$2:G73,G73)) -> 3 | J73: =IF(OR($A73="",TRIM($G73)=""),"",IFERROR(IF(INDEX(INDIRECT("'"&$G73&"'!F1:F100"),MATCH($A73,INDIRECT("'"&$G73&"'!A1:A100"),0))="","",INDEX(INDIRECT("'"&$G73&"'!F1:F100"),MATCH($A73,INDIRECT("'"&$G73&"'!A1:A100"),0))),"")) | L73: =IF(COUNT(J73:K73)<2,"",J73+K73) | M73: =IF(L73="","",RANK(L73,$L$2:$L$201,0))
A74: 175 | B74: Wireless and Optical Communication | C74: Isolation-Wall Integrated Graphene THz MIMO Antenna with Wideband and High-Diversity Performance for 6G Applications | D74: Tanvir Ahmed Fahim (Bangladesh Army International University of Science and Technology, Cumilla)*; Md. Abdullah-Al- Mamun (Bangladesh Army International University of Science and Technology, Cumilla); Md. Gulam Mustafa (Bangladesh Army International University of Science and Technology, Cumilla); Joton Kumar Dea (Bangladesh Army International University of Science and Technology, Cumilla); Md. Ashraful Haque (University of Liberal Arts Bangladesh, Dhaka) | E74: www.fahim116@gmail.com; mamunal59@gmail.com; mustafaredwan1996@gmail.com; jotonkumardea@gmail.com; limon.ashraf@gmail.com | F74: www.fahim116@gmail.com | G74: T4P2 | H74: =IF(TRIM(G74)="","No","Yes") -> Yes | I74: =IF(TRIM(G74)="","",COUNTIFS($G$2:G74,G74)) -> 5 | J74: =IF(OR($A74="",TRIM($G74)=""),"",IFERROR(IF(INDEX(INDIRECT("'"&$G74&"'!F1:F100"),MATCH($A74,INDIRECT("'"&$G74&"'!A1:A100"),0))="","",INDEX(INDIRECT("'"&$G74&"'!F1:F100"),MATCH($A74,INDIRECT("'"&$G74&"'!A1:A100"),0))),"")) | L74: =IF(COUNT(J74:K74)<2,"",J74+K74) | M74: =IF(L74="","",RANK(L74,$L$2:$L$201,0))
A75: 217 | B75: Wireless and Optical Communication | C75: AFDM-Aided PD-NOMA with Dynamic Power Allocation for High-Mobility THz Communications | D75: Md. Maharaj Kabir (Khulna University); Mohammad Ismat Kadir (Khulna University)* | E75: msc250909@ku.ac.bd; ismat.kadir@ece.ku.ac.bd | F75: ismat.kadir@ece.ku.ac.bd | G75: T1P2 | H75: =IF(TRIM(G75)="","No","Yes") -> Yes | I75: =IF(TRIM(G75)="","",COUNTIFS($G$2:G75,G75)) -> 3 | J75: =IF(OR($A75="",TRIM($G75)=""),"",IFERROR(IF(INDEX(INDIRECT("'"&$G75&"'!F1:F100"),MATCH($A75,INDIRECT("'"&$G75&"'!A1:A100"),0))="","",INDEX(INDIRECT("'"&$G75&"'!F1:F100"),MATCH($A75,INDIRECT("'"&$G75&"'!A1:A100"),0))),"")) | L75: =IF(COUNT(J75:K75)<2,"",J75+K75) | M75: =IF(L75="","",RANK(L75,$L$2:$L$201,0))
A76: 228 | B76: Wireless and Optical Communication | C76: Side-Fed Circular Slotted BD Flag-Shaped Antenna with DGS for Sub-6 GHz IoT and Smart Wireless Applications | D76: Md Sohel Pervez (Pabna University of Science and Technology); Naymaa Rashid (Pabna University of Science and Technology); Md. Ashraful Haque (University of Liberal Arts Bangladesh); Sajeeb Chandra Das (TH Cologne University of Applied Sciences); Tithi Rani (Rajshahi University of Science and Technology); Liton Chandra Paul (Pabna University of Science and Technology)* | E76: sohel.pervezpust@gmail.com; naymaa.rashid.mrittika@gmail.com; limon.ashraf@gmail.com; sajeebchandradas@gmail.com; tithi.saha.134040@gmail.com; litonpaulete@gmail.com | F76: litonpaulete@gmail.com | G76: T4P2 | H76: =IF(TRIM(G76)="","No","Yes") -> Yes | I76: =IF(TRIM(G76)="","",COUNTIFS($G$2:G76,G76)) -> 6 | J76: =IF(OR($A76="",TRIM($G76)=""),"",IFERROR(IF(INDEX(INDIRECT("'"&$G76&"'!F1:F100"),MATCH($A76,INDIRECT("'"&$G76&"'!A1:A100"),0))="","",INDEX(INDIRECT("'"&$G76&"'!F1:F100"),MATCH($A76,INDIRECT("'"&$G76&"'!A1:A100"),0))),"")) | L76: =IF(COUNT(J76:K76)<2,"",J76+K76) | M76: =IF(L76="","",RANK(L76,$L$2:$L$201,0))
A77: 326 | B77: Wireless and Optical Communication | C77: Design and Analysis of a Conformal Frequency and Pattern Reconfigurable Antenna for Wearable Applications | D77: AL-MAHRUF RAHMAN (Rajshahi University of Engineering and Technology)*; MD. HEDAYETULLAH (Mymensingh Engineering College); ABU SADAT MD. SAYEM (The University of Queensland) | E77: mahruf.eee.ruet@gmail.com; hedayetullahz1324@gmail.com; sayem@eee.ruet.ac.bd | F77: mahruf.eee.ruet@gmail.com | H77: =IF(TRIM(G77)="","No","Yes") -> No | I77: =IF(TRIM(G77)="","",COUNTIFS($G$2:G77,G77)) | J77: =IF(OR($A77="",TRIM($G77)=""),"",IFERROR(IF(INDEX(INDIRECT("'"&$G77&"'!F1:F100"),MATCH($A77,INDIRECT("'"&$G77&"'!A1:A100"),0))="","",INDEX(INDIRECT("'"&$G77&"'!F1:F100"),MATCH($A77,INDIRECT("'"&$G77&"'!A1:A100"),0))),"")) | L77: =IF(COUNT(J77:K77)<2,"",J77+K77) | M77: =IF(L77="","",RANK(L77,$L$2:$L$201,0))
A78: 85 | B78: Electronics and Nanotechnology | C78: Multi-Metaheuristic Optimisation of Cascade Controllers for DC-DC Converters: A Comparative Study of PI, PID, and Sliding Mode Control | D78: Md Maniruz Zaman (Bangladesh University of Engineering and Technology)*; Jiad Bin Asad (Uttara University); Amit Das (Uttara University); Md. Shamsul Islam (Uttara University); Md. Mehedi Hasan Tusar (Uttara University); Uttam Mahapatra (Uttara University) | E78: mmzaman.ruet@gmail.com; jiadbinasad@gmail.com; amit.das.ruet@gmail.com; islamshamsul127@gmail.com; its.mehedi.eee@gmail.com; uttammahapatra211@gmail.com | F78: mmzaman.ruet@gmail.com | G78: T4P3 | H78: =IF(TRIM(G78)="","No","Yes") -> Yes | I78: =IF(TRIM(G78)="","",COUNTIFS($G$2:G78,G78)) -> 2 | J78: =IF(OR($A78="",TRIM($G78)=""),"",IFERROR(IF(INDEX(INDIRECT("'"&$G78&"'!F1:F100"),MATCH($A78,INDIRECT("'"&$G78&"'!A1:A100"),0))="","",INDEX(INDIRECT("'"&$G78&"'!F1:F100"),MATCH($A78,INDIRECT("'"&$G78&"'!A1:A100"),0))),"")) | L78: =IF(COUNT(J78:K78)<2,"",J78+K78) | M78: =IF(L78="","",RANK(L78,$L$2:$L$201,0))
A79: 148 | B79: Electronics and Nanotechnology | C79: Cross-Design Limitations of ML-Based PPA Prediction in OpenLane | D79: Atair Rahman Alvi (BRAC University)*; Tahmid Noor Rahman (BRAC University); Ifrana Hamim (BRAC University); Md. Siam Khan Niloy (AIUB) | E79: alvialvi91@gmail.com; tahmid5555@gmail.com; hamimifrana@gmail.com; mdsiamkhanniloy@gmail.com | F79: alvialvi91@gmail.com | G79: T4P3 | H79: =IF(TRIM(G79)="","No","Yes") -> Yes | I79: =IF(TRIM(G79)="","",COUNTIFS($G$2:G79,G79)) -> 3 | J79: =IF(OR($A79="",TRIM($G79)=""),"",IFERROR(IF(INDEX(INDIRECT("'"&$G79&"'!F1:F100"),MATCH($A79,INDIRECT("'"&$G79&"'!A1:A100"),0))="","",INDEX(INDIRECT("'"&$G79&"'!F1:F100"),MATCH($A79,INDIRECT("'"&$G79&"'!A1:A100"),0))),"")) | L79: =IF(COUNT(J79:K79)<2,"",J79+K79) | M79: =IF(L79="","",RANK(L79,$L$2:$L$201,0))
A80: 160 | B80: Electronics and Nanotechnology | C80: Numerical Investigation of a Corrugated PDMS Diaphragm-based Fiber Optic Fabry-Perot Sensor for Acoustic Sensing | D80: Sinthia Islam (Khulna University of Engineering & Technology)*; Dr. Md Jahirul Islam ( Khulna University of Engineering & Technology); Nafisa Pervin (Khulna University of Engineering & Technology) | E80: islam1903063@stud.kuet.ac.bd; jahirul@eee.kuet.ac.bd; pervin1903041@stud.kuet.ac.bd | F80: islam1903063@stud.kuet.ac.bd | G80: T2P2 | H80: =IF(TRIM(G80)="","No","Yes") -> Yes | I80: =IF(TRIM(G80)="","",COUNTIFS($G$2:G80,G80)) -> 5 | J80: =IF(OR($A80="",TRIM($G80)=""),"",IFERROR(IF(INDEX(INDIRECT("'"&$G80&"'!F1:F100"),MATCH($A80,INDIRECT("'"&$G80&"'!A1:A100"),0))="","",INDEX(INDIRECT("'"&$G80&"'!F1:F100"),MATCH($A80,INDIRECT("'"&$G80&"'!A1:A100"),0))),"")) | L80: =IF(COUNT(J80:K80)<2,"",J80+K80) | M80: =IF(L80="","",RANK(L80,$L$2:$L$201,0))
A81: 210 | B81: Electronics and Nanotechnology | C81: A 16.1-fJ/conv.-step 8-bit 100-MS/s SAR ADC for WLAN Receiver Baseband in 65-nm CMOS | D81: Junayet Hossain (BUET)*; Mithon Rahman (BUET) | E81: junayethossain260@gmail.com; mithonrahman24@gmail.com | F81: junayethossain260@gmail.com | G81: T2P2 | H81: =IF(TRIM(G81)="","No","Yes") -> Yes | I81: =IF(TRIM(G81)="","",COUNTIFS($G$2:G81,G81)) -> 6 | J81: =IF(OR($A81="",TRIM($G81)=""),"",IFERROR(IF(INDEX(INDIRECT("'"&$G81&"'!F1:F100"),MATCH($A81,INDIRECT("'"&$G81&"'!A1:A100"),0))="","",INDEX(INDIRECT("'"&$G81&"'!F1:F100"),MATCH($A81,INDIRECT("'"&$G81&"'!A1:A100"),0))),"")) | L81: =IF(COUNT(J81:K81)<2,"",J81+K81) | M81: =IF(L81="","",RANK(L81,$L$2:$L$201,0))
A82: 255 | B82: Electronics and Nanotechnology | C82: A Unified MOPSO-Optimized Cascade Control Framework for DC–DC Boost Converters: Comparative Evaluation of PI, PID, Sliding Mode, and Finite-Control-Set MPC | D82: Md Maniruz Zaman (Bangladesh University of Engineering and Technology)*; Jiad Bin Asad (Uttara University); Amit Das (Uttara University); Md. Shamsul Islam (Uttara University); Md. Mehedi Hasan Tusar (Uttara University); Uttam Mahapatra (Uttara University) | E82: mmzaman.ruet@gmail.com; jiadbinasad@gmail.com; amit.das.ruet@gmail.com; islamshamsul127@gmail.com; its.mehedi.eee@gmail.com; uttammahapatra211@gmail.com | F82: mmzaman.ruet@gmail.com | H82: =IF(TRIM(G82)="","No","Yes") -> No | I82: =IF(TRIM(G82)="","",COUNTIFS($G$2:G82,G82)) | J82: =IF(OR($A82="",TRIM($G82)=""),"",IFERROR(IF(INDEX(INDIRECT("'"&$G82&"'!F1:F100"),MATCH($A82,INDIRECT("'"&$G82&"'!A1:A100"),0))="","",INDEX(INDIRECT("'"&$G82&"'!F1:F100"),MATCH($A82,INDIRECT("'"&$G82&"'!A1:A100"),0))),"")) | L82: =IF(COUNT(J82:K82)<2,"",J82+K82) | M82: =IF(L82="","",RANK(L82,$L$2:$L$201,0))
A83: 274 | B83: Electronics and Nanotechnology | C83: Modulation Strategy for Optimizing Semiconductor Losses for A High Power Step-Down Dual Active Bridge Converter in AI Data Center Applications | D83: Mohammad Reza (Islamic University of Technology )*; Mubeen Chowdhury (Islamic University of Technology ); Nasif Niloy (Islamic University of Technology ) | E83: farhanreza@iut-dhaka.edu; mubeeraisul@iut-dhaka.edu; nasifniloy@iut-dhaka.edu | F83: farhanreza@iut-dhaka.edu | G83: T4P3 | H83: =IF(TRIM(G83)="","No","Yes") -> Yes | I83: =IF(TRIM(G83)="","",COUNTIFS($G$2:G83,G83)) -> 4 | J83: =IF(OR($A83="",TRIM($G83)=""),"",IFERROR(IF(INDEX(INDIRECT("'"&$G83&"'!F1:F100"),MATCH($A83,INDIRECT("'"&$G83&"'!A1:A100"),0))="","",INDEX(INDIRECT("'"&$G83&"'!F1:F100"),MATCH($A83,INDIRECT("'"&$G83&"'!A1:A100"),0))),"")) | L83: =IF(COUNT(J83:K83)<2,"",J83+K83) | M83: =IF(L83="","",RANK(L83,$L$2:$L$201,0))
A84: 345 | B84: Electronics and Nanotechnology | C84: An Au/ITO Dual-Layer Photonic Crystal Fiber Surface Plasmon Resonance Biosensor for Label-Free Detection and Discrimination of Basal, HeLa, and Jurkat Cancer Cells | D84: Samiul Hasan (Independent University)*; Fardous Mahmud (Independent University); Naim Abrar Shaharia ( Independent University); Minhazul Abedin Nabil (Independent University); Hemal Sharma ( Independent University); Kh Shahriya Zaman ( Independent University); Feroz Ahmed (Independent University) | E84: samiulhasan803@gmail.com; fardousmahmud8@gmail.com; 2221447@iub.edu.bd; 2221738@iub.edu.bd; sharma.hemal14@gmail.com; shahriya@iub.edu.bd; fahmed@iub.edu.bd | F84: samiulhasan803@gmail.com | G84: T4P3 | H84: =IF(TRIM(G84)="","No","Yes") -> Yes | I84: =IF(TRIM(G84)="","",COUNTIFS($G$2:G84,G84)) -> 5 | J84: =IF(OR($A84="",TRIM($G84)=""),"",IFERROR(IF(INDEX(INDIRECT("'"&$G84&"'!F1:F100"),MATCH($A84,INDIRECT("'"&$G84&"'!A1:A100"),0))="","",INDEX(INDIRECT("'"&$G84&"'!F1:F100"),MATCH($A84,INDIRECT("'"&$G84&"'!A1:A100"),0))),"")) | L84: =IF(COUNT(J84:K84)<2,"",J84+K84) | M84: =IF(L84="","",RANK(L84,$L$2:$L$201,0))
A85: 365 | B85: Electronics and Nanotechnology | C85: PSO-Based Selective Harmonic Elimination with Smart Cell-Bypassing for a 15-Level Asymmetric Cascaded H-Bridge Inverter | D85: Hosen Miah (Green University of Bangladesh)*; Md. Ahsanul Alam (Green University of Bangladesh); Md. Asif Hasan (Green University of Bangladesh); Rajoyn Ahmed Rudro (Green University of Bangladesh); Md Zihad Alamin Tashfin (Green University of Bangladesh); Iftekhar Ahmmed (Green University of Bangladesh) | E85: husseinbijoy7@gmail.com; ahsanul@eee.green.edu.bd; asifhasanpl90@gmail.com; rejwanahmedruddro@gmail.com; alaminzihad.mail@gmail.com; iftekhar215ac@gmail.com | F85: husseinbijoy7@gmail.com | G85: T2P1 | H85: =IF(TRIM(G85)="","No","Yes") -> Yes | I85: =IF(TRIM(G85)="","",COUNTIFS($G$2:G85,G85)) -> 5 | J85: =IF(OR($A85="",TRIM($G85)=""),"",IFERROR(IF(INDEX(INDIRECT("'"&$G85&"'!F1:F100"),MATCH($A85,INDIRECT("'"&$G85&"'!A1:A100"),0))="","",INDEX(INDIRECT("'"&$G85&"'!F1:F100"),MATCH($A85,INDIRECT("'"&$G85&"'!A1:A100"),0))),"")) | L85: =IF(COUNT(J85:K85)<2,"",J85+K85) | M85: =IF(L85="","",RANK(L85,$L$2:$L$201,0))
A86: 110 | B86: FinTech and Digital Business Analytics | C86: Uncertainty-Aware Sequential Fraud Detection: A Bayesian Transformer Framework with Dual Explainability and Calibrated Probabilistic Inference | D86: Tanvir Ahmed (Daffodil International University )*; Sharmin Jahan Shithy (Daffodil International University); Md Asraful Islam Jony (Daffodil International University) | E86: tanvir2305341789@diu.edu.bd; shithy1013@gmail.com; jony2305341752@diu.edu.bd | F86: tanvir2305341789@diu.edu.bd | H86: =IF(TRIM(G86)="","No","Yes") -> No | I86: =IF(TRIM(G86)="","",COUNTIFS($G$2:G86,G86)) | J86: =IF(OR($A86="",TRIM($G86)=""),"",IFERROR(IF(INDEX(INDIRECT("'"&$G86&"'!F1:F100"),MATCH($A86,INDIRECT("'"&$G86&"'!A1:A100"),0))="","",INDEX(INDIRECT("'"&$G86&"'!F1:F100"),MATCH($A86,INDIRECT("'"&$G86&"'!A1:A100"),0))),"")) | L86: =IF(COUNT(J86:K86)<2,"",J86+K86) | M86: =IF(L86="","",RANK(L86,$L$2:$L$201,0))
A87: 208 | B87: FinTech and Digital Business Analytics | C87: The Effect of e-KYC Adoption on the Cost Efficiency of Commercial Banks in Bangladesh: A Dynamic Panel Study | D87: Shabab Sabiq (University of Barishal); Progga Biswas Parama (Eden Mohila College); Khadiza Tul Ferdaous (University Of Liberal Arts Bangladesh); Mashiyat Tafannum (University of Dhaka ); Arpita Mistry (Daffodil international University); Maftun Ahommed (University Of Liberal Arts Bangladesh)* | E87: ssabiq18.fin@bu.ac.bd; progga.biswas.mkt@gmail.com; khadiza.ferdaous.bba@ulab.edu.bd; mashiyat-2019512668@fin.du.ac.bd; mistry2304083062@diu.edu.bd; maftun.ahommed.cse@ulab.edu.bd | F87: maftun.ahommed.cse@ulab.edu.bd | G87: T2P3 | H87: =IF(TRIM(G87)="","No","Yes") -> Yes | I87: =IF(TRIM(G87)="","",COUNTIFS($G$2:G87,G87)) -> 5 | J87: =IF(OR($A87="",TRIM($G87)=""),"",IFERROR(IF(INDEX(INDIRECT("'"&$G87&"'!F1:F100"),MATCH($A87,INDIRECT("'"&$G87&"'!A1:A100"),0))="","",INDEX(INDIRECT("'"&$G87&"'!F1:F100"),MATCH($A87,INDIRECT("'"&$G87&"'!A1:A100"),0))),"")) | L87: =IF(COUNT(J87:K87)<2,"",J87+K87) | M87: =IF(L87="","",RANK(L87,$L$2:$L$201,0))
A88: 279 | B88: FinTech and Digital Business Analytics | C88: Programmable Remittances for Bangladesh A Permissioned Blockchain System for Diaspora-Controlled Household Payments | D88: Tanjim Mahmud Rakin (American International University-Bangladesh)*; MD Mushfiqur Rahman Mushfique (Islamic University of Technology) | E88: tanjimmahmudwork@gmail.com; mushfique2@iut-dhaka.edu | F88: tanjimmahmudwork@gmail.com | G88: T4P4 | H88: =IF(TRIM(G88)="","No","Yes") -> Yes | I88: =IF(TRIM(G88)="","",COUNTIFS($G$2:G88,G88)) -> 7 | J88: =IF(OR($A88="",TRIM($G88)=""),"",IFERROR(IF(INDEX(INDIRECT("'"&$G88&"'!F1:F100"),MATCH($A88,INDIRECT("'"&$G88&"'!A1:A100"),0))="","",INDEX(INDIRECT("'"&$G88&"'!F1:F100"),MATCH($A88,INDIRECT("'"&$G88&"'!A1:A100"),0))),"")) | L88: =IF(COUNT(J88:K88)<2,"",J88+K88) | M88: =IF(L88="","",RANK(L88,$L$2:$L$201,0))
A89: 280 | B89: FinTech and Digital Business Analytics | C89: Architectural Differences among MFS, PSP, and PSO in Bangladesh: A Liability–Ledger Reference Model | D89: Tanjim Mahmud Rakin (American International University-Bangladesh)* | E89: tanjimmahmudwork@gmail.com | F89: tanjimmahmudwork@gmail.com | G89: T4P4 | H89: =IF(TRIM(G89)="","No","Yes") -> Yes | I89: =IF(TRIM(G89)="","",COUNTIFS($G$2:G89,G89)) -> 8 | J89: =IF(OR($A89="",TRIM($G89)=""),"",IFERROR(IF(INDEX(INDIRECT("'"&$G89&"'!F1:F100"),MATCH($A89,INDIRECT("'"&$G89&"'!A1:A100"),0))="","",INDEX(INDIRECT("'"&$G89&"'!F1:F100"),MATCH($A89,INDIRECT("'"&$G89&"'!A1:A100"),0))),"")) | L89: =IF(COUNT(J89:K89)<2,"",J89+K89) | M89: =IF(L89="","",RANK(L89,$L$2:$L$201,0))
A90: 307 | B90: FinTech and Digital Business Analytics | C90: FinTech and Digital Business Analytics: A Reference Framework and Machine-Learning Case Study for Data-Driven Financial Services | D90: SHIVAM SATIJA (Virginia Commonwealth University)* | E90: SATIJAS3@VCU.EDU | F90: SATIJAS3@VCU.EDU | H90: =IF(TRIM(G90)="","No","Yes") -> No | I90: =IF(TRIM(G90)="","",COUNTIFS($G$2:G90,G90)) | J90: =IF(OR($A90="",TRIM($G90)=""),"",IFERROR(IF(INDEX(INDIRECT("'"&$G90&"'!F1:F100"),MATCH($A90,INDIRECT("'"&$G90&"'!A1:A100"),0))="","",INDEX(INDIRECT("'"&$G90&"'!F1:F100"),MATCH($A90,INDIRECT("'"&$G90&"'!A1:A100"),0))),"")) | L90: =IF(COUNT(J90:K90)<2,"",J90+K90) | M90: =IF(L90="","",RANK(L90,$L$2:$L$201,0))
A91: 317 | B91: FinTech and Digital Business Analytics | C91: Adaptive Neuro Weave Ensemble Learning System for Predictive Organizational and Market Analytics | D91: Sangeetha A (Sri Ramakrishna College of Arts and Science)* | E91: priyamca007@gmail.com | F91: priyamca007@gmail.com | H91: =IF(TRIM(G91)="","No","Yes") -> No | I91: =IF(TRIM(G91)="","",COUNTIFS($G$2:G91,G91)) | J91: =IF(OR($A91="",TRIM($G91)=""),"",IFERROR(IF(INDEX(INDIRECT("'"&$G91&"'!F1:F100"),MATCH($A91,INDIRECT("'"&$G91&"'!A1:A100"),0))="","",INDEX(INDIRECT("'"&$G91&"'!F1:F100"),MATCH($A91,INDIRECT("'"&$G91&"'!A1:A100"),0))),"")) | L91: =IF(COUNT(J91:K91)<2,"",J91+K91) | M91: =IF(L91="","",RANK(L91,$L$2:$L$201,0))
A92: 139 | B92: Energy and Sustainability | C92: A Comparative Study of Statistical, Machine Learning, and Deep Learning Models for Short-Term Electricity Load Forecasting on the Bangladesh National Grid | D92: Kazi Shadman Sakib (University of Dhaka); Syeda Tamima Sama Parsa (Sylhet Engineering College); Mubinur Rashid Tahjib (Sylhet Engineering College)*; Md. Shahid Iqbal (Mymensingh Engineering College) | E92: kazishadman-2017614973@cs.du.ac.bd; syeda.parsa@sec.ac.bd; mubinur.tahjib@sec.ac.bd; iqbal@mec.ac.bd | F92: mubinur.tahjib@sec.ac.bd | G92: T4P3 | H92: =IF(TRIM(G92)="","No","Yes") -> Yes | I92: =IF(TRIM(G92)="","",COUNTIFS($G$2:G92,G92)) -> 6 | J92: =IF(OR($A92="",TRIM($G92)=""),"",IFERROR(IF(INDEX(INDIRECT("'"&$G92&"'!F1:F100"),MATCH($A92,INDIRECT("'"&$G92&"'!A1:A100"),0))="","",INDEX(INDIRECT("'"&$G92&"'!F1:F100"),MATCH($A92,INDIRECT("'"&$G92&"'!A1:A100"),0))),"")) | L92: =IF(COUNT(J92:K92)<2,"",J92+K92) | M92: =IF(L92="","",RANK(L92,$L$2:$L$201,0))
A93: 282 | B93: Energy and Sustainability | C93: Floating Solar on an Oxbow Lake: Energy, Water, and Rice Co-Benefits at Bergobindopur Baor, Bangladesh | D93: Md Saqlain Mustak Saki (Green University of Bangladesh)*; Md Shoab Khan (Green University of Bangladesh); Md Hujaifa Ahmmed Tanvir (Green University of Bangladesh); ASM Shihavuddin (Green University of Bangladesh) | E93: saqlainm1307@gmail.com; shoabkhan788@gmail.com; hujaifaahmmedtanvir322@gmail.com; shihav@eee.green.edu.bd | F93: saqlainm1307@gmail.com | G93: T2P4 | H93: =IF(TRIM(G93)="","No","Yes") -> Yes | I93: =IF(TRIM(G93)="","",COUNTIFS($G$2:G93,G93)) -> 6 | J93: =IF(OR($A93="",TRIM($G93)=""),"",IFERROR(IF(INDEX(INDIRECT("'"&$G93&"'!F1:F100"),MATCH($A93,INDIRECT("'"&$G93&"'!A1:A100"),0))="","",INDEX(INDIRECT("'"&$G93&"'!F1:F100"),MATCH($A93,INDIRECT("'"&$G93&"'!A1:A100"),0))),"")) | L93: =IF(COUNT(J93:K93)<2,"",J93+K93) | M93: =IF(L93="","",RANK(L93,$L$2:$L$201,0))
A94: 187 | B94: Digital Learning Technologies | C94: Design of a generative AI agent as a learning support tool for special education needs students | D94: Franciszek Gorczyca (GradeAid); Md Saifuddin Khalid (Technical University of Denmark)* | E94: franciszek@gradeaid.ai; skhalid@dtu.dk | F94: skhalid@dtu.dk | G94: T2P2 | H94: =IF(TRIM(G94)="","No","Yes") -> Yes | I94: =IF(TRIM(G94)="","",COUNTIFS($G$2:G94,G94)) -> 7 | J94: =IF(OR($A94="",TRIM($G94)=""),"",IFERROR(IF(INDEX(INDIRECT("'"&$G94&"'!F1:F100"),MATCH($A94,INDIRECT("'"&$G94&"'!A1:A100"),0))="","",INDEX(INDIRECT("'"&$G94&"'!F1:F100"),MATCH($A94,INDIRECT("'"&$G94&"'!A1:A100"),0))),"")) | L94: =IF(COUNT(J94:K94)<2,"",J94+K94) | M94: =IF(L94="","",RANK(L94,$L$2:$L$201,0))
A95: 223 | B95: Digital Learning Technologies | C95: Technical Challenges and Solutions for Building Augmented Reality for Education | D95: Mohammed Oussama Seddini (Le Mans Université); Mohamed Ez-Zaouia (University of Rennes); Mohamed Hamza Falih (Le Mans Université); Iza Marfisi (Le Mans Université); Md Saifuddin Khalid (Technical University of Denmark)* | E95: Mohammed_Oussama.Seddini.Etu@univ-lemans.fr; mohamed.ez-zaouia@univ-rennes.fr; Mohamed_Hamza.Falih@univ-lemans.fr; iza.marfisi@univ-lemans.fr; skhalid@dtu.dk | F95: skhalid@dtu.dk | H95: =IF(TRIM(G95)="","No","Yes") -> No | I95: =IF(TRIM(G95)="","",COUNTIFS($G$2:G95,G95)) | J95: =IF(OR($A95="",TRIM($G95)=""),"",IFERROR(IF(INDEX(INDIRECT("'"&$G95&"'!F1:F100"),MATCH($A95,INDIRECT("'"&$G95&"'!A1:A100"),0))="","",INDEX(INDIRECT("'"&$G95&"'!F1:F100"),MATCH($A95,INDIRECT("'"&$G95&"'!A1:A100"),0))),"")) | L95: =IF(COUNT(J95:K95)<2,"",J95+K95) | M95: =IF(L95="","",RANK(L95,$L$2:$L$201,0))
A96: 230 | B96: Digital Learning Technologies | C96: Comparing local GPT and Student Performance on Introductory Statistics MCQ Examinations | D96: Nipa Chowdhury (Technical University of Denmark (DTU)); Sumaya Ahmed Promi (Technical University of Denmark (DTU)); Nicolai Siim Larsen (Technical University of Denmark (DTU)); Md Saifuddin Khalid (Technical University of Denmark)* | E96: nipachynipu@gmail.com; promi9425@gmail.com; nisi@dtu.dk; skhalid@dtu.dk | F96: skhalid@dtu.dk | G96: T2P1 | H96: =IF(TRIM(G96)="","No","Yes") -> Yes | I96: =IF(TRIM(G96)="","",COUNTIFS($G$2:G96,G96)) -> 6 | J96: =IF(OR($A96="",TRIM($G96)=""),"",IFERROR(IF(INDEX(INDIRECT("'"&$G96&"'!F1:F100"),MATCH($A96,INDIRECT("'"&$G96&"'!A1:A100"),0))="","",INDEX(INDIRECT("'"&$G96&"'!F1:F100"),MATCH($A96,INDIRECT("'"&$G96&"'!A1:A100"),0))),"")) | L96: =IF(COUNT(J96:K96)<2,"",J96+K96) | M96: =IF(L96="","",RANK(L96,$L$2:$L$201,0))
A97: 276 | B97: Digital Learning Technologies | C97: An Interpretable Ensemble Learning Framework for Predicting Students' Entrepreneurial Intention in Digital Entrepreneurship Education | D97: K. M. Arafat Islam (Daffodil International University)*; Abdul Fardaus (Green University of Bangladesh) | E97: islam15-5498@diu.edu.bd; abdulfardaus0@gmail.com | F97: islam15-5498@diu.edu.bd | G97: T2P4 | H97: =IF(TRIM(G97)="","No","Yes") -> Yes | I97: =IF(TRIM(G97)="","",COUNTIFS($G$2:G97,G97)) -> 7 | J97: =IF(OR($A97="",TRIM($G97)=""),"",IFERROR(IF(INDEX(INDIRECT("'"&$G97&"'!F1:F100"),MATCH($A97,INDIRECT("'"&$G97&"'!A1:A100"),0))="","",INDEX(INDIRECT("'"&$G97&"'!F1:F100"),MATCH($A97,INDIRECT("'"&$G97&"'!A1:A100"),0))),"")) | L97: =IF(COUNT(J97:K97)<2,"",J97+K97) | M97: =IF(L97="","",RANK(L97,$L$2:$L$201,0))
A98: 295 | B98: Digital Learning Technologies | C98: A Dual-Focus UX Prioritization Framework for Educational Games Using Sentiment Analysis | D98: Mohammed Ashikur Rahman (Southeast Universuty)*; Md Kowsar Ahmed (University Malaya) | E98: ashikur.rahman@seu.edu.bd; kowsar2311@gmail.com | F98: ashikur.rahman@seu.edu.bd | G98: T4P2 | H98: =IF(TRIM(G98)="","No","Yes") -> Yes | I98: =IF(TRIM(G98)="","",COUNTIFS($G$2:G98,G98)) -> 7 | J98: =IF(OR($A98="",TRIM($G98)=""),"",IFERROR(IF(INDEX(INDIRECT("'"&$G98&"'!F1:F100"),MATCH($A98,INDIRECT("'"&$G98&"'!A1:A100"),0))="","",INDEX(INDIRECT("'"&$G98&"'!F1:F100"),MATCH($A98,INDIRECT("'"&$G98&"'!A1:A100"),0))),"")) | L98: =IF(COUNT(J98:K98)<2,"",J98+K98) | M98: =IF(L98="","",RANK(L98,$L$2:$L$201,0))
H99: =IF(TRIM(G99)="","No","Yes") -> No | I99: =IF(TRIM(G99)="","",COUNTIFS($G$2:G99,G99)) | J99: =IF(OR($A99="",TRIM($G99)=""),"",IFERROR(IF(INDEX(INDIRECT("'"&$G99&"'!F1:F100"),MATCH($A99,INDIRECT("'"&$G99&"'!A1:A100"),0))="","",INDEX(INDIRECT("'"&$G99&"'!F1:F100"),MATCH($A99,INDIRECT("'"&$G99&"'!A1:A100"),0))),"")) | L99: =IF(COUNT(J99:K99)<2,"",J99+K99) | M99: =IF(L99="","",RANK(L99,$L$2:$L$201,0))
H100: =IF(TRIM(G100)="","No","Yes") -> No | I100: =IF(TRIM(G100)="","",COUNTIFS($G$2:G100,G100)) | J100: =IF(OR($A100="",TRIM($G100)=""),"",IFERROR(IF(INDEX(INDIRECT("'"&$G100&"'!F1:F100"),MATCH($A100,INDIRECT("'"&$G100&"'!A1:A100"),0))="","",INDEX(INDIRECT("'"&$G100&"'!F1:F100"),MATCH($A100,INDIRECT("'"&$G100&"'!A1:A100"),0))),"")) | L100: =IF(COUNT(J100:K100)<2,"",J100+K100) | M100: =IF(L100="","",RANK(L100,$L$2:$L$201,0))
...

Sheet Session Overview
A1: Session Code | B1: Type | C1: Papers Assigned | D1: Paper Capacity | E1: Paper Status | F1: Chairs Assigned | G1: Senior Faculty Assigned | H1: Junior Faculty Assigned
A2: ='_Lists'!$B$2 -> T1P1 | B2: =IF(LEFT(A2,1)="T","Technical Parallel Session",IF(LEFT(A2,7)="Keynote","Keynote Session",IF(A2="IEEE Workshop","Workshop",""))) -> Technical Parallel Session | C2: =IF(B2="Technical Parallel Session",COUNTIF(Papers!$G$2:$G$201,A2),"-") -> 3 | D2: =IF(LEFT(A2,2)="T1",4,IF(OR(LEFT(A2,2)="T2",LEFT(A2,2)="T3",LEFT(A2,2)="T4"),8,"-")) -> 4 | E2: =IF(D2="-","-",IF(C2>D2,"Over Capacity",IF(C2=D2,"Full","Open ("&D2-C2&" slots left)"))) -> Open (1 slots left) | F2: =COUNTIF(Chairs!$K$2:$K$359,A2) -> 1 | G2: =COUNTIF('Senior Faculty'!$K$2:$K$401,A2) -> 1 | H2: =COUNTIF('Junior Faculty'!$K$2:$K$401,A2) -> 2
A3: ='_Lists'!$B$3 -> T1P2 | B3: =IF(LEFT(A3,1)="T","Technical Parallel Session",IF(LEFT(A3,7)="Keynote","Keynote Session",IF(A3="IEEE Workshop","Workshop",""))) -> Technical Parallel Session | C3: =IF(B3="Technical Parallel Session",COUNTIF(Papers!$G$2:$G$201,A3),"-") -> 3 | D3: =IF(LEFT(A3,2)="T1",4,IF(OR(LEFT(A3,2)="T2",LEFT(A3,2)="T3",LEFT(A3,2)="T4"),8,"-")) -> 4 | E3: =IF(D3="-","-",IF(C3>D3,"Over Capacity",IF(C3=D3,"Full","Open ("&D3-C3&" slots left)"))) -> Open (1 slots left) | F3: =COUNTIF(Chairs!$K$2:$K$359,A3) -> 1 | G3: =COUNTIF('Senior Faculty'!$K$2:$K$401,A3) -> 1 | H3: =COUNTIF('Junior Faculty'!$K$2:$K$401,A3) -> 2
A4: ='_Lists'!$B$4 -> T1P3 | B4: =IF(LEFT(A4,1)="T","Technical Parallel Session",IF(LEFT(A4,7)="Keynote","Keynote Session",IF(A4="IEEE Workshop","Workshop",""))) -> Technical Parallel Session | C4: =IF(B4="Technical Parallel Session",COUNTIF(Papers!$G$2:$G$201,A4),"-") -> 3 | D4: =IF(LEFT(A4,2)="T1",4,IF(OR(LEFT(A4,2)="T2",LEFT(A4,2)="T3",LEFT(A4,2)="T4"),8,"-")) -> 4 | E4: =IF(D4="-","-",IF(C4>D4,"Over Capacity",IF(C4=D4,"Full","Open ("&D4-C4&" slots left)"))) -> Open (1 slots left) | F4: =COUNTIF(Chairs!$K$2:$K$359,A4) -> 1 | G4: =COUNTIF('Senior Faculty'!$K$2:$K$401,A4) -> 1 | H4: =COUNTIF('Junior Faculty'!$K$2:$K$401,A4) -> 2
A5: ='_Lists'!$B$5 -> T2P1 | B5: =IF(LEFT(A5,1)="T","Technical Parallel Session",IF(LEFT(A5,7)="Keynote","Keynote Session",IF(A5="IEEE Workshop","Workshop",""))) -> Technical Parallel Session | C5: =IF(B5="Technical Parallel Session",COUNTIF(Papers!$G$2:$G$201,A5),"-") -> 6 | D5: 8 | E5: =IF(D5="-","-",IF(C5>D5,"Over Capacity",IF(C5=D5,"Full","Open ("&D5-C5&" slots left)"))) -> Open (2 slots left) | F5: =COUNTIF(Chairs!$K$2:$K$359,A5) -> 1 | G5: =COUNTIF('Senior Faculty'!$K$2:$K$401,A5) -> 1 | H5: =COUNTIF('Junior Faculty'!$K$2:$K$401,A5) -> 2
A6: ='_Lists'!$B$6 -> T2P2 | B6: =IF(LEFT(A6,1)="T","Technical Parallel Session",IF(LEFT(A6,7)="Keynote","Keynote Session",IF(A6="IEEE Workshop","Workshop",""))) -> Technical Parallel Session | C6: =IF(B6="Technical Parallel Session",COUNTIF(Papers!$G$2:$G$201,A6),"-") -> 7 | D6: 8 | E6: =IF(D6="-","-",IF(C6>D6,"Over Capacity",IF(C6=D6,"Full","Open ("&D6-C6&" slots left)"))) -> Open (1 slots left) | F6: =COUNTIF(Chairs!$K$2:$K$359,A6) -> 1 | G6: =COUNTIF('Senior Faculty'!$K$2:$K$401,A6) -> 1 | H6: =COUNTIF('Junior Faculty'!$K$2:$K$401,A6) -> 2
A7: ='_Lists'!$B$7 -> T2P3 | B7: =IF(LEFT(A7,1)="T","Technical Parallel Session",IF(LEFT(A7,7)="Keynote","Keynote Session",IF(A7="IEEE Workshop","Workshop",""))) -> Technical Parallel Session | C7: =IF(B7="Technical Parallel Session",COUNTIF(Papers!$G$2:$G$201,A7),"-") -> 5 | D7: 8 | E7: =IF(D7="-","-",IF(C7>D7,"Over Capacity",IF(C7=D7,"Full","Open ("&D7-C7&" slots left)"))) -> Open (3 slots left) | F7: =COUNTIF(Chairs!$K$2:$K$359,A7) -> 1 | G7: =COUNTIF('Senior Faculty'!$K$2:$K$401,A7) -> 1 | H7: =COUNTIF('Junior Faculty'!$K$2:$K$401,A7) -> 2
A8: ='_Lists'!$B$8 -> T2P4 | B8: =IF(LEFT(A8,1)="T","Technical Parallel Session",IF(LEFT(A8,7)="Keynote","Keynote Session",IF(A8="IEEE Workshop","Workshop",""))) -> Technical Parallel Session | C8: =IF(B8="Technical Parallel Session",COUNTIF(Papers!$G$2:$G$201,A8),"-") -> 7 | D8: 8 | E8: =IF(D8="-","-",IF(C8>D8,"Over Capacity",IF(C8=D8,"Full","Open ("&D8-C8&" slots left)"))) -> Open (1 slots left) | F8: =COUNTIF(Chairs!$K$2:$K$359,A8) -> 1 | G8: =COUNTIF('Senior Faculty'!$K$2:$K$401,A8) -> 1 | H8: =COUNTIF('Junior Faculty'!$K$2:$K$401,A8) -> 2
A9: ='_Lists'!$B$9 -> T2P5 | B9: =IF(LEFT(A9,1)="T","Technical Parallel Session",IF(LEFT(A9,7)="Keynote","Keynote Session",IF(A9="IEEE Workshop","Workshop",""))) -> Technical Parallel Session | C9: =IF(B9="Technical Parallel Session",COUNTIF(Papers!$G$2:$G$201,A9),"-") -> 0 | D9: 4 | E9: =IF(D9="-","-",IF(C9>D9,"Over Capacity",IF(C9=D9,"Full","Open ("&D9-C9&" slots left)"))) -> Open (4 slots left) | F9: =COUNTIF(Chairs!$K$2:$K$359,A9) -> 0 | G9: =COUNTIF('Senior Faculty'!$K$2:$K$401,A9) -> 0 | H9: =COUNTIF('Junior Faculty'!$K$2:$K$401,A9) -> 0
A10: ='_Lists'!$B$10 -> T3P1 | B10: =IF(LEFT(A10,1)="T","Technical Parallel Session",IF(LEFT(A10,7)="Keynote","Keynote Session",IF(A10="IEEE Workshop","Workshop",""))) -> Technical Parallel Session | C10: =IF(B10="Technical Parallel Session",COUNTIF(Papers!$G$2:$G$201,A10),"-") -> 0 | D10: 4 | E10: =IF(D10="-","-",IF(C10>D10,"Over Capacity",IF(C10=D10,"Full","Open ("&D10-C10&" slots left)"))) -> Open (4 slots left) | F10: =COUNTIF(Chairs!$K$2:$K$359,A10) -> 1 | G10: =COUNTIF('Senior Faculty'!$K$2:$K$401,A10) -> 1 | H10: =COUNTIF('Junior Faculty'!$K$2:$K$401,A10) -> 2
A11: ='_Lists'!$B$11 -> T3P2 | B11: =IF(LEFT(A11,1)="T","Technical Parallel Session",IF(LEFT(A11,7)="Keynote","Keynote Session",IF(A11="IEEE Workshop","Workshop",""))) -> Technical Parallel Session | C11: =IF(B11="Technical Parallel Session",COUNTIF(Papers!$G$2:$G$201,A11),"-") -> 0 | D11: 4 | E11: =IF(D11="-","-",IF(C11>D11,"Over Capacity",IF(C11=D11,"Full","Open ("&D11-C11&" slots left)"))) -> Open (4 slots left) | F11: =COUNTIF(Chairs!$K$2:$K$359,A11) -> 0 | G11: =COUNTIF('Senior Faculty'!$K$2:$K$401,A11) -> 0 | H11: =COUNTIF('Junior Faculty'!$K$2:$K$401,A11) -> 0
A12: ='_Lists'!$B$12 -> T3P3 | B12: =IF(LEFT(A12,1)="T","Technical Parallel Session",IF(LEFT(A12,7)="Keynote","Keynote Session",IF(A12="IEEE Workshop","Workshop",""))) -> Technical Parallel Session | C12: =IF(B12="Technical Parallel Session",COUNTIF(Papers!$G$2:$G$201,A12),"-") -> 0 | D12: 4 | E12: =IF(D12="-","-",IF(C12>D12,"Over Capacity",IF(C12=D12,"Full","Open ("&D12-C12&" slots left)"))) -> Open (4 slots left) | F12: =COUNTIF(Chairs!$K$2:$K$359,A12) -> 1 | G12: =COUNTIF('Senior Faculty'!$K$2:$K$401,A12) -> 1 | H12: =COUNTIF('Junior Faculty'!$K$2:$K$401,A12) -> 2
A13: ='_Lists'!$B$13 -> T3P4 | B13: =IF(LEFT(A13,1)="T","Technical Parallel Session",IF(LEFT(A13,7)="Keynote","Keynote Session",IF(A13="IEEE Workshop","Workshop",""))) -> Technical Parallel Session | C13: =IF(B13="Technical Parallel Session",COUNTIF(Papers!$G$2:$G$201,A13),"-") -> 0 | D13: 4 | E13: =IF(D13="-","-",IF(C13>D13,"Over Capacity",IF(C13=D13,"Full","Open ("&D13-C13&" slots left)"))) -> Open (4 slots left) | F13: =COUNTIF(Chairs!$K$2:$K$359,A13) -> 0 | G13: =COUNTIF('Senior Faculty'!$K$2:$K$401,A13) -> 0 | H13: =COUNTIF('Junior Faculty'!$K$2:$K$401,A13) -> 0
A14: ='_Lists'!$B$14 -> T3P5 | B14: =IF(LEFT(A14,1)="T","Technical Parallel Session",IF(LEFT(A14,7)="Keynote","Keynote Session",IF(A14="IEEE Workshop","Workshop",""))) -> Technical Parallel Session | C14: =IF(B14="Technical Parallel Session",COUNTIF(Papers!$G$2:$G$201,A14),"-") -> 0 | D14: 4 | E14: =IF(D14="-","-",IF(C14>D14,"Over Capacity",IF(C14=D14,"Full","Open ("&D14-C14&" slots left)"))) -> Open (4 slots left) | F14: =COUNTIF(Chairs!$K$2:$K$359,A14) -> 1 | G14: =COUNTIF('Senior Faculty'!$K$2:$K$401,A14) -> 1 | H14: =COUNTIF('Junior Faculty'!$K$2:$K$401,A14) -> 1
A15: ='_Lists'!$B$15 -> T4P1 | B15: =IF(LEFT(A15,1)="T","Technical Parallel Session",IF(LEFT(A15,7)="Keynote","Keynote Session",IF(A15="IEEE Workshop","Workshop",""))) -> Technical Parallel Session | C15: =IF(B15="Technical Parallel Session",COUNTIF(Papers!$G$2:$G$201,A15),"-") -> 9 | D15: 10 | E15: =IF(D15="-","-",IF(C15>D15,"Over Capacity",IF(C15=D15,"Full","Open ("&D15-C15&" slots left)"))) -> Open (1 slots left) | F15: =COUNTIF(Chairs!$K$2:$K$359,A15) -> 1 | G15: =COUNTIF('Senior Faculty'!$K$2:$K$401,A15) -> 1 | H15: =COUNTIF('Junior Faculty'!$K$2:$K$401,A15) -> 1
A16: ='_Lists'!$B$16 -> T4P2 | B16: =IF(LEFT(A16,1)="T","Technical Parallel Session",IF(LEFT(A16,7)="Keynote","Keynote Session",IF(A16="IEEE Workshop","Workshop",""))) -> Technical Parallel Session | C16: =IF(B16="Technical Parallel Session",COUNTIF(Papers!$G$2:$G$201,A16),"-") -> 7 | D16: 10 | E16: =IF(D16="-","-",IF(C16>D16,"Over Capacity",IF(C16=D16,"Full","Open ("&D16-C16&" slots left)"))) -> Open (3 slots left) | F16: =COUNTIF(Chairs!$K$2:$K$359,A16) -> 1 | G16: =COUNTIF('Senior Faculty'!$K$2:$K$401,A16) -> 1 | H16: =COUNTIF('Junior Faculty'!$K$2:$K$401,A16) -> 1
A17: ='_Lists'!$B$17 -> T4P3 | B17: =IF(LEFT(A17,1)="T","Technical Parallel Session",IF(LEFT(A17,7)="Keynote","Keynote Session",IF(A17="IEEE Workshop","Workshop",""))) -> Technical Parallel Session | C17: =IF(B17="Technical Parallel Session",COUNTIF(Papers!$G$2:$G$201,A17),"-") -> 6 | D17: 10 | E17: =IF(D17="-","-",IF(C17>D17,"Over Capacity",IF(C17=D17,"Full","Open ("&D17-C17&" slots left)"))) -> Open (4 slots left) | F17: =COUNTIF(Chairs!$K$2:$K$359,A17) -> 1 | G17: =COUNTIF('Senior Faculty'!$K$2:$K$401,A17) -> 1 | H17: =COUNTIF('Junior Faculty'!$K$2:$K$401,A17) -> 1
A18: ='_Lists'!$B$18 -> T4P4 | B18: =IF(LEFT(A18,1)="T","Technical Parallel Session",IF(LEFT(A18,7)="Keynote","Keynote Session",IF(A18="IEEE Workshop","Workshop",""))) -> Technical Parallel Session | C18: =IF(B18="Technical Parallel Session",COUNTIF(Papers!$G$2:$G$201,A18),"-") -> 8 | D18: 10 | E18: =IF(D18="-","-",IF(C18>D18,"Over Capacity",IF(C18=D18,"Full","Open ("&D18-C18&" slots left)"))) -> Open (2 slots left) | F18: =COUNTIF(Chairs!$K$2:$K$359,A18) -> 1 | G18: =COUNTIF('Senior Faculty'!$K$2:$K$401,A18) -> 1 | H18: =COUNTIF('Junior Faculty'!$K$2:$K$401,A18) -> 1
A19: ='_Lists'!$B$19 -> T4P5 | B19: =IF(LEFT(A19,1)="T","Technical Parallel Session",IF(LEFT(A19,7)="Keynote","Keynote Session",IF(A19="IEEE Workshop","Workshop",""))) -> Technical Parallel Session | C19: =IF(B19="Technical Parallel Session",COUNTIF(Papers!$G$2:$G$201,A19),"-") -> 5 | D19: 10 | E19: =IF(D19="-","-",IF(C19>D19,"Over Capacity",IF(C19=D19,"Full","Open ("&D19-C19&" slots left)"))) -> Open (5 slots left) | F19: =COUNTIF(Chairs!$K$2:$K$359,A19) -> 1 | G19: =COUNTIF('Senior Faculty'!$K$2:$K$401,A19) -> 1 | H19: =COUNTIF('Junior Faculty'!$K$2:$K$401,A19) -> 1
A20: ='_Lists'!$B$20 -> T4P6 | B20: =IF(LEFT(A20,1)="T","Technical Parallel Session",IF(LEFT(A20,7)="Keynote","Keynote Session",IF(A20="IEEE Workshop","Workshop",""))) -> Technical Parallel Session | C20: =IF(B20="Technical Parallel Session",COUNTIF(Papers!$G$2:$G$201,A20),"-") -> 6 | D20: 10 | E20: =IF(D20="-","-",IF(C20>D20,"Over Capacity",IF(C20=D20,"Full","Open ("&D20-C20&" slots left)"))) -> Open (4 slots left) | F20: =COUNTIF(Chairs!$K$2:$K$359,A20) -> 1 | G20: =COUNTIF('Senior Faculty'!$K$2:$K$401,A20) -> 1 | H20: =COUNTIF('Junior Faculty'!$K$2:$K$401,A20) -> 1
A21: ='_Lists'!$B$21 -> Keynote 1 | B21: =IF(LEFT(A21,1)="T","Technical Parallel Session",IF(LEFT(A21,7)="Keynote","Keynote Session",IF(A21="IEEE Workshop","Workshop",""))) -> Keynote Session | C21: =IF(B21="Technical Parallel Session",COUNTIF(Papers!$G$2:$G$201,A21),"-") -> - | D21: =IF(LEFT(A21,2)="T1",4,IF(OR(LEFT(A21,2)="T2",LEFT(A21,2)="T3",LEFT(A21,2)="T4"),8,"-")) -> - | E21: =IF(D21="-","-",IF(C21>D21,"Over Capacity",IF(C21=D21,"Full","Open ("&D21-C21&" slots left)"))) -> - | F21: =COUNTIF(Chairs!$K$2:$K$359,A21) -> 1 | G21: =COUNTIF('Senior Faculty'!$K$2:$K$401,A21) -> 1 | H21: =COUNTIF('Junior Faculty'!$K$2:$K$401,A21) -> 0
A22: ='_Lists'!$B$22 -> Keynote 2 | B22: =IF(LEFT(A22,1)="T","Technical Parallel Session",IF(LEFT(A22,7)="Keynote","Keynote Session",IF(A22="IEEE Workshop","Workshop",""))) -> Keynote Session | C22: =IF(B22="Technical Parallel Session",COUNTIF(Papers!$G$2:$G$201,A22),"-") -> - | D22: =IF(LEFT(A22,2)="T1",4,IF(OR(LEFT(A22,2)="T2",LEFT(A22,2)="T3",LEFT(A22,2)="T4"),8,"-")) -> - | E22: =IF(D22="-","-",IF(C22>D22,"Over Capacity",IF(C22=D22,"Full","Open ("&D22-C22&" slots left)"))) -> - | F22: =COUNTIF(Chairs!$K$2:$K$359,A22) -> 1 | G22: =COUNTIF('Senior Faculty'!$K$2:$K$401,A22) -> 1 | H22: =COUNTIF('Junior Faculty'!$K$2:$K$401,A22) -> 0
A23: ='_Lists'!$B$23 -> Keynote 3 | B23: =IF(LEFT(A23,1)="T","Technical Parallel Session",IF(LEFT(A23,7)="Keynote","Keynote Session",IF(A23="IEEE Workshop","Workshop",""))) -> Keynote Session | C23: =IF(B23="Technical Parallel Session",COUNTIF(Papers!$G$2:$G$201,A23),"-") -> - | D23: =IF(LEFT(A23,2)="T1",4,IF(OR(LEFT(A23,2)="T2",LEFT(A23,2)="T3",LEFT(A23,2)="T4"),8,"-")) -> - | E23: =IF(D23="-","-",IF(C23>D23,"Over Capacity",IF(C23=D23,"Full","Open ("&D23-C23&" slots left)"))) -> - | F23: =COUNTIF(Chairs!$K$2:$K$359,A23) -> 0 | G23: =COUNTIF('Senior Faculty'!$K$2:$K$401,A23) -> 0 | H23: =COUNTIF('Junior Faculty'!$K$2:$K$401,A23) -> 0
A24: ='_Lists'!$B$24 -> IEEE Workshop | B24: =IF(LEFT(A24,1)="T","Technical Parallel Session",IF(LEFT(A24,7)="Keynote","Keynote Session",IF(A24="IEEE Workshop","Workshop",""))) -> Workshop | C24: =IF(B24="Technical Parallel Session",COUNTIF(Papers!$G$2:$G$201,A24),"-") -> - | D24: =IF(LEFT(A24,2)="T1",4,IF(OR(LEFT(A24,2)="T2",LEFT(A24,2)="T3",LEFT(A24,2)="T4"),8,"-")) -> - | E24: =IF(D24="-","-",IF(C24>D24,"Over Capacity",IF(C24=D24,"Full","Open ("&D24-C24&" slots left)"))) -> - | F24: =COUNTIF(Chairs!$K$2:$K$359,A24) -> 1 | G24: =COUNTIF('Senior Faculty'!$K$2:$K$401,A24) -> 1 | H24: =COUNTIF('Junior Faculty'!$K$2:$K$401,A24) -> 0

Sheet Keynote 1
A1: Session | B1: Keynote 1
A2: Session Title | B2: AI and Deep Learning for Robotics and Health care Applications
A3: Session Time | B3: =IF(LEFT($B$1,2)="T1",Schedule!$A$4&", "&Schedule!$A$10,IF(LEFT($B$1,2)="T2",Schedule!$A$4&", "&Schedule!$A$12,IF(LEFT($B$1,2)="T3",Schedule!$A$4&", "&#REF!,IF(LEFT($B$1,2)="T4",Schedule!$A$16&", "&Schedule!$A$18,IF($B$1="Keynote 1",Schedule!$A$4&", "&Schedule!$A$8,IF($B$1="Keynote 2",Schedule!$A$4&", "&Schedule!$A$13,IF($B$1="Keynote 3",Schedule!$A$16&", "&Schedule!$A$19,IF($B$1="IEEE Workshop",Schedule!$A$16&", "&#REF!,"")))))))) -> Day 1, 10:40-11:40
A4: Session Room | B4: {=IFERROR(INDEX(Sessions!$D$2:$D$173,MATCH($B$1,Sessions!$B$2:$B$173,0))&"","")}
A5: Session Chair | B5: {=IFERROR(INDEX(Chairs!$J$2:$J$359,MATCH(1,INDEX((Chairs!$K$2:$K$359=$B$1)*(Chairs!$N$2:$N$359=1),0),0)),"")} -> Dr. Aminur Rahman | C5: {=IFERROR(INDEX(Chairs!$L$2:$L$359,MATCH(1,INDEX((Chairs!$K$2:$K$359=$B$1)*(Chairs!$N$2:$N$359=1),0),0))&"","")} -> aminur@bubt.edu.bd | D5: {=IFERROR(INDEX(Chairs!$M$2:$M$359,MATCH(1,INDEX((Chairs!$K$2:$K$359=$B$1)*(Chairs!$N$2:$N$359=1),0),0))&"","")} -> 01716539541
A6: Session Moderator | B6: {=IFERROR(INDEX('Senior Faculty'!$J$2:$J$401,MATCH(1,INDEX(('Senior Faculty'!$K$2:$K$401=$B$1)*('Senior Faculty'!$N$2:$N$401=1),0),0)),"")} -> Dr. T. M Abul Kalam Azad | C6: {=IFERROR(INDEX('Senior Faculty'!$L$2:$L$401,MATCH(1,INDEX(('Senior Faculty'!$K$2:$K$401=$B$1)*('Senior Faculty'!$N$2:$N$401=1),0),0))&"","")} -> abul.kalam@ulab.edu.bd | D6: {=IFERROR(INDEX('Senior Faculty'!$M$2:$M$401,MATCH(1,INDEX(('Senior Faculty'!$K$2:$K$401=$B$1)*('Senior Faculty'!$N$2:$N$401=1),0),0))&"","")} -> 01789379752
A7: Rappoteur 1 | B7: {=IFERROR(INDEX('Junior Faculty'!$J$2:$J$401,MATCH(1,INDEX(('Junior Faculty'!$K$2:$K$401=$B$1)*('Junior Faculty'!$N$2:$N$401=1),0),0)),"")} | C7: {=IFERROR(INDEX('Junior Faculty'!$L$2:$L$401,MATCH(1,INDEX(('Junior Faculty'!$K$2:$K$401=$B$1)*('Junior Faculty'!$N$2:$N$401=1),0),0))&"","")} | D7: {=IFERROR(INDEX('Junior Faculty'!$M$2:$M$401,MATCH(1,INDEX(('Junior Faculty'!$K$2:$K$401=$B$1)*('Junior Faculty'!$N$2:$N$401=1),0),0))&"","")}
A8: Rappoteur 2 | B8: {=IFERROR(INDEX('Junior Faculty'!$J$2:$J$401,MATCH(1,INDEX(('Junior Faculty'!$K$2:$K$401=$B$1)*('Junior Faculty'!$N$2:$N$401=2),0),0)),"")} | C8: {=IFERROR(INDEX('Junior Faculty'!$L$2:$L$401,MATCH(1,INDEX(('Junior Faculty'!$K$2:$K$401=$B$1)*('Junior Faculty'!$N$2:$N$401=2),0),0))&"","")} | D8: {=IFERROR(INDEX('Junior Faculty'!$M$2:$M$401,MATCH(1,INDEX(('Junior Faculty'!$K$2:$K$401=$B$1)*('Junior Faculty'!$N$2:$N$401=2),0),0))&"","")}
A10: Keynote Details
A11: Speakers Info | B11: Professor Dr. Celia Shahnaz, FTWAS, SMIEEE, LFIEB, Department of EEE, BUET
A12: Speakers Intro | B12: Celia Shahnaz, SMIEEE, Fellow IEB, received Ph.D. degree from Concordia University, Canada and is currently a professor at, Department of EEE, BUET, Bangladesh since 2015. She was the winner of Canadian Common Scholarship for pursuing her Ph.D study in Canada and recipient of Bangladesh Academy of Science Gold Medal for her contributions in science and technology. The World Academy of Science (TWAS) members have elected her as a Fellow of TWAS for the advancement of science in developing countries, effective 1 January 2023. Recently, her nomination has been approved and she has been inducted into IEEE-Eta Kappa Nu as a Professional Member into the Eta Chapter of the Board of Governors. She has served as 2023-24, Liaison of WIE to IEEE Board of Directors and 2023-25 Member, IEEE in 2050 and Beyond subcommittee. She has been selected and appointed as 2026 IEEE SSIT Education subcommittee, 2025-27 IEEE Computer society Distinguished Visitor. She has been appointed as 2025-26 Chair, IEEE WIE Nominations and Appoints. She has been elected as 2022 IEEE WIE Committee Chair-Elect and she has served as the 2023-2024 IEEE WIE Committee Chair. She has been appointed as 2024-25, Division V Representative, IEEE TAB Award and Recognition Committee , 2024-26 Member, IEEE Fourier Award for Signal Processing Committee , 2024-25 IEEE Computer society Awards Chair, 2025 Member, IEEE CS Diversity and Inclusion Committee, 2024 Member, IEEE CS Election Committee, 2020, 2022-23 Member, IEEE New Initiative Committee, 2021-24 Member, IEEE History Committee, Liaison between IEEE History Committee and IEEE WIE, 2023 Corresponding member, IEEE BOD Ad-Hoc: Coordinating IEEE’s Response to Multimedia-Based Digital Reality Technologies, 2023 Member, the future of the IEEE WIE ILC Adhoc. She has served as 2021-22 Chair, IEEE SPS Women in Signal Processing, 2021-22 Liaison between IEEE SPS and IEEE WIE, 2021-22 Member, IEEE Educational Activities Board Faculty Resource Committee, 2022 Member, IEEE WIE Strategic planning Committee, 2021 Chair, IEEE WIE History Subcommittee, 2020-21 Member, IEEE WIE Senior Member Elevation Drive and 2019-2022 Member, IEEE WIE WePower Subcommittee. She has served as an Editorial board member, IET Signal Processing From 2018 to date. She is the immediate past Chair, IEEE Bangladesh Section, Co-founder & Chair, IEEE EMBS, IAS, RAS, SSIT Bangladesh Chapters, Co-founder & Vice-Chair, IEEE SPS Bangladesh Chapter, Founder and Advisor, WIE AG, and founder and Chair of SIGHT group FLASH, IEEE Bangladesh Section. She is the recipient of the 2025 R10 Outstanding Volunteer Award, 2021 IEEE MGA Achievement Award, 2021 Inspiring Women in Academia Award from Bangladesh brand forum, 2019 R10 Humanitarian Activities Outstanding Volunteer Award, 2016 MGA Leadership Award 2015 WIE Inspiring Member Award, 2013 R10 WIE Professional Volunteer Award. She has more than 25 years of experience (25 years as an IEEE volunteer) in leading impactful Technical, Professional, Educational, Industrial, Women Empowerment, Humanitarian Technology, Power and Energy-related Projects at national/international levels.
A13: Abstract | B13: Rapid advances in signal processing, artificial intelligence (AI), machine learning, and deep learning are transforming robotics and healthcare by enabling intelligent systems to analyze complex signals, perceive their environments, and support data-driven decision-making. This talk highlights recent developments in audio, visual, biomedical, and multimodal signal processing, with emphasis on their applications in human-centered intelligent systems. In healthcare, AI-assisted processing of biomedical signals and medical images is creating new opportunities for automated screening, diagnosis, monitoring, and clinical decision support. Deep neural networks, attention-based models, ensemble learning, and generative AI are increasingly being applied to EEG, ECG, heart sounds, medical images, and other physiological data for disease detection, abnormality classification, sleep analysis, and personalized healthcare. Privacy-preserving approaches such as federated learning are also becoming important for developing collaborative medical AI systems while protecting sensitive patient information. In robotics, the integration of sensing, computer vision, signal processing, and AI is enabling more autonomous, adaptive, and interactive systems. Deep-learning-based perception, multimodal recognition, reinforcement learning, and intelligent control are supporting applications in assistive robotics, autonomous navigation, environmental monitoring, human–robot interaction, and accessibility technologies such as sign-language recognition. A major trend across these fields is the shift from conventional feature-engineered approaches toward adaptive, multimodal, explainable, and data-driven intelligent systems. The convergence of advanced signal processing with generative AI, lightweight neural networks, intelligent sensors, and edge computing is expected to further enhance real-time performance, reliability, and accessibility. These developments offer strong potential for safer robotics, affordable healthcare, and scalable intelligent solutions addressing practical societal and technological challenges.

Sheet Keynote 2
A1: Session | B1: Keynote 2
A2: Session Title
A3: Session Time | B3: =IF(LEFT($B$1,2)="T1",Schedule!$A$4&", "&Schedule!$A$10,IF(LEFT($B$1,2)="T2",Schedule!$A$4&", "&Schedule!$A$12,IF(LEFT($B$1,2)="T3",Schedule!$A$4&", "&#REF!,IF(LEFT($B$1,2)="T4",Schedule!$A$16&", "&Schedule!$A$18,IF($B$1="Keynote 1",Schedule!$A$4&", "&Schedule!$A$8,IF($B$1="Keynote 2",Schedule!$A$4&", "&Schedule!$A$13,IF($B$1="Keynote 3",Schedule!$A$16&", "&Schedule!$A$19,IF($B$1="IEEE Workshop",Schedule!$A$16&", "&#REF!,"")))))))) -> Day 1, 16:30-17:30
A4: Session Room | B4: {=IFERROR(INDEX(Sessions!$D$2:$D$173,MATCH($B$1,Sessions!$B$2:$B$173,0))&"","")}
A5: Session Chair | B5: {=IFERROR(INDEX(Chairs!$J$2:$J$359,MATCH(1,INDEX((Chairs!$K$2:$K$359=$B$1)*(Chairs!$N$2:$N$359=1),0),0)),"")} -> Prof. Dr. Md. Shahriar Rahman | C5: {=IFERROR(INDEX(Chairs!$L$2:$L$359,MATCH(1,INDEX((Chairs!$K$2:$K$359=$B$1)*(Chairs!$N$2:$N$359=1),0),0))&"","")} -> mshahriar@cse.uiu.ac.bd | D5: {=IFERROR(INDEX(Chairs!$M$2:$M$359,MATCH(1,INDEX((Chairs!$K$2:$K$359=$B$1)*(Chairs!$N$2:$N$359=1),0),0))&"","")} -> 01742092172
A6: Session Moderator | B6: {=IFERROR(INDEX('Senior Faculty'!$J$2:$J$401,MATCH(1,INDEX(('Senior Faculty'!$K$2:$K$401=$B$1)*('Senior Faculty'!$N$2:$N$401=1),0),0)),"")} -> Prof. Dr. Muhammad Golam Kibria | C6: {=IFERROR(INDEX('Senior Faculty'!$L$2:$L$401,MATCH(1,INDEX(('Senior Faculty'!$K$2:$K$401=$B$1)*('Senior Faculty'!$N$2:$N$401=1),0),0))&"","")} -> golam.kibria@ulab.edu.bd | D6: {=IFERROR(INDEX('Senior Faculty'!$M$2:$M$401,MATCH(1,INDEX(('Senior Faculty'!$K$2:$K$401=$B$1)*('Senior Faculty'!$N$2:$N$401=1),0),0))&"","")} -> 01771122144
A7: Rappoteur 1 | B7: {=IFERROR(INDEX('Junior Faculty'!$J$2:$J$401,MATCH(1,INDEX(('Junior Faculty'!$K$2:$K$401=$B$1)*('Junior Faculty'!$N$2:$N$401=1),0),0)),"")} | C7: {=IFERROR(INDEX('Junior Faculty'!$L$2:$L$401,MATCH(1,INDEX(('Junior Faculty'!$K$2:$K$401=$B$1)*('Junior Faculty'!$N$2:$N$401=1),0),0))&"","")} | D7: {=IFERROR(INDEX('Junior Faculty'!$M$2:$M$401,MATCH(1,INDEX(('Junior Faculty'!$K$2:$K$401=$B$1)*('Junior Faculty'!$N$2:$N$401=1),0),0))&"","")}
A8: Rappoteur 2 | B8: {=IFERROR(INDEX('Junior Faculty'!$J$2:$J$401,MATCH(1,INDEX(('Junior Faculty'!$K$2:$K$401=$B$1)*('Junior Faculty'!$N$2:$N$401=2),0),0)),"")} | C8: {=IFERROR(INDEX('Junior Faculty'!$L$2:$L$401,MATCH(1,INDEX(('Junior Faculty'!$K$2:$K$401=$B$1)*('Junior Faculty'!$N$2:$N$401=2),0),0))&"","")} | D8: {=IFERROR(INDEX('Junior Faculty'!$M$2:$M$401,MATCH(1,INDEX(('Junior Faculty'!$K$2:$K$401=$B$1)*('Junior Faculty'!$N$2:$N$401=2),0),0))&"","")}
A10: Keynote Details
A11: Speakers Info
A12: Speakers Intro
A13: Abstract

Sheet Keynote 3
A1: Session | B1: Keynote 3
A2: Session Title | B2: Towards a Car-lite Society – Challenges and Opportunities
A3: Session Time | B3: =IF(LEFT($B$1,2)="T1",Schedule!$A$4&", "&Schedule!$A$10,IF(LEFT($B$1,2)="T2",Schedule!$A$4&", "&Schedule!$A$12,IF(LEFT($B$1,2)="T3",Schedule!$A$4&", "&#REF!,IF(LEFT($B$1,2)="T4",Schedule!$A$16&", "&Schedule!$A$18,IF($B$1="Keynote 1",Schedule!$A$4&", "&Schedule!$A$8,IF($B$1="Keynote 2",Schedule!$A$4&", "&Schedule!$A$13,IF($B$1="Keynote 3",Schedule!$A$16&", "&Schedule!$A$19,IF($B$1="IEEE Workshop",Schedule!$A$16&", "&#REF!,"")))))))) -> Day 2, 14:30-15:30
A4: Session Room | B4: https://bdren.zoom.us/j/8428351030?pwd=7kfJZ1PoRiAzd0aKSn3l28Yuta2D1P.1&omn=92475321723
A5: Session Chair | B5: Dr. Jia Uddin | C5: {=IFERROR(INDEX(Chairs!$L$2:$L$359,MATCH(1,INDEX((Chairs!$K$2:$K$359=$B$1)*(Chairs!$N$2:$N$359=1),0),0))&"","")} | D5: {=IFERROR(INDEX(Chairs!$M$2:$M$359,MATCH(1,INDEX((Chairs!$K$2:$K$359=$B$1)*(Chairs!$N$2:$N$359=1),0),0))&"","")}
A6: Session Moderator | B6: {=IFERROR(INDEX('Senior Faculty'!$J$2:$J$401,MATCH(1,INDEX(('Senior Faculty'!$K$2:$K$401=$B$1)*('Senior Faculty'!$N$2:$N$401=1),0),0)),"")} | C6: {=IFERROR(INDEX('Senior Faculty'!$L$2:$L$401,MATCH(1,INDEX(('Senior Faculty'!$K$2:$K$401=$B$1)*('Senior Faculty'!$N$2:$N$401=1),0),0))&"","")} | D6: {=IFERROR(INDEX('Senior Faculty'!$M$2:$M$401,MATCH(1,INDEX(('Senior Faculty'!$K$2:$K$401=$B$1)*('Senior Faculty'!$N$2:$N$401=1),0),0))&"","")}
A7: Rappoteur 1 | B7: {=IFERROR(INDEX('Junior Faculty'!$J$2:$J$401,MATCH(1,INDEX(('Junior Faculty'!$K$2:$K$401=$B$1)*('Junior Faculty'!$N$2:$N$401=1),0),0)),"")} | C7: {=IFERROR(INDEX('Junior Faculty'!$L$2:$L$401,MATCH(1,INDEX(('Junior Faculty'!$K$2:$K$401=$B$1)*('Junior Faculty'!$N$2:$N$401=1),0),0))&"","")} | D7: {=IFERROR(INDEX('Junior Faculty'!$M$2:$M$401,MATCH(1,INDEX(('Junior Faculty'!$K$2:$K$401=$B$1)*('Junior Faculty'!$N$2:$N$401=1),0),0))&"","")}
A8: Rappoteur 2 | B8: {=IFERROR(INDEX('Junior Faculty'!$J$2:$J$401,MATCH(1,INDEX(('Junior Faculty'!$K$2:$K$401=$B$1)*('Junior Faculty'!$N$2:$N$401=2),0),0)),"")} | C8: {=IFERROR(INDEX('Junior Faculty'!$L$2:$L$401,MATCH(1,INDEX(('Junior Faculty'!$K$2:$K$401=$B$1)*('Junior Faculty'!$N$2:$N$401=2),0),0))&"","")} | D8: {=IFERROR(INDEX('Junior Faculty'!$M$2:$M$401,MATCH(1,INDEX(('Junior Faculty'!$K$2:$K$401=$B$1)*('Junior Faculty'!$N$2:$N$401=2),0),0))&"","")}
A10: Keynote Details
A11: Speakers Info | B11: Dr Rong Su
A12: Speakers Intro | B12: Professor, School of Electrical & Electronic Engineering, Nanyang Technological University, Singapore
A13: Abstract | B13: Private vehicles are well known to be one key contribution factor for traffic network inefficiency such as traffic jams, waste gas emissions and excessive traffic space requirements (due to parking needs). However, the average utilization rate of private cars is extremely low. How to reduce the number of private cars and their daily usage is one open question for the academia and industry. A car-lite society relies less on private cars for transport, emphasizing sustainable alternatives like walking, cycling, and public transport to reduce car dependency. One key challenge is how to convince people that their travel needs and quality of mobility will not degrade, even after they give up their private cars. One conjecture is that a person might be willing to consider this option only when he/she is certain that, whenever a travel-need arises, there will always be a suitable car available within a short period of time acceptable by the person. That is, the technologies must ensure a guaranteed maximum waiting time in any circumstances. In this talk, we will discuss how different mobility-related technologies might contribute to a holistic system solution to achieve a car-lite society, and what possible challenges are.

Sheet Workshop
A1: Session | B1: IEEE Workshop
A2: Session Title | B2: Responsible AI for Academic Research
A3: Session Time | B3: Day 1, 11:40-12:40
A4: Session Room | B4: PD104
A5: Session Facillitator | B5: IEEE Workshop
A6: Session Moderator | B6: {=IFERROR(INDEX('Senior Faculty'!$J$2:$J$401,MATCH(1,INDEX(('Senior Faculty'!$K$2:$K$401=$B$1)*('Senior Faculty'!$N$2:$N$401=1),0),0)),"")} -> Prof. Dr. Nafees Mansoor | C6: {=IFERROR(INDEX('Senior Faculty'!$L$2:$L$401,MATCH(1,INDEX(('Senior Faculty'!$K$2:$K$401=$B$1)*('Senior Faculty'!$N$2:$N$401=1),0),0))&"","")} -> nafees.mansoor@ulab.edu.bd | D6: {=IFERROR(INDEX('Senior Faculty'!$M$2:$M$401,MATCH(1,INDEX(('Senior Faculty'!$K$2:$K$401=$B$1)*('Senior Faculty'!$N$2:$N$401=1),0),0))&"","")} -> 01879242323
A7: Rappoteur 1 | B7: {=IFERROR(INDEX('Junior Faculty'!$J$2:$J$401,MATCH(1,INDEX(('Junior Faculty'!$K$2:$K$401=$B$1)*('Junior Faculty'!$N$2:$N$401=1),0),0)),"")} | C7: {=IFERROR(INDEX('Junior Faculty'!$L$2:$L$401,MATCH(1,INDEX(('Junior Faculty'!$K$2:$K$401=$B$1)*('Junior Faculty'!$N$2:$N$401=1),0),0))&"","")} | D7: {=IFERROR(INDEX('Junior Faculty'!$M$2:$M$401,MATCH(1,INDEX(('Junior Faculty'!$K$2:$K$401=$B$1)*('Junior Faculty'!$N$2:$N$401=1),0),0))&"","")}
A8: Rappoteur 2 | B8: {=IFERROR(INDEX('Junior Faculty'!$J$2:$J$401,MATCH(1,INDEX(('Junior Faculty'!$K$2:$K$401=$B$1)*('Junior Faculty'!$N$2:$N$401=2),0),0)),"")} | C8: {=IFERROR(INDEX('Junior Faculty'!$L$2:$L$401,MATCH(1,INDEX(('Junior Faculty'!$K$2:$K$401=$B$1)*('Junior Faculty'!$N$2:$N$401=2),0),0))&"","")} | D8: {=IFERROR(INDEX('Junior Faculty'!$M$2:$M$401,MATCH(1,INDEX(('Junior Faculty'!$K$2:$K$401=$B$1)*('Junior Faculty'!$N$2:$N$401=2),0),0))&"","")}
A10: Keynote Details
A11: Speakers Info
A12: Speakers Intro
A13: Abstract

Sheet T1P1
A1: Session | B1: T1P1
A2: Session Title | B2: {=IFERROR(INDEX(Sessions!$C$2:$C$173,MATCH($B$1,Sessions!$B$2:$B$173,0))&"","")} -> Machine Learning Foundations and Intelligent Systems
A3: Session Time | B3: =IF(LEFT($B$1,2)="T1",Schedule!$A$4&", "&Schedule!$A$10,IF(LEFT($B$1,2)="T2",Schedule!$A$4&", "&Schedule!$A$12,IF(LEFT($B$1,2)="T3",Schedule!$A$4&", "&#REF!,IF(LEFT($B$1,2)="T4",Schedule!$A$16&", "&Schedule!$A$18,IF($B$1="Keynote 1",Schedule!$A$4&", "&Schedule!$A$8,IF($B$1="Keynote 2",Schedule!$A$4&", "&Schedule!$A$13,IF($B$1="Keynote 3",Schedule!$A$16&", "&Schedule!$A$19,IF($B$1="IEEE Workshop",Schedule!$A$16&", "&#REF!,"")))))))) -> Day 1, 11:40-12:40
A4: Session Room | B4: PD101
A5: Session Chair 1 | B5: {=IFERROR(INDEX(Chairs!$J$2:$J$359,MATCH(1,INDEX((Chairs!$K$2:$K$359=$B$1)*(Chairs!$N$2:$N$359=1),0),0)),"")} -> Dr. Md.Ruhul Amin | C5: {=IFERROR(INDEX(Chairs!$L$2:$L$359,MATCH(1,INDEX((Chairs!$K$2:$K$359=$B$1)*(Chairs!$N$2:$N$359=1),0),0))&"","")} -> dr.mdruhulamin@seu.edu.bd | D5: {=IFERROR(INDEX(Chairs!$M$2:$M$359,MATCH(1,INDEX((Chairs!$K$2:$K$359=$B$1)*(Chairs!$N$2:$N$359=1),0),0))&"","")} -> 01710949921
A6: Session Chair 2 | B6: Dr. Mirza Rasheduzzaman | C6: mirza.rasheduzzaman@gmail.com | D6: 1787736780
A7: Session Moderator | B7: {=IFERROR(INDEX('Senior Faculty'!$J$2:$J$401,MATCH(1,INDEX(('Senior Faculty'!$K$2:$K$401=$B$1)*('Senior Faculty'!$N$2:$N$401=1),0),0)),"")} -> Dr. Ayesha Akter Lata | C7: {=IFERROR(INDEX('Senior Faculty'!$L$2:$L$401,MATCH(1,INDEX(('Senior Faculty'!$K$2:$K$401=$B$1)*('Senior Faculty'!$N$2:$N$401=1),0),0))&"","")} -> ayesha.akter@ulab.edu.bd | D7: {=IFERROR(INDEX('Senior Faculty'!$M$2:$M$401,MATCH(1,INDEX(('Senior Faculty'!$K$2:$K$401=$B$1)*('Senior Faculty'!$N$2:$N$401=1),0),0))&"","")} -> 01856412501
A8: Rappoteur 1 | B8: {=IFERROR(INDEX('Junior Faculty'!$J$2:$J$401,MATCH(1,INDEX(('Junior Faculty'!$K$2:$K$401=$B$1)*('Junior Faculty'!$N$2:$N$401=1),0),0)),"")} -> Suravi Akhter | C8: {=IFERROR(INDEX('Junior Faculty'!$L$2:$L$401,MATCH(1,INDEX(('Junior Faculty'!$K$2:$K$401=$B$1)*('Junior Faculty'!$N$2:$N$401=1),0),0))&"","")} -> suravi.akhter@ulab.edu.bd | D8: {=IFERROR(INDEX('Junior Faculty'!$M$2:$M$401,MATCH(1,INDEX(('Junior Faculty'!$K$2:$K$401=$B$1)*('Junior Faculty'!$N$2:$N$401=1),0),0))&"","")} -> 01308395394
A9: Rappoteur 2 | B9: {=IFERROR(INDEX('Junior Faculty'!$J$2:$J$401,MATCH(1,INDEX(('Junior Faculty'!$K$2:$K$401=$B$1)*('Junior Faculty'!$N$2:$N$401=2),0),0)),"")} -> Abir Bin Yousuf | C9: {=IFERROR(INDEX('Junior Faculty'!$L$2:$L$401,MATCH(1,INDEX(('Junior Faculty'!$K$2:$K$401=$B$1)*('Junior Faculty'!$N$2:$N$401=2),0),0))&"","")} -> abir.yousuf@ulab.edu.bd | D9: {=IFERROR(INDEX('Junior Faculty'!$M$2:$M$401,MATCH(1,INDEX(('Junior Faculty'!$K$2:$K$401=$B$1)*('Junior Faculty'!$N$2:$N$401=2),0),0))&"","")} -> 01628312807
A11: Papers
A12: ID | B12: Title | C12: Authors | E12: Emails | F12: Chair Score (/50)
A13: {=IFERROR(INDEX(Papers!$A$2:$A$201,MATCH(1,INDEX((Papers!$G$2:$G$201=$B$1)*(Papers!$I$2:$I$201=1),0),0)),"")} -> 49 | B13: {=IFERROR(INDEX(Papers!$C$2:$C$201,MATCH(1,INDEX((Papers!$G$2:$G$201=$B$1)*(Papers!$I$2:$I$201=1),0),0)),"")} -> SPPC: Benchmarking Selenium, Playwright, Puppeteer, and Cypress for Energy-Efficient Web Automation | C13: {=IFERROR(INDEX(Papers!$D$2:$D$201,MATCH(1,INDEX((Papers!$G$2:$G$201=$B$1)*(Papers!$I$2:$I$201=1),0),0)),"")} -> MD. Zihaul Islam Zihan (American International University-Bangladesh); Al Israfil Niloy ( American International University-Bangladesh); Raid Ibney Hasan Arnob (American International University-Bangladesh); Rifat Rudro (American International University-Bangladesh)*; Kamruddin Nur (American International University-Bangladesh) | E13: {=IFERROR(INDEX(Papers!$E$2:$E$201,MATCH(1,INDEX((Papers!$G$2:$G$201=$B$1)*(Papers!$I$2:$I$201=1),0),0)),"")} -> 22-49229-3@student.aiub.edu; 22-49033-3@student.aiub.edu; 22-48357-3@student.aiub.edu; mamun.rudro@aiub.edu; kamruddin@aiub.edu
A14: {=IFERROR(INDEX(Papers!$A$2:$A$201,MATCH(1,INDEX((Papers!$G$2:$G$201=$B$1)*(Papers!$I$2:$I$201=2),0),0)),"")} -> 58 | B14: {=IFERROR(INDEX(Papers!$C$2:$C$201,MATCH(1,INDEX((Papers!$G$2:$G$201=$B$1)*(Papers!$I$2:$I$201=2),0),0)),"")} -> Explainable Machine Learning for Cross-Species Myeloid Biomarker Discovery in Glioblastoma | C14: {=IFERROR(INDEX(Papers!$D$2:$D$201,MATCH(1,INDEX((Papers!$G$2:$G$201=$B$1)*(Papers!$I$2:$I$201=2),0),0)),"")} -> MD Himel Kabir (American International University-Bangladesh); Shanjida Sultana (American International University-Bangladesh); MD Salauddin (American International University-Bangladesh); Rifat Rudro (American International University-Bangladesh)*; Kamruddin Nur (American International University-Bangladesh) | E14: {=IFERROR(INDEX(Papers!$E$2:$E$201,MATCH(1,INDEX((Papers!$G$2:$G$201=$B$1)*(Papers!$I$2:$I$201=2),0),0)),"")} -> 23-51481-1@student.aiub.edu; 23-51519-1@student.aiub.edu; 23-51479-1@student.aiub.edu; mamun.rudro@aiub.edu; kamruddin@aiub.edu
A15: {=IFERROR(INDEX(Papers!$A$2:$A$201,MATCH(1,INDEX((Papers!$G$2:$G$201=$B$1)*(Papers!$I$2:$I$201=3),0),0)),"")} -> 177 | B15: {=IFERROR(INDEX(Papers!$C$2:$C$201,MATCH(1,INDEX((Papers!$G$2:$G$201=$B$1)*(Papers!$I$2:$I$201=3),0),0)),"")} -> An Interpretable Machine Learning Approach for Maternity Risk Prediction and Assessment | C15: {=IFERROR(INDEX(Papers!$D$2:$D$201,MATCH(1,INDEX((Papers!$G$2:$G$201=$B$1)*(Papers!$I$2:$I$201=3),0),0)),"")} -> Shah Jafor Sadeek Quaderi (University of Liberal Arts Bangladesh)*; Nasir Uddin Ahmed (University of Liberal Arts Bangladesh); Md. Sahidullah (Asian University of Bangladesh) | E15: {=IFERROR(INDEX(Papers!$E$2:$E$201,MATCH(1,INDEX((Papers!$G$2:$G$201=$B$1)*(Papers!$I$2:$I$201=3),0),0)),"")} -> jafor.sadeek@ulab.edu.bd; nasir.uddin1@ulab.edu.bd; sahidullah.shafi.work@gmail.com
A16: {=IFERROR(INDEX(Papers!$A$2:$A$201,MATCH(1,INDEX((Papers!$G$2:$G$201=$B$1)*(Papers!$I$2:$I$201=4),0),0)),"")} | B16: {=IFERROR(INDEX(Papers!$C$2:$C$201,MATCH(1,INDEX((Papers!$G$2:$G$201=$B$1)*(Papers!$I$2:$I$201=4),0),0)),"")} | C16: {=IFERROR(INDEX(Papers!$D$2:$D$201,MATCH(1,INDEX((Papers!$G$2:$G$201=$B$1)*(Papers!$I$2:$I$201=4),0),0)),"")} | E16: {=IFERROR(INDEX(Papers!$E$2:$E$201,MATCH(1,INDEX((Papers!$G$2:$G$201=$B$1)*(Papers!$I$2:$I$201=4),0),0)),"")}
A17: {=IFERROR(INDEX(Papers!$A$2:$A$201,MATCH(1,INDEX((Papers!$G$2:$G$201=$B$1)*(Papers!$I$2:$I$201=5),0),0)),"")} | B17: {=IFERROR(INDEX(Papers!$C$2:$C$201,MATCH(1,INDEX((Papers!$G$2:$G$201=$B$1)*(Papers!$I$2:$I$201=5),0),0)),"")} | C17: {=IFERROR(INDEX(Papers!$D$2:$D$201,MATCH(1,INDEX((Papers!$G$2:$G$201=$B$1)*(Papers!$I$2:$I$201=5),0),0)),"")} | E17: {=IFERROR(INDEX(Papers!$E$2:$E$201,MATCH(1,INDEX((Papers!$G$2:$G$201=$B$1)*(Papers!$I$2:$I$201=5),0),0)),"")}
A18: {=IFERROR(INDEX(Papers!$A$2:$A$201,MATCH(1,INDEX((Papers!$G$2:$G$201=$B$1)*(Papers!$I$2:$I$201=6),0),0)),"")} | B18: {=IFERROR(INDEX(Papers!$C$2:$C$201,MATCH(1,INDEX((Papers!$G$2:$G$201=$B$1)*(Papers!$I$2:$I$201=6),0),0)),"")} | C18: {=IFERROR(INDEX(Papers!$D$2:$D$201,MATCH(1,INDEX((Papers!$G$2:$G$201=$B$1)*(Papers!$I$2:$I$201=6),0),0)),"")} | E18: {=IFERROR(INDEX(Papers!$E$2:$E$201,MATCH(1,INDEX((Papers!$G$2:$G$201=$B$1)*(Papers!$I$2:$I$201=6),0),0)),"")}
A19: {=IFERROR(INDEX(Papers!$A$2:$A$201,MATCH(1,INDEX((Papers!$G$2:$G$201=$B$1)*(Papers!$I$2:$I$201=7),0),0)),"")} | B19: {=IFERROR(INDEX(Papers!$C$2:$C$201,MATCH(1,INDEX((Papers!$G$2:$G$201=$B$1)*(Papers!$I$2:$I$201=7),0),0)),"")} | C19: {=IFERROR(INDEX(Papers!$D$2:$D$201,MATCH(1,INDEX((Papers!$G$2:$G$201=$B$1)*(Papers!$I$2:$I$201=7),0),0)),"")} | E19: {=IFERROR(INDEX(Papers!$E$2:$E$201,MATCH(1,INDEX((Papers!$G$2:$G$201=$B$1)*(Papers!$I$2:$I$201=7),0),0)),"")}
A20: {=IFERROR(INDEX(Papers!$A$2:$A$201,MATCH(1,INDEX((Papers!$G$2:$G$201=$B$1)*(Papers!$I$2:$I$201=8),0),0)),"")} | B20: {=IFERROR(INDEX(Papers!$C$2:$C$201,MATCH(1,INDEX((Papers!$G$2:$G$201=$B$1)*(Papers!$I$2:$I$201=8),0),0)),"")} | C20: {=IFERROR(INDEX(Papers!$D$2:$D$201,MATCH(1,INDEX((Papers!$G$2:$G$201=$B$1)*(Papers!$I$2:$I$201=8),0),0)),"")} | E20: {=IFERROR(INDEX(Papers!$E$2:$E$201,MATCH(1,INDEX((Papers!$G$2:$G$201=$B$1)*(Papers!$I$2:$I$201=8),0),0)),"")}

Sheet T1P2
A1: Session | B1: T1P2
A2: Session Title | B2: {=IFERROR(INDEX(Sessions!$C$2:$C$173,MATCH($B$1,Sessions!$B$2:$B$173,0))&"","")} -> Natural Language, Computer Vision, and Multimodal AI
A3: Session Time | B3: =IF(LEFT($B$1,2)="T1",Schedule!$A$4&", "&Schedule!$A$10,IF(LEFT($B$1,2)="T2",Schedule!$A$4&", "&Schedule!$A$12,IF(LEFT($B$1,2)="T3",Schedule!$A$4&", "&#REF!,IF(LEFT($B$1,2)="T4",Schedule!$A$16&", "&Schedule!$A$18,IF($B$1="Keynote 1",Schedule!$A$4&", "&Schedule!$A$8,IF($B$1="Keynote 2",Schedule!$A$4&", "&Schedule!$A$13,IF($B$1="Keynote 3",Schedule!$A$16&", "&Schedule!$A$19,IF($B$1="IEEE Workshop",Schedule!$A$16&", "&#REF!,"")))))))) -> Day 1, 11:40-12:40
A4: Session Room | B4: PD102
A5: Session Chair | B5: {=IFERROR(INDEX(Chairs!$J$2:$J$359,MATCH(1,INDEX((Chairs!$K$2:$K$359=$B$1)*(Chairs!$N$2:$N$359=1),0),0)),"")} -> Prof. Dr. Kamruddin Nur | C5: {=IFERROR(INDEX(Chairs!$L$2:$L$359,MATCH(1,INDEX((Chairs!$K$2:$K$359=$B$1)*(Chairs!$N$2:$N$359=1),0),0))&"","")} -> kamruddin.nur@gmail.com | D5: {=IFERROR(INDEX(Chairs!$M$2:$M$359,MATCH(1,INDEX((Chairs!$K$2:$K$359=$B$1)*(Chairs!$N$2:$N$359=1),0),0))&"","")} -> 01777354323
A6: Session Chair 2 | B6: Prof. Dr. Engr. Muhibul Haque Bhuyan | C6: muhibulhb@aiub.edu | D6: 1815657346
A7: Session Moderator | B7: {=IFERROR(INDEX('Senior Faculty'!$J$2:$J$401,MATCH(1,INDEX(('Senior Faculty'!$K$2:$K$401=$B$1)*('Senior Faculty'!$N$2:$N$401=1),0),0)),"")} -> Dr. Al Amin Sheikh | C7: {=IFERROR(INDEX('Senior Faculty'!$L$2:$L$401,MATCH(1,INDEX(('Senior Faculty'!$K$2:$K$401=$B$1)*('Senior Faculty'!$N$2:$N$401=1),0),0))&"","")} -> taskia.khatun@ulab.edu.bd | D7: {=IFERROR(INDEX('Senior Faculty'!$M$2:$M$401,MATCH(1,INDEX(('Senior Faculty'!$K$2:$K$401=$B$1)*('Senior Faculty'!$N$2:$N$401=1),0),0))&"","")} -> 01701564663
A8: Rappoteur 1 | B8: {=IFERROR(INDEX('Junior Faculty'!$J$2:$J$401,MATCH(1,INDEX(('Junior Faculty'!$K$2:$K$401=$B$1)*('Junior Faculty'!$N$2:$N$401=1),0),0)),"")} -> Nazmul Abdal | C8: {=IFERROR(INDEX('Junior Faculty'!$L$2:$L$401,MATCH(1,INDEX(('Junior Faculty'!$K$2:$K$401=$B$1)*('Junior Faculty'!$N$2:$N$401=1),0),0))&"","")} -> nazmul.abdal@ulab.edu.bd | D8: {=IFERROR(INDEX('Junior Faculty'!$M$2:$M$401,MATCH(1,INDEX(('Junior Faculty'!$K$2:$K$401=$B$1)*('Junior Faculty'!$N$2:$N$401=1),0),0))&"","")} -> 01752813855
A9: Rappoteur 2 | B9: {=IFERROR(INDEX('Junior Faculty'!$J$2:$J$401,MATCH(1,INDEX(('Junior Faculty'!$K$2:$K$401=$B$1)*('Junior Faculty'!$N$2:$N$401=2),0),0)),"")} -> Foysal Ahmed | C9: {=IFERROR(INDEX('Junior Faculty'!$L$2:$L$401,MATCH(1,INDEX(('Junior Faculty'!$K$2:$K$401=$B$1)*('Junior Faculty'!$N$2:$N$401=2),0),0))&"","")} -> foysal.ahmed@ulab.edu.bd | D9: {=IFERROR(INDEX('Junior Faculty'!$M$2:$M$401,MATCH(1,INDEX(('Junior Faculty'!$K$2:$K$401=$B$1)*('Junior Faculty'!$N$2:$N$401=2),0),0))&"","")} -> 01632917360
A11: Papers
A12: ID | B12: Title | C12: Authors | E12: Emails | F12: Chair Score (/50)
A13: {=IFERROR(INDEX(Papers!$A$2:$A$201,MATCH(1,INDEX((Papers!$G$2:$G$201=$B$1)*(Papers!$I$2:$I$201=1),0),0)),"")} -> 94 | B13: {=IFERROR(INDEX(Papers!$C$2:$C$201,MATCH(1,INDEX((Papers!$G$2:$G$201=$B$1)*(Papers!$I$2:$I$201=1),0),0)),"")} -> TaxNet-Bangladesh: Building a Domain-Specific Tax Question-Answering System for Businesses in Bangladesh | C13: {=IFERROR(INDEX(Papers!$D$2:$D$201,MATCH(1,INDEX((Papers!$G$2:$G$201=$B$1)*(Papers!$I$2:$I$201=1),0),0)),"")} -> Raihan Kibria (University of Liberal Arts Bangladesh)*; Noshin Tabassum (University of Liberal Arts Bangladesh); Md. Nadimul Islam (University of Liberal Arts Bangladesh); Jannatul Ferdous Badhon (University of Liberal Arts Bangladesh); Monira Akter (University of Liberal Arts Bangladesh); MD KAVIUL HOSSAIN (University of Liberal Arts Bangladesh) | E13: {=IFERROR(INDEX(Papers!$E$2:$E$201,MATCH(1,INDEX((Papers!$G$2:$G$201=$B$1)*(Papers!$I$2:$I$201=1),0),0)),"")} -> raihan.kibria@ulab.edu.bd; noshin.tabassum.cse@ulab.edu.bd; nadimul.islam.cse@ulab.edu.bd; jannatul.ferdous3.cse@ulab.edu.bd; monira.akter.cse@ulab.edu.bd; kaviul.hossain@ulab.edu.bd
A14: {=IFERROR(INDEX(Papers!$A$2:$A$201,MATCH(1,INDEX((Papers!$G$2:$G$201=$B$1)*(Papers!$I$2:$I$201=2),0),0)),"")} -> 162 | B14: {=IFERROR(INDEX(Papers!$C$2:$C$201,MATCH(1,INDEX((Papers!$G$2:$G$201=$B$1)*(Papers!$I$2:$I$201=2),0),0)),"")} -> Distributed Transformer Inference for Sentiment Analysis: An HTCondor and DAGMan-Based Workflow Approach on AWS | C14: {=IFERROR(INDEX(Papers!$D$2:$D$201,MATCH(1,INDEX((Papers!$G$2:$G$201=$B$1)*(Papers!$I$2:$I$201=2),0),0)),"")} -> MD KAVIUL HOSSAIN (University of Liberal Arts Bangladesh); Nasir Uddin Ahmed (University of Liberal Arts Bangladesh)*; Fatema Khan (University of Liberal Arts Bangladesh) | E14: {=IFERROR(INDEX(Papers!$E$2:$E$201,MATCH(1,INDEX((Papers!$G$2:$G$201=$B$1)*(Papers!$I$2:$I$201=2),0),0)),"")} -> kaviul.hossain@ulab.edu.bd; nasir.uddin1@ulab.edu.bd; fatema.khan@ulab.edu.bd
A15: {=IFERROR(INDEX(Papers!$A$2:$A$201,MATCH(1,INDEX((Papers!$G$2:$G$201=$B$1)*(Papers!$I$2:$I$201=3),0),0)),"")} -> 217 | B15: {=IFERROR(INDEX(Papers!$C$2:$C$201,MATCH(1,INDEX((Papers!$G$2:$G$201=$B$1)*(Papers!$I$2:$I$201=3),0),0)),"")} -> AFDM-Aided PD-NOMA with Dynamic Power Allocation for High-Mobility THz Communications | C15: {=IFERROR(INDEX(Papers!$D$2:$D$201,MATCH(1,INDEX((Papers!$G$2:$G$201=$B$1)*(Papers!$I$2:$I$201=3),0),0)),"")} -> Md. Maharaj Kabir (Khulna University); Mohammad Ismat Kadir (Khulna University)* | E15: {=IFERROR(INDEX(Papers!$E$2:$E$201,MATCH(1,INDEX((Papers!$G$2:$G$201=$B$1)*(Papers!$I$2:$I$201=3),0),0)),"")} -> msc250909@ku.ac.bd; ismat.kadir@ece.ku.ac.bd
A16: {=IFERROR(INDEX(Papers!$A$2:$A$201,MATCH(1,INDEX((Papers!$G$2:$G$201=$B$1)*(Papers!$I$2:$I$201=4),0),0)),"")} | B16: {=IFERROR(INDEX(Papers!$C$2:$C$201,MATCH(1,INDEX((Papers!$G$2:$G$201=$B$1)*(Papers!$I$2:$I$201=4),0),0)),"")} | C16: {=IFERROR(INDEX(Papers!$D$2:$D$201,MATCH(1,INDEX((Papers!$G$2:$G$201=$B$1)*(Papers!$I$2:$I$201=4),0),0)),"")} | E16: {=IFERROR(INDEX(Papers!$E$2:$E$201,MATCH(1,INDEX((Papers!$G$2:$G$201=$B$1)*(Papers!$I$2:$I$201=4),0),0)),"")}
A17: {=IFERROR(INDEX(Papers!$A$2:$A$201,MATCH(1,INDEX((Papers!$G$2:$G$201=$B$1)*(Papers!$I$2:$I$201=5),0),0)),"")} | B17: {=IFERROR(INDEX(Papers!$C$2:$C$201,MATCH(1,INDEX((Papers!$G$2:$G$201=$B$1)*(Papers!$I$2:$I$201=5),0),0)),"")} | C17: {=IFERROR(INDEX(Papers!$D$2:$D$201,MATCH(1,INDEX((Papers!$G$2:$G$201=$B$1)*(Papers!$I$2:$I$201=5),0),0)),"")} | E17: {=IFERROR(INDEX(Papers!$E$2:$E$201,MATCH(1,INDEX((Papers!$G$2:$G$201=$B$1)*(Papers!$I$2:$I$201=5),0),0)),"")}
A18: {=IFERROR(INDEX(Papers!$A$2:$A$201,MATCH(1,INDEX((Papers!$G$2:$G$201=$B$1)*(Papers!$I$2:$I$201=6),0),0)),"")} | B18: {=IFERROR(INDEX(Papers!$C$2:$C$201,MATCH(1,INDEX((Papers!$G$2:$G$201=$B$1)*(Papers!$I$2:$I$201=6),0),0)),"")} | C18: {=IFERROR(INDEX(Papers!$D$2:$D$201,MATCH(1,INDEX((Papers!$G$2:$G$201=$B$1)*(Papers!$I$2:$I$201=6),0),0)),"")} | E18: {=IFERROR(INDEX(Papers!$E$2:$E$201,MATCH(1,INDEX((Papers!$G$2:$G$201=$B$1)*(Papers!$I$2:$I$201=6),0),0)),"")}
A19: {=IFERROR(INDEX(Papers!$A$2:$A$201,MATCH(1,INDEX((Papers!$G$2:$G$201=$B$1)*(Papers!$I$2:$I$201=7),0),0)),"")} | B19: {=IFERROR(INDEX(Papers!$C$2:$C$201,MATCH(1,INDEX((Papers!$G$2:$G$201=$B$1)*(Papers!$I$2:$I$201=7),0),0)),"")} | C19: {=IFERROR(INDEX(Papers!$D$2:$D$201,MATCH(1,INDEX((Papers!$G$2:$G$201=$B$1)*(Papers!$I$2:$I$201=7),0),0)),"")} | E19: {=IFERROR(INDEX(Papers!$E$2:$E$201,MATCH(1,INDEX((Papers!$G$2:$G$201=$B$1)*(Papers!$I$2:$I$201=7),0),0)),"")}
A20: {=IFERROR(INDEX(Papers!$A$2:$A$201,MATCH(1,INDEX((Papers!$G$2:$G$201=$B$1)*(Papers!$I$2:$I$201=8),0),0)),"")} | B20: {=IFERROR(INDEX(Papers!$C$2:$C$201,MATCH(1,INDEX((Papers!$G$2:$G$201=$B$1)*(Papers!$I$2:$I$201=8),0),0)),"")} | C20: {=IFERROR(INDEX(Papers!$D$2:$D$201,MATCH(1,INDEX((Papers!$G$2:$G$201=$B$1)*(Papers!$I$2:$I$201=8),0),0)),"")} | E20: {=IFERROR(INDEX(Papers!$E$2:$E$201,MATCH(1,INDEX((Papers!$G$2:$G$201=$B$1)*(Papers!$I$2:$I$201=8),0),0)),"")}

Sheet T1P3
A1: Session | B1: T1P3
A2: Session Title | B2: {=IFERROR(INDEX(Sessions!$C$2:$C$173,MATCH($B$1,Sessions!$B$2:$B$173,0))&"","")} -> Wireless Networks and Optical Communication Systems
A3: Session Time | B3: =IF(LEFT($B$1,2)="T1",Schedule!$A$4&", "&Schedule!$A$10,IF(LEFT($B$1,2)="T2",Schedule!$A$4&", "&Schedule!$A$12,IF(LEFT($B$1,2)="T3",Schedule!$A$4&", "&#REF!,IF(LEFT($B$1,2)="T4",Schedule!$A$16&", "&Schedule!$A$18,IF($B$1="Keynote 1",Schedule!$A$4&", "&Schedule!$A$8,IF($B$1="Keynote 2",Schedule!$A$4&", "&Schedule!$A$13,IF($B$1="Keynote 3",Schedule!$A$16&", "&Schedule!$A$19,IF($B$1="IEEE Workshop",Schedule!$A$16&", "&#REF!,"")))))))) -> Day 1, 11:40-12:40
A4: Session Room | B4: PD103
A5: Session Chair 1 | B5: {=IFERROR(INDEX(Chairs!$J$2:$J$359,MATCH(1,INDEX((Chairs!$K$2:$K$359=$B$1)*(Chairs!$N$2:$N$359=1),0),0)),"")} -> Dr. Nahid Akhter Jahan | C5: {=IFERROR(INDEX(Chairs!$L$2:$L$359,MATCH(1,INDEX((Chairs!$K$2:$K$359=$B$1)*(Chairs!$N$2:$N$359=1),0),0))&"","")} -> nahid.jahan@bracu.ac.bd | D5: {=IFERROR(INDEX(Chairs!$M$2:$M$359,MATCH(1,INDEX((Chairs!$K$2:$K$359=$B$1)*(Chairs!$N$2:$N$359=1),0),0))&"","")} -> 01828141026
A6: Session Chair 2 | B6: Dr. Mohammad Rifat Ahmmad Rashid | C6: rifat.rashid@ewubd.edu | D6: 1314447616
A7: Session Moderator | B7: {=IFERROR(INDEX('Senior Faculty'!$J$2:$J$401,MATCH(1,INDEX(('Senior Faculty'!$K$2:$K$401=$B$1)*('Senior Faculty'!$N$2:$N$401=1),0),0)),"")} -> Md. Ashraful Haque, PhD | C7: {=IFERROR(INDEX('Senior Faculty'!$L$2:$L$401,MATCH(1,INDEX(('Senior Faculty'!$K$2:$K$401=$B$1)*('Senior Faculty'!$N$2:$N$401=1),0),0))&"","")} -> ashraful.haque1@ulab.edu.bd | D7: {=IFERROR(INDEX('Senior Faculty'!$M$2:$M$401,MATCH(1,INDEX(('Senior Faculty'!$K$2:$K$401=$B$1)*('Senior Faculty'!$N$2:$N$401=1),0),0))&"","")} -> 01745323543
A8: Rappoteur 1 | B8: {=IFERROR(INDEX('Junior Faculty'!$J$2:$J$401,MATCH(1,INDEX(('Junior Faculty'!$K$2:$K$401=$B$1)*('Junior Faculty'!$N$2:$N$401=1),0),0)),"")} -> Fatema Khan | C8: {=IFERROR(INDEX('Junior Faculty'!$L$2:$L$401,MATCH(1,INDEX(('Junior Faculty'!$K$2:$K$401=$B$1)*('Junior Faculty'!$N$2:$N$401=1),0),0))&"","")} -> fatema.khan@ulab.edu.bd | D8: {=IFERROR(INDEX('Junior Faculty'!$M$2:$M$401,MATCH(1,INDEX(('Junior Faculty'!$K$2:$K$401=$B$1)*('Junior Faculty'!$N$2:$N$401=1),0),0))&"","")} -> 01781527079
A9: Rappoteur 2 | B9: {=IFERROR(INDEX('Junior Faculty'!$J$2:$J$401,MATCH(1,INDEX(('Junior Faculty'!$K$2:$K$401=$B$1)*('Junior Faculty'!$N$2:$N$401=2),0),0)),"")} -> Atanu Shuvam Roy | C9: {=IFERROR(INDEX('Junior Faculty'!$L$2:$L$401,MATCH(1,INDEX(('Junior Faculty'!$K$2:$K$401=$B$1)*('Junior Faculty'!$N$2:$N$401=2),0),0))&"","")} -> atanu.shuvam@ulab.edu.bd | D9: {=IFERROR(INDEX('Junior Faculty'!$M$2:$M$401,MATCH(1,INDEX(('Junior Faculty'!$K$2:$K$401=$B$1)*('Junior Faculty'!$N$2:$N$401=2),0),0))&"","")} -> 01937545261
A11: Papers
A12: ID | B12: Title | C12: Authors | E12: Emails | F12: Chair Score (/50)
A13: {=IFERROR(INDEX(Papers!$A$2:$A$201,MATCH(1,INDEX((Papers!$G$2:$G$201=$B$1)*(Papers!$I$2:$I$201=1),0),0)),"")} -> 33 | B13: {=IFERROR(INDEX(Papers!$C$2:$C$201,MATCH(1,INDEX((Papers!$G$2:$G$201=$B$1)*(Papers!$I$2:$I$201=1),0),0)),"")} -> Performance Analysis of RIS-Assisted 6G Wireless Systems with Hybrid Architectures and Hardware Constraints | C13: {=IFERROR(INDEX(Papers!$D$2:$D$201,MATCH(1,INDEX((Papers!$G$2:$G$201=$B$1)*(Papers!$I$2:$I$201=1),0),0)),"")} -> Md Hossam-E-Haider (Military Institute of Science & Technology); Md. Rafiul Islam Talukder (Military Institute of Science & Technology); Md. Mehedi Hasan Khan Apurbo (Military Institute of Science & Technology); Samia Rahman (Military Institute of Science & Technology )*; Nusrat Jahan Neela Monika (Military Institute of Science & Technology) | E13: {=IFERROR(INDEX(Papers!$E$2:$E$201,MATCH(1,INDEX((Papers!$G$2:$G$201=$B$1)*(Papers!$I$2:$I$201=1),0),0)),"")} -> haider@eece.mist.ac.bd; rafiulriad44@gmail.com; apurpohossain472@gmail.com; rsamia5594@gmail.com; nusratnila204@gmail.com
A14: {=IFERROR(INDEX(Papers!$A$2:$A$201,MATCH(1,INDEX((Papers!$G$2:$G$201=$B$1)*(Papers!$I$2:$I$201=2),0),0)),"")} -> 116 | B14: {=IFERROR(INDEX(Papers!$C$2:$C$201,MATCH(1,INDEX((Papers!$G$2:$G$201=$B$1)*(Papers!$I$2:$I$201=2),0),0)),"")} -> Novel Microstrip-fed Implantable Antenna Design Operating at 5.85 GHz for Medical Applications | C14: {=IFERROR(INDEX(Papers!$D$2:$D$201,MATCH(1,INDEX((Papers!$G$2:$G$201=$B$1)*(Papers!$I$2:$I$201=2),0),0)),"")} -> Dr. Mohammad Khan (North South University)*; Sadman Ishraq (North South University); MA Sheam (North South University); Ayatullah Hasnat Behesti (North South University) | E14: {=IFERROR(INDEX(Papers!$E$2:$E$201,MATCH(1,INDEX((Papers!$G$2:$G$201=$B$1)*(Papers!$I$2:$I$201=2),0),0)),"")} -> monirkhan.qmul@gmail.com; sadman.ishraq@northsouth.edu; sheam1720@gmail.com; ayatullah.behesti@northsouth.edu
A15: {=IFERROR(INDEX(Papers!$A$2:$A$201,MATCH(1,INDEX((Papers!$G$2:$G$201=$B$1)*(Papers!$I$2:$I$201=3),0),0)),"")} -> 136 | B15: {=IFERROR(INDEX(Papers!$C$2:$C$201,MATCH(1,INDEX((Papers!$G$2:$G$201=$B$1)*(Papers!$I$2:$I$201=3),0),0)),"")} -> An X-Band 2×2 MIMO Antenna Array with Enhanced Beamforming and Radiation Performance | C15: {=IFERROR(INDEX(Papers!$D$2:$D$201,MATCH(1,INDEX((Papers!$G$2:$G$201=$B$1)*(Papers!$I$2:$I$201=3),0),0)),"")} -> Sohanur Sohag (Uttara University )*; Anoy Roy (Chittagong university of engineering and technology); Rahul Barua (National University); Nea Jaw Rakhine (University of Chittagong); Md. Rakib Uddin (Uttara University); Md. Ashraful Haque (University of Liberal Arts Bangladesh ) | E15: {=IFERROR(INDEX(Papers!$E$2:$E$201,MATCH(1,INDEX((Papers!$G$2:$G$201=$B$1)*(Papers!$I$2:$I$201=3),0),0)),"")} -> sohanur.rs1@uttarauniversity.edu.bd; anoyroy.eee@gmail.com; rahulbarua349@gmail.com; neajawrakhine@gmail.com; rakibuddin2202@gmail.com; limon.ashraf@gmail.com
A16: {=IFERROR(INDEX(Papers!$A$2:$A$201,MATCH(1,INDEX((Papers!$G$2:$G$201=$B$1)*(Papers!$I$2:$I$201=4),0),0)),"")} | B16: {=IFERROR(INDEX(Papers!$C$2:$C$201,MATCH(1,INDEX((Papers!$G$2:$G$201=$B$1)*(Papers!$I$2:$I$201=4),0),0)),"")} | C16: {=IFERROR(INDEX(Papers!$D$2:$D$201,MATCH(1,INDEX((Papers!$G$2:$G$201=$B$1)*(Papers!$I$2:$I$201=4),0),0)),"")} | E16: {=IFERROR(INDEX(Papers!$E$2:$E$201,MATCH(1,INDEX((Papers!$G$2:$G$201=$B$1)*(Papers!$I$2:$I$201=4),0),0)),"")}
A17: {=IFERROR(INDEX(Papers!$A$2:$A$201,MATCH(1,INDEX((Papers!$G$2:$G$201=$B$1)*(Papers!$I$2:$I$201=5),0),0)),"")} | B17: {=IFERROR(INDEX(Papers!$C$2:$C$201,MATCH(1,INDEX((Papers!$G$2:$G$201=$B$1)*(Papers!$I$2:$I$201=5),0),0)),"")} | C17: {=IFERROR(INDEX(Papers!$D$2:$D$201,MATCH(1,INDEX((Papers!$G$2:$G$201=$B$1)*(Papers!$I$2:$I$201=5),0),0)),"")} | E17: {=IFERROR(INDEX(Papers!$E$2:$E$201,MATCH(1,INDEX((Papers!$G$2:$G$201=$B$1)*(Papers!$I$2:$I$201=5),0),0)),"")}
A18: {=IFERROR(INDEX(Papers!$A$2:$A$201,MATCH(1,INDEX((Papers!$G$2:$G$201=$B$1)*(Papers!$I$2:$I$201=6),0),0)),"")} | B18: {=IFERROR(INDEX(Papers!$C$2:$C$201,MATCH(1,INDEX((Papers!$G$2:$G$201=$B$1)*(Papers!$I$2:$I$201=6),0),0)),"")} | C18: {=IFERROR(INDEX(Papers!$D$2:$D$201,MATCH(1,INDEX((Papers!$G$2:$G$201=$B$1)*(Papers!$I$2:$I$201=6),0),0)),"")} | E18: {=IFERROR(INDEX(Papers!$E$2:$E$201,MATCH(1,INDEX((Papers!$G$2:$G$201=$B$1)*(Papers!$I$2:$I$201=6),0),0)),"")}
